Workbook

Sheet Зачернение
A1: Схемы зачернений (проведение предупредительных противопаводковых мероприятий по ослаблению прочности льда на затороопасных участках рек)
A2: № | B2: Наименование защищаемого населенного пункта | C2: Дата (дд.мм.гггг) | D2: Наименование реки | E2: Наименование района | F2: Наименование населенного пункта | G2: ОКТМО | H2: Количество полос | I2: Ширина, м | J2: Протяженность, м | K2: Площадь, м2 | L2: Объем зачерняющего материала, м3 | M2: Глубина протаивания льда, см | N2: Геопозиция (широта) | O2: Геопозиция (долгота) | P2: Местность | Q2: Ответственный
A3: 1 | B3: =VLOOKUP(G3,ОКТМО!B:M,12,0) -> Чагда | D3: Алдан | E3: =VLOOKUP(G3,ОКТМО!B:M,6,0) -> Алданский муниципальный район | F3: =VLOOKUP(G3,ОКТМО!B:M,12,0) -> Чагда | G3: 98603460101 | H3: 2 | I3: 20 | J3: 1000 | K3: =I3*J3*H3 -> 40000 | L3: 80 | N3: 58.72149334 | O3: 130.61732873 | P3: выше н.п. Чагда | Q3: ЛБВУ ФАВР
A4: 2 | B4: =VLOOKUP(G4,ОКТМО!B:M,12,0) -> Чагда | D4: Алдан | E4: =VLOOKUP(G4,ОКТМО!B:M,6,0) -> Алданский муниципальный район | F4: =VLOOKUP(G4,ОКТМО!B:M,12,0) -> Чагда | G4: 98603460101 | H4: 2 | I4: 20 | J4: 1000 | K4: =I4*J4*H4 -> 40000 | L4: 80 | N4: 58.78355898 | O4: 130.60016259 | P4: у о. Первомайский | Q4: ЛБВУ ФАВР
A5: 3 | B5: =VLOOKUP(G5,ОКТМО!B:M,12,0) -> Белькачи | D5: Алдан | E5: =VLOOKUP(G5,ОКТМО!B:M,6,0) -> Усть-Майский муниципальный район | F5: =VLOOKUP(G5,ОКТМО!B:M,12,0) -> Белькачи | G5: 98654405101 | H5: 2 | I5: 20 | J5: 2000 | K5: =I5*J5*H5 -> 80000 | L5: 160 | N5: 59.14552075 | O5: 131.93019208 | P5: у о. Бур-Ары | Q5: ЛБВУ ФАВР
A6: 4 | B6: =VLOOKUP(G6,ОКТМО!B:M,12,0) -> Белькачи | D6: Алдан | E6: =VLOOKUP(G6,ОКТМО!B:M,6,0) -> Усть-Майский муниципальный район | F6: =VLOOKUP(G6,ОКТМО!B:M,12,0) -> Белькачи | G6: 98654405101 | H6: 2 | I6: 20 | J6: 1000 | K6: =I6*J6*H6 -> 40000 | L6: 80 | N6: 59.14481644 | O6: 132.07095441 | P6: в 12км ниже н.п. Белькачи | Q6: ЛБВУ ФАВР
A7: 5 | B7: =VLOOKUP(G7,ОКТМО!B:M,12,0) -> Эжанцы | D7: Алдан | E7: =VLOOKUP(G7,ОКТМО!B:M,6,0) -> Усть-Майский муниципальный район | F7: =VLOOKUP(G7,ОКТМО!B:M,12,0) -> Эжанцы | G7: 98654425101 | H7: 2 | I7: 20 | J7: 2000 | K7: =I7*J7*H7 -> 80000 | L7: 160 | N7: 60.50585294 | O7: 135.10204457 | P7: ниже н.п. Эжанцы | Q7: ЛБВУ ФАВР
A8: 6 | B8: =VLOOKUP(G8,ОКТМО!B:M,12,0) -> Кюпцы | D8: Алдан | E8: =VLOOKUP(G8,ОКТМО!B:M,6,0) -> Усть-Майский муниципальный район | F8: =VLOOKUP(G8,ОКТМО!B:M,12,0) -> Кюпцы | G8: 98654410101 | H8: 2 | I8: 20 | J8: 2200 | K8: =I8*J8*H8 -> 88000 | L8: 176 | N8: 60.89963345 | O8: 135.35176073 | P8: у о. Тит-Ары | Q8: ЛБВУ ФАВР
A9: 7 | B9: =VLOOKUP(G9,ОКТМО!B:M,12,0) -> Кюпцы | D9: Алдан | E9: =VLOOKUP(G9,ОКТМО!B:M,6,0) -> Усть-Майский муниципальный район | F9: =VLOOKUP(G9,ОКТМО!B:M,12,0) -> Кюпцы | G9: 98654410101 | H9: 2 | I9: 20 | J9: 1000 | K9: =I9*J9*H9 -> 40000 | L9: 80 | N9: 61.00061654 | O9: 135.43085347 | P9: у пер. Ноторские острова | Q9: ЛБВУ ФАВР
A10: 8 | B10: =VLOOKUP(G10,ОКТМО!B:M,12,0) -> Кюпцы | D10: Алдан | E10: =VLOOKUP(G10,ОКТМО!B:M,6,0) -> Усть-Майский муниципальный район | F10: =VLOOKUP(G10,ОКТМО!B:M,12,0) -> Кюпцы | G10: 98654410101 | H10: 2 | I10: 20 | J10: 1500 | K10: =I10*J10*H10 -> 60000 | L10: 120 | N10: 61.09484956 | O10: 135.50089132 | P10: у о. Улахан Отоннуур | Q10: ЛБВУ ФАВР
A11: 9 | B11: =VLOOKUP(G11,ОКТМО!B:M,12,0) -> Кюпцы | D11: Алдан | E11: =VLOOKUP(G11,ОКТМО!B:M,6,0) -> Усть-Майский муниципальный район | F11: =VLOOKUP(G11,ОКТМО!B:M,12,0) -> Кюпцы | G11: 98654410101 | H11: 2 | I11: 20 | J11: 1500 | K11: =I11*J11*H11 -> 60000 | L11: 120 | N11: 61.32250202 | O11: 135.49728129 | P11: уч. Сымнар | Q11: ЛБВУ ФАВР
A12: 10 | B12: =VLOOKUP(G12,ОКТМО!B:M,12,0) -> Хандыга | D12: Алдан | E12: =VLOOKUP(G12,ОКТМО!B:M,6,0) -> Томпонский муниципальный район | F12: =VLOOKUP(G12,ОКТМО!B:M,12,0) -> Хандыга | G12: 98650151051 | H12: 2 | I12: 20 | J12: 1000 | K12: =I12*J12*H12 -> 40000 | L12: 40 | N12: 62.59919178 | O12: 135.27743823 | P12: у о. Арга (перекат Собачий) | Q12: ЛБВУ ФАВР
A13: 11 | B13: =VLOOKUP(G13,ОКТМО!B:M,12,0) -> Хандыга | D13: Алдан | E13: =VLOOKUP(G13,ОКТМО!B:M,6,0) -> Томпонский муниципальный район | F13: =VLOOKUP(G13,ОКТМО!B:M,12,0) -> Хандыга | G13: 98650151051 | H13: 2 | I13: 20 | J13: 1000 | K13: =I13*J13*H13 -> 40000 | L13: 40 | N13: 62.58243892 | O13: 135.21014697 | P13: у о. Арга (перекат Собачий) | Q13: ЛБВУ ФАВР
A14: 12 | B14: =VLOOKUP(G14,ОКТМО!B:M,12,0) -> Кескил | D14: Алдан | E14: =VLOOKUP(G14,ОКТМО!B:M,6,0) -> Томпонский муниципальный район | F14: =VLOOKUP(G14,ОКТМО!B:M,12,0) -> Кескил | G14: 98650430101 | H14: 2 | I14: 20 | J14: 1500 | K14: =I14*J14*H14 -> 60000 | L14: 60 | N14: 62.68549287 | O14: 134.72297199 | P14: у о. Маган | Q14: ЛБВУ ФАВР
... A16: 14 | B16: =VLOOKUP(G16,ОКТМО!B:M,12,0) -> Хара-Алдан | D16: Алдан | E16: =VLOOKUP(G16,ОКТМО!B:M,6,0) -> Таттинский муниципальный район | F16: =VLOOKUP(G16,ОКТМО!B:M,12,0) -> Хара-Алдан | G16: 98604465101 | H16: 2 | I16: 20 | J16: 2000 | K16: =I16*J16*H16 -> 80000 | L16: 80 | N16: 63.34089060 | O16: 133.26350696 | P16: в 8 км. ниже с. Хара-Алдан | Q16: ЛБВУ ФАВР
A17: 15 | B17: =VLOOKUP(G17,ОКТМО!B:M,12,0) -> Сыгыннах | D17: Алдан | E17: =VLOOKUP(G17,ОКТМО!B:M,6,0) -> Намский муниципальный район | F17: =VLOOKUP(G17,ОКТМО!B:M,12,0) -> Сыгыннах | G17: 98635405101 | H17: 2 | I17: 20 | J17: 2000 | K17: =I17*J17*H17 -> 80000 | L17: NULL | N17: 63.45301846 | O17: 129.57625695 | P17: у о. Ходжох | Q17: ЛБВУ ФАВР
A18: 16 | B18: =VLOOKUP(G18,ОКТМО!B:M,12,0) -> Сыгыннах | D18: Алдан | E18: =VLOOKUP(G18,ОКТМО!B:M,6,0) -> Намский муниципальный район | F18: =VLOOKUP(G18,ОКТМО!B:M,12,0) -> Сыгыннах | G18: 98635405101 | H18: 2 | I18: 20 | J18: 2000 | K18: =I18*J18*H18 -> 80000 | L18: NULL | N18: 63.41831961 | O18: 129.71616098 | P18: у о. Сис-Кумах | Q18: ЛБВУ ФАВР
A19: 17 | B19: =VLOOKUP(G19,ОКТМО!B:M,12,0) -> Сыгыннах | D19: Алдан | E19: =VLOOKUP(G19,ОКТМО!B:M,6,0) -> Намский муниципальный район | F19: =VLOOKUP(G19,ОКТМО!B:M,12,0) -> Сыгыннах | G19: 98635405101 | H19: 2 | I19: 20 | J19: 2000 | K19: =I19*J19*H19 -> 80000 | L19: NULL | N19: 63.41463231 | O19: 129.98343774 | P19: у о. Ого-Унуохтаах | Q19: ЛБВУ ФАВР
A20: 18 | B20: =VLOOKUP(G20,ОКТМО!B:M,12,0) -> Верхняя Амга | D20: Амга | E20: =VLOOKUP(G20,ОКТМО!B:M,6,0) -> Алданский муниципальный район | F20: =VLOOKUP(G20,ОКТМО!B:M,12,0) -> Верхняя Амга | G20: 98603105111 | H20: 2 | I20: 20 | J20: 2000 | K20: =I20*J20*H20 -> 80000 | L20: NULL | N20: 59.65822343 | O20: 127.10953626 | P20: р. Курум Кюнкю | Q20: ЛБВУ ФАВР
A21: 19 | B21: =VLOOKUP(G21,ОКТМО!B:M,12,0) -> Верхняя Амга | D21: Амга | E21: =VLOOKUP(G21,ОКТМО!B:M,6,0) -> Алданский муниципальный район | F21: =VLOOKUP(G21,ОКТМО!B:M,12,0) -> Верхняя Амга | G21: 98603105111 | H21: 2 | I21: 20 | J21: 2000 | K21: =I21*J21*H21 -> 80000 | L21: NULL | N21: 59.63037606 | O21: 127.17408094 | P21: р. Курум Арыта | Q21: ЛБВУ ФАВР
A22: 20 | B22: =VLOOKUP(G22,ОКТМО!B:M,12,0) -> Амга | D22: Амга | E22: =VLOOKUP(G22,ОКТМО!B:M,6,0) -> Амгинский муниципальный район | F22: =VLOOKUP(G22,ОКТМО!B:M,12,0) -> Амга | G22: 98608432101 | H22: 2 | I22: 20 | J22: 2000 | K22: =I22*J22*H22 -> 80000 | L22: NULL | N22: 60.85311468 | O22: 131.92317407 | P22: о. Ус-Уэстэх | Q22: ЛБВУ ФАВР
A23: 21 | B23: =VLOOKUP(G23,ОКТМО!B:M,12,0) -> Амга | D23: Амга | E23: =VLOOKUP(G23,ОКТМО!B:M,6,0) -> Амгинский муниципальный район | F23: =VLOOKUP(G23,ОКТМО!B:M,12,0) -> Амга | G23: =98608432101 -> 98608432101 | H23: 2 | I23: 20 | J23: 2000 | K23: =I23*J23*H23 -> 80000 | L23: NULL | N23: 60.86874549 | O23: 132.00883310 | P23: о. Молода | Q23: ЛБВУ ФАВР
A24: 22 | B24: =VLOOKUP(G24,ОКТМО!B:M,12,0) -> Бетюнцы | D24: Амга | E24: =VLOOKUP(G24,ОКТМО!B:M,6,0) -> Амгинский муниципальный район | F24: =VLOOKUP(G24,ОКТМО!B:M,12,0) -> Бетюнцы | G24: 98608440101 | H24: 2 | I24: 20 | J24: 2000 | K24: =I24*J24*H24 -> 80000 | L24: NULL | N24: 60.90707963 | O24: 132.21671503 | P24: о. Уорай (Невезения) | Q24: ЛБВУ ФАВР
A25: 23 | B25: =VLOOKUP(G25,ОКТМО!B:M,12,0) -> Абага | D25: Амга | E25: =VLOOKUP(G25,ОКТМО!B:M,6,0) -> Амгинский муниципальный район | F25: =VLOOKUP(G25,ОКТМО!B:M,12,0) -> Абага | G25: 98608405101 | H25: 2 | I25: 20 | J25: 2000 | K25: =I25*J25*H25 -> 80000 | L25: NULL | N25: 61.00999419 | O25: 132.42828767 | P25: Харчы Хайата | Q25: ЛБВУ ФАВР
A26: 24 | B26: =VLOOKUP(G26,ОКТМО!B:M,12,0) -> Михайловка | D26: Амга | E26: =VLOOKUP(G26,ОКТМО!B:M,6,0) -> Амгинский муниципальный район | F26: =VLOOKUP(G26,ОКТМО!B:M,12,0) -> Михайловка | G26: 98608460101 | H26: 2 | I26: 20 | J26: 1500 | K26: =I26*J26*H26 -> 60000 | L26: NULL | N26: 61.21052784 | O26: 132.60715883 | P26: р. Ксенофонт Арыта | Q26: ЛБВУ ФАВР
A27: 25 | B27: =VLOOKUP(G27,ОКТМО!B:M,12,0) -> Мындагай | D27: Амга | E27: =VLOOKUP(G27,ОКТМО!B:M,6,0) -> Чурапчинский муниципальный район | F27: =VLOOKUP(G27,ОКТМО!B:M,12,0) -> Мындагай | G27: 98658415101 | H27: 2 | I27: 20 | J27: 2000 | K27: =I27*J27*H27 -> 80000 | L27: NULL | N27: 61.66781163 | O27: 133.26530855 | P27: о. Уолала | Q27: ЛБВУ ФАВР
A28: 26 | B28: =VLOOKUP(G28,ОКТМО!B:M,12,0) -> Мындагай | D28: Амга | E28: =VLOOKUP(G28,ОКТМО!B:M,6,0) -> Чурапчинский муниципальный район | F28: =VLOOKUP(G28,ОКТМО!B:M,12,0) -> Мындагай | G28: 98658415101 | H28: 2 | I28: 20 | J28: 2000 | K28: =I28*J28*H28 -> 80000 | L28: NULL | N28: 61.70851855 | O28: 133.39233797 | P28: Моккуда | Q28: ЛБВУ ФАВР
A29: 27 | B29: =VLOOKUP(G29,ОКТМО!B:M,12,0) -> Мырыла | D29: Амга | E29: =VLOOKUP(G29,ОКТМО!B:M,6,0) -> Чурапчинский муниципальный район | F29: =VLOOKUP(G29,ОКТМО!B:M,12,0) -> Мырыла | G29: 98658435101 | H29: 2 | I29: 20 | J29: 4000 | K29: =I29*J29*H29 -> 160000 | L29: NULL | N29: 61.86336351 | O29: 133.67489259 | P29: Тэйэр Хайа | Q29: ЛБВУ ФАВР
A30: 28 | B30: =VLOOKUP(G30,ОКТМО!B:M,12,0) -> Чымнайи | D30: Амга | E30: =VLOOKUP(G30,ОКТМО!B:M,6,0) -> Таттинский муниципальный район | F30: =VLOOKUP(G30,ОКТМО!B:M,12,0) -> Чымнайи | G30: 98604460101 | H30: 2 | I30: 20 | J30: 2000 | K30: =I30*J30*H30 -> 80000 | L30: NULL | N30: 62.20163795 | O30: 134.68666475 | P30: о. Уодай | Q30: ЛБВУ ФАВР
A31: 29 | B31: =VLOOKUP(G31,ОКТМО!B:M,12,0) -> Орто-Нахара | D31: Нюя | E31: =VLOOKUP(G31,ОКТМО!B:M,6,0) -> Ленский муниципальный район | F31: =VLOOKUP(G31,ОКТМО!B:M,12,0) -> Орто-Нахара | G31: 98627433101 | H31: 2 | I31: 10 | J31: 1000 | K31: =I31*J31*H31 -> 20000 | L31: NULL | N31: 60.79993778 | O31: 114.43259638 | P31: в районе летника Киэнг-Юрях | Q31: ЛБВУ ФАВР
A32: 30 | B32: =VLOOKUP(G32,ОКТМО!B:M,12,0) -> Орто-Нахара | D32: Нюя | E32: =VLOOKUP(G32,ОКТМО!B:M,6,0) -> Ленский муниципальный район | F32: =VLOOKUP(G32,ОКТМО!B:M,12,0) -> Орто-Нахара | G32: 98627433101 | H32: 2 | I32: 10 | J32: 1000 | K32: =I32*J32*H32 -> 20000 | L32: NULL | N32: 60.82555406 | O32: 114.51568048 | P32: в районе МТФ «Захаровка» | Q32: ЛБВУ ФАВР
A33: 31 | B33: =VLOOKUP(G33,ОКТМО!B:M,12,0) -> Орто-Нахара | D33: Нюя | E33: =VLOOKUP(G33,ОКТМО!B:M,6,0) -> Ленский муниципальный район | F33: =VLOOKUP(G33,ОКТМО!B:M,12,0) -> Орто-Нахара | G33: 98627433101 | H33: 2 | I33: 10 | J33: 1000 | K33: =I33*J33*H33 -> 20000 | L33: NULL | N33: 60.82295988 | O33: 114.54091470 | P33: ниже участка №2 | Q33: ЛБВУ ФАВР
A34: 32 | B34: =VLOOKUP(G34,ОКТМО!B:M,12,0) -> Орто-Нахара | D34: Нюя | E34: =VLOOKUP(G34,ОКТМО!B:M,6,0) -> Ленский муниципальный район | F34: =VLOOKUP(G34,ОКТМО!B:M,12,0) -> Орто-Нахара | G34: 98627433101 | H34: 2 | I34: 10 | J34: 1000 | K34: =I34*J34*H34 -> 20000 | L34: NULL | N34: 60.81977963 | O34: 114.55928247 | P34: ниже участка №3 | Q34: ЛБВУ ФАВР
A35: 33 | B35: =VLOOKUP(G35,ОКТМО!B:M,12,0) -> Тяня | D35: Токко | E35: =VLOOKUP(G35,ОКТМО!B:M,6,0) -> Олекминский муниципальный район | F35: =VLOOKUP(G35,ОКТМО!B:M,12,0) -> Тяня | G35: 98641475101 | H35: 2 | I35: 20 | J35: 2000 | K35: =I35*J35*H35 -> 80000 | L35: NULL | N35: 59.07944229 | O35: 119.75873392 | P35: в 5,5 км от устья р. Тяня | Q35: ЛБВУ ФАВР
... A48: 46 | B48: =VLOOKUP(G48,ОКТМО!B:M,12,0) -> Якутск | D48: Лена | E48: =VLOOKUP(G48,ОКТМО!B:M,6,0) -> Городской округ Город Якутск | F48: =VLOOKUP(G48,ОКТМО!B:M,12,0) -> Якутск | G48: 98701000001 | H48: 3 | I48: 20 | J48: 1500 | K48: =I48*J48*H48 -> 90000 | L48: NULL | N48: 62.29527834 | O48: 130.07369440 | P48: Кангаласский мыс | Q48: ФИЛИАЛ "ЛЕНАРЕГИОНВОДХОЗ"
A49: 47 | B49: =VLOOKUP(G49,ОКТМО!B:M,12,0) -> Якутск | D49: Лена | E49: =VLOOKUP(G49,ОКТМО!B:M,6,0) -> Городской округ Город Якутск | F49: =VLOOKUP(G49,ОКТМО!B:M,12,0) -> Якутск | G49: 98701000001 | H49: NULL | I49: NULL | J49: 8000 | K49: NULL | L49: Распиловка | N49: 62.34439989 | O49: 130.05515497 | P49: Кангаласский мыс | Q49: ФИЛИАЛ "ЛЕНАРЕГИОНВОДХОЗ"
A50: 48 | B50: =VLOOKUP(G50,ОКТМО!B:M,12,0) -> Якутск | D50: Лена | E50: =VLOOKUP(G50,ОКТМО!B:M,6,0) -> Городской округ Город Якутск | F50: =VLOOKUP(G50,ОКТМО!B:M,12,0) -> Якутск | G50: 98701000001 | H50: 2 | I50: 20 | J50: 2000 | K50: =I50*J50*H50 -> 80000 | L50: NULL | N50: 62.36128680 | O50: 130.03730219 | P50: Кангаласский мыс | Q50: ФИЛИАЛ "ЛЕНАРЕГИОНВОДХОЗ"
A51: 49 | B51: =VLOOKUP(G51,ОКТМО!B:M,12,0) -> Ымыяхтах | D51: Лена | E51: =VLOOKUP(G51,ОКТМО!B:M,6,0) -> Намский муниципальный район | F51: =VLOOKUP(G51,ОКТМО!B:M,12,0) -> Ымыяхтах | G51: 98635415101 | H51: 3 | I51: 20 | J51: 3500 | K51: =I51*J51*H51 -> 210000 | L51: NULL | N51: 62.42889837 | O51: 129.98889368 | P51: у Буденновской протоки | Q51: ФИЛИАЛ "ЛЕНАРЕГИОНВОДХОЗ"
A52: 50 | B52: =VLOOKUP(G52,ОКТМО!B:M,12,0) -> Ымыяхтах | D52: Лена | E52: =VLOOKUP(G52,ОКТМО!B:M,6,0) -> Намский муниципальный район | F52: =VLOOKUP(G52,ОКТМО!B:M,12,0) -> Ымыяхтах | G52: 98635415101 | H52: NULL | I52: NULL | J52: 5000 | K52: NULL | L52: Распиловка | N52: 62.46145649 | O52: 129.98958032 | P52: у Буденновской протоки | Q52: ФИЛИАЛ "ЛЕНАРЕГИОНВОДХОЗ"
A53: 51 | B53: =VLOOKUP(G53,ОКТМО!B:M,12,0) -> Ымыяхтах | D53: Лена | E53: =VLOOKUP(G53,ОКТМО!B:M,6,0) -> Намский муниципальный район | F53: =VLOOKUP(G53,ОКТМО!B:M,12,0) -> Ымыяхтах | G53: 98635415101 | H53: NULL | I53: NULL | J53: 8000 | K53: NULL | L53: Распиловка | N53: 62.47954664 | O53: 129.99816339 | P53: у о. Делюсюннях | Q53: ФИЛИАЛ "ЛЕНАРЕГИОНВОДХОЗ"
A54: 52 | B54: =VLOOKUP(G54,ОКТМО!B:M,12,0) -> Ымыяхтах | D54: Лена | E54: =VLOOKUP(G54,ОКТМО!B:M,6,0) -> Намский муниципальный район | F54: =VLOOKUP(G54,ОКТМО!B:M,12,0) -> Ымыяхтах | G54: 98635415101 | H54: 3 | I54: 20 | J54: 1000 | K54: =I54*J54*H54 -> 60000 | L54: NULL | N54: 62.52567448 | O54: 130.00811975 | P54: ниже о. Делюсюннях | Q54: ФИЛИАЛ "ЛЕНАРЕГИОНВОДХОЗ"
A55: 53 | B55: =VLOOKUP(G55,ОКТМО!B:M,12,0) -> Партизан | D55: Лена | E55: =VLOOKUP(G55,ОКТМО!B:M,6,0) -> Намский муниципальный район | F55: =VLOOKUP(G55,ОКТМО!B:M,12,0) -> Партизан | G55: 98635435101 | H55: 3 | I55: 20 | J55: 4500 | K55: =I55*J55*H55 -> 270000 | L55: NULL | N55: 62.56271524 | O55: 129.89379327 | P55: у о. Ат-Арыыта | Q55: ФИЛИАЛ "ЛЕНАРЕГИОНВОДХОЗ"
A56: 54 | B56: =VLOOKUP(G56,ОКТМО!B:M,12,0) -> Партизан | D56: Лена | E56: =VLOOKUP(G56,ОКТМО!B:M,6,0) -> Намский муниципальный район | F56: =VLOOKUP(G56,ОКТМО!B:M,12,0) -> Партизан | G56: 98635435101 | H56: NULL | I56: NULL | J56: 6000 | K56: NULL | L56: Распиловка | N56: 62.58216690 | O56: 129.83645837 | P56: у о. Куолай(х) | Q56: ФИЛИАЛ "ЛЕНАРЕГИОНВОДХОЗ"
A57: 55 | B57: =VLOOKUP(G57,ОКТМО!B:M,12,0) -> Партизан | D57: Лена | E57: =VLOOKUP(G57,ОКТМО!B:M,6,0) -> Намский муниципальный район | F57: =VLOOKUP(G57,ОКТМО!B:M,12,0) -> Партизан | G57: 98635435101 | H57: 3 | I57: 20 | J57: 1000 | K57: =I57*J57*H57 -> 60000 | L57: NULL | N57: 62.61376847 | O57: 129.83611505 | P57: у о. Эселях-Ары | Q57: ФИЛИАЛ "ЛЕНАРЕГИОНВОДХОЗ"
A58: 56 | B58: =VLOOKUP(G58,ОКТМО!B:M,12,0) -> Партизан | D58: Лена | E58: =VLOOKUP(G58,ОКТМО!B:M,6,0) -> Намский муниципальный район | F58: =VLOOKUP(G58,ОКТМО!B:M,12,0) -> Партизан | G58: 98635435101 | H58: NULL | I58: NULL | J58: 4000 | K58: NULL | L58: Распиловка | N58: 62.62671540 | O58: 129.85156458 | P58: у о. Эселях-Ары | Q58: ФИЛИАЛ "ЛЕНАРЕГИОНВОДХОЗ"
A59: 57 | B59: =VLOOKUP(G59,ОКТМО!B:M,12,0) -> Партизан | D59: Лена | E59: =VLOOKUP(G59,ОКТМО!B:M,6,0) -> Намский муниципальный район | F59: =VLOOKUP(G59,ОКТМО!B:M,12,0) -> Партизан | G59: 98635435101 | H59: 3 | I59: 20 | J59: 3000 | K59: =I59*J59*H59 -> 180000 | L59: NULL | N59: 62.64943780 | O59: 129.86289423 | P59: у о. Эселях-Ары | Q59: ФИЛИАЛ "ЛЕНАРЕГИОНВОДХОЗ"
A60: 58 | B60: =VLOOKUP(G60,ОКТМО!B:M,12,0) -> Намцы | D60: Лена | E60: =VLOOKUP(G60,ОКТМО!B:M,6,0) -> Намский муниципальный район | F60: =VLOOKUP(G60,ОКТМО!B:M,12,0) -> Намцы | G60: 98635425101 | H60: NULL | I60: NULL | J60: 10000 | K60: NULL | L60: Распиловка | N60: 62.68931764 | O60: 129.83405512 | P60: у о. Ойо5ос-Ары | Q60: ФИЛИАЛ "ЛЕНАРЕГИОНВОДХОЗ"
A61: 59 | B61: =VLOOKUP(G61,ОКТМО!B:M,12,0) -> Намцы | D61: Лена | E61: =VLOOKUP(G61,ОКТМО!B:M,6,0) -> Намский муниципальный район | F61: =VLOOKUP(G61,ОКТМО!B:M,12,0) -> Намцы | G61: 98635425101 | H61: 3 | I61: 20 | J61: 5000 | K61: =I61*J61*H61 -> 300000 | L61: NULL | N61: 62.73244712 | O61: 129.77912347 | P61: у о. Ойо5ос-Ары | Q61: ФИЛИАЛ "ЛЕНАРЕГИОНВОДХОЗ"
A62: 60 | B62: =VLOOKUP(G62,ОКТМО!B:M,12,0) -> Графский Берег | D62: Лена | E62: =VLOOKUP(G62,ОКТМО!B:M,6,0) -> Намский муниципальный район | F62: =VLOOKUP(G62,ОКТМО!B:M,12,0) -> Графский Берег | G62: 98635455106 | H62: 3 | I62: 20 | J62: 3000 | K62: =I62*J62*H62 -> 180000 | L62: NULL | N62: 62.84837614 | O62: 129.76225104 | P62: у Песчаной Горы | Q62: ФИЛИАЛ "ЛЕНАРЕГИОНВОДХОЗ"
A63: 61 | B63: =VLOOKUP(G63,ОКТМО!B:M,12,0) -> Графский Берег | D63: Лена | E63: =VLOOKUP(G63,ОКТМО!B:M,6,0) -> Намский муниципальный район | F63: =VLOOKUP(G63,ОКТМО!B:M,12,0) -> Графский Берег | G63: 98635455106 | H63: 3 | I63: 20 | J63: 2000 | K63: =I63*J63*H63 -> 120000 | L63: NULL | N63: 62.90222267 | O63: 129.77117743 | P63: у о. Ханаластаах | Q63: ФИЛИАЛ "ЛЕНАРЕГИОНВОДХОЗ"
A64: 62 | B64: =VLOOKUP(G64,ОКТМО!B:M,12,0) -> Сангар | D64: Лена | E64: =VLOOKUP(G64,ОКТМО!B:M,6,0) -> Кобяйский муниципальный район | F64: =VLOOKUP(G64,ОКТМО!B:M,12,0) -> Сангар | G64: 98624151051 | H64: 3 | I64: 20 | J64: 2000 | K64: =I64*J64*H64 -> 120000 | L64: NULL | N64: 63.88523702 | O64: 127.51077518 | P64: у пгт. Сангар | Q64: ФИЛИАЛ "ЛЕНАРЕГИОНВОДХОЗ"
A65: 63 | B65: =VLOOKUP(G65,ОКТМО!B:M,12,0) -> Сангар | D65: Лена | E65: =VLOOKUP(G65,ОКТМО!B:M,6,0) -> Кобяйский муниципальный район | F65: =VLOOKUP(G65,ОКТМО!B:M,12,0) -> Сангар | G65: 98624151051 | H65: 3 | I65: 20 | J65: 2000 | K65: =I65*J65*H65 -> 120000 | L65: NULL | N65: 63.95240521 | O65: 127.41498813 | P65: у пгт. Сангар | Q65: ФИЛИАЛ "ЛЕНАРЕГИОНВОДХОЗ"
A66: 64 | B66: =VLOOKUP(G66,ОКТМО!B:M,12,0) -> Сангар | D66: Лена | E66: =VLOOKUP(G66,ОКТМО!B:M,6,0) -> Кобяйский муниципальный район | F66: =VLOOKUP(G66,ОКТМО!B:M,12,0) -> Сангар | G66: 98624151051 | H66: 3 | I66: 20 | J66: 2000 | K66: =I66*J66*H66 -> 120000 | L66: NULL | N66: 63.98796176 | O66: 127.30237827 | P66: у о. Улахан-Кубалах | Q66: ФИЛИАЛ "ЛЕНАРЕГИОНВОДХОЗ"
A67: 65 | B67: =VLOOKUP(G67,ОКТМО!B:M,12,0) -> Сангар | D67: Лена | E67: =VLOOKUP(G67,ОКТМО!B:M,6,0) -> Кобяйский муниципальный район | F67: =VLOOKUP(G67,ОКТМО!B:M,12,0) -> Сангар | G67: 98624151051 | H67: 3 | I67: 20 | J67: 2000 | K67: =I67*J67*H67 -> 120000 | L67: NULL | N67: 64.11310360 | O67: 126.97759494 | P67: у о. Кочуй | Q67: ФИЛИАЛ "ЛЕНАРЕГИОНВОДХОЗ"
A68: 66 | B68: =VLOOKUP(G68,ОКТМО!B:M,12,0) -> Сангар | D68: Лена | E68: =VLOOKUP(G68,ОКТМО!B:M,6,0) -> Кобяйский муниципальный район | F68: =VLOOKUP(G68,ОКТМО!B:M,12,0) -> Сангар | G68: 98624151051 | H68: 3 | I68: 20 | J68: 2000 | K68: =I68*J68*H68 -> 120000 | L68: NULL | N68: 64.14306611 | O68: 126.94944247 | P68: у переката Киси-Беляга | Q68: ФИЛИАЛ "ЛЕНАРЕГИОНВОДХОЗ"
A69: 67 | B69: =VLOOKUP(G69,ОКТМО!B:M,12,0) -> Зырянка | D69: Колыма | E69: =VLOOKUP(G69,ОКТМО!B:M,6,0) -> Верхнеколымский муниципальный район | F69: =VLOOKUP(G69,ОКТМО!B:M,12,0) -> Зырянка | G69: 98615151051 | H69: 2 | I69: 20 | J69: 1500 | K69: =I69*J69*H69 -> 60000 | L69: NULL | N69: 65.75808513 | O69: 150.88453159 | P69: выше о. Чукочаннах | Q69: ФИЛИАЛ "ЛЕНАРЕГИОНВОДХОЗ"
A70: 68 | B70: =VLOOKUP(G70,ОКТМО!B:M,12,0) -> Зырянка | D70: Колыма | E70: =VLOOKUP(G70,ОКТМО!B:M,6,0) -> Верхнеколымский муниципальный район | F70: =VLOOKUP(G70,ОКТМО!B:M,12,0) -> Зырянка | G70: 98615151051 | H70: 2 | I70: 20 | J70: 3000 | K70: =I70*J70*H70 -> 120000 | L70: NULL | N70: 65.79485076 | O70: 150.86393222 | P70: у о. Юнсюлях | Q70: ФИЛИАЛ "ЛЕНАРЕГИОНВОДХОЗ"
A71: 69 | B71: =VLOOKUP(G71,ОКТМО!B:M,12,0) -> Зырянка | D71: Ясачная | E71: =VLOOKUP(G71,ОКТМО!B:M,6,0) -> Верхнеколымский муниципальный район | F71: =VLOOKUP(G71,ОКТМО!B:M,12,0) -> Зырянка | G71: 98615151051 | H71: 1 | I71: 20 | J71: 2500 | K71: =I71*J71*H71 -> 50000 | L71: NULL | N71: 65.73033536 | O71: 150.84513530 | P71: у п. Верхнеколымск | Q71: ФИЛИАЛ "ЛЕНАРЕГИОНВОДХОЗ"
A72: 70 | B72: =VLOOKUP(G72,ОКТМО!B:M,12,0) -> Зырянка | D72: Ясачная | E72: =VLOOKUP(G72,ОКТМО!B:M,6,0) -> Верхнеколымский муниципальный район | F72: =VLOOKUP(G72,ОКТМО!B:M,12,0) -> Зырянка | G72: 98615151051 | H72: 2 | I72: 20 | J72: 2000 | K72: =I72*J72*H72 -> 80000 | L72: NULL | N72: 65.73061760 | O72: 150.88169917 | P72: начиная с участка «2 км» | Q72: ФИЛИАЛ "ЛЕНАРЕГИОНВОДХОЗ"
... A77: 75 | B77: =VLOOKUP(G77,ОКТМО!B:M,12,0) -> Среднеколымск | D77: Колыма | E77: =VLOOKUP(G77,ОКТМО!B:M,6,0) -> Среднеколымский муниципальный район | F77: =VLOOKUP(G77,ОКТМО!B:M,12,0) -> Среднеколымск | G77: 98646101001 | H77: 2 | I77: 20 | J77: 2000 | K77: =I77*J77*H77 -> 80000 | L77: NULL | N77: 67.58998000 | O77: 154.99092921 | P77: у о. Середниковский | Q77: ФИЛИАЛ "ЛЕНАРЕГИОНВОДХОЗ"

Sheet Реестр_ЧС
A1: № п/п | B1: ЧС по характеру и виду источника возникновения, в соответствии с перечнем | C1: Дата, субъект РФ, место, краткое описание чрезвычайной ситуации, причина возникновения ЧС | D1: Уровень ЧС | E1: Количество погибших | F1: Количество пострадавших | G1: Количество пострадавших (в том числе - детей) | H1: Количество спасенных | I1: дата введения | J1: район | K1: Год | L1: Тип ЧС
A2: 1 | B2: 1.8. Аварии на коммунальных системах жизнеобеспечения | C2: 03.01.01г. в Алданском районе, г.Томмот, в результате выхода из строя двух сетевых насосов остановлена котельная МУП ЖКХ, слита вода из системы отопления из 20 жилых домов, 5 зданий соцкультбыта, 2000 м теплотрассы. Без тепла остались 180 человек, из них 40 детей. | D2: Муниципальный | F2: 180 | I2: 36894 | J2: Алданский муниципальный район | K2: =YEAR(I2) -> 2001 | L2: Аварии в отопительный сезон
A3: 2 | B3: 1.8. Аварии на коммунальных системах жизнеобеспечения | C3: 04.01.01г. в 23 час.00 мин.в Усть - Янском районе, п.Казачье, остановлена котельная ПАКУ из-за течи котла, второй котел не смогли запустить (работают котлы на нефти). Слита вода с 5 жилых домов и 14 частных домов, теплотрассы длиной 1,82 км., с контор ЖКП, здания администрации, конторы ГУП "Дьааана. | D3: Муниципальный | I3: 36895 | J3: Усть-Янский муниципальный район | K3: =YEAR(I3) -> 2001 | L3: Аварии в отопительный сезон
A4: 3 | B4: 1.2.5. Пожары в зданиях (сооружениях) жилого, административного, учебно - воспитательного, социального, культурно - досугового назначения, здравоохранения | C4: 10.01.01г. в 04 час. 21мин в Томпонском районе, п.Хандыга, по улице П.Алексеева,15, произошел пожар в жилом доме. На месте пожара обнаружено 2 трупа: гр.Гороховой Л.А -1932 г.р. - пенсионерка и гр.Кучина А.В - 1972 г. р.- БОМР. Причина, виновник, ущерб пожара устанавливается . | D4: Локальный | E4: 2 | I4: 36901 | J4: Томпонский муниципальный район | K4: =YEAR(I4) -> 2001 | L4: Техногенные пожары
A5: 4 | B5: 1.8. Аварии на коммунальных системах жизнеобеспечения | C5: 15.01.01г. в Ленском районе, г.Ленск, из-за сильной утечки воды на теплотрассе, остановлена подача тепла в жилые дома от котельной "Чапаево". В результате аварии слита вода с 46-ти жилых домов (из них 16 жил.д. и 30 част. д.). Проживает 670 чел, из них 180 дети. | D5: Федеральный | F5: 670 | G5: 180 | I5: 36906 | J5: Ленский муниципальный район | K5: =YEAR(I5) -> 2001 | L5: Аварии в отопительный сезон
A6: 5 | B6: 1.2.4. Пожары на транспортных средствах (в т.ч. железнодорожный, водный,автомобильный, воздушный транспорт) | C6: 22.01.01г. в 11 час.50 мин. в Аллайховском районе, п.Чокурдах при заправке газоконденсатом емкости бензовоза произошло воспламенение топлива. В результате взрыва уничтожена автомашина УРАЛ-5557 Муниципального управления ЖКХ. Водитель не пострадал. | D6: Локальный | E6: 2 | I6: 36913 | J6: Аллаиховский муниципальный район | K6: =YEAR(I6) -> 2001 | L6: Дорожно-транспортные происшествия, на водном транспорте, АСР
A7: 6 | B7: 1.2.5. Пожары в зданиях (сооружениях) жилого, административного, учебно - воспитательного, социального, культурно - досугового назначения, здравоохранения | C7: 28.01.01г. в 03 час.30 мин. в Кобяйском районе, с.Кобяйск, произошел пожар в жилом доме. Здание деревянное двухэтажное огнем унеч-тожено полностью. На месте пожара обнаружено 3 трупа: гр.Сметаниной Р. Н. - 1973 г.р., гр.Сметанина К.- 1990 г.р. и гр.Сметанина С.- 1994 г.р.Причина, виновник, ущерб пожара устанавливаются. | D7: Локальный | E7: 3 | I7: 36919 | J7: Кобяйский муниципальный район | K7: =YEAR(I7) -> 2001 | L7: Техногенные пожары
A8: 7 | B8: 1.2.1. Пожары в зданиях,сооружениях, установках (в т.ч. магистральные газо -, нефте -, продуктопроводы) производственного назначения. | C8: 02.02.01г. в 14 час. 20 мин. в Усть - Янском районе, п.Депутатский, произошел пожар в здании ДЭС ( 11 ДГ). Огнем уничтожен силовой кабель и все ДГ. Электрообеспечение поселка отсутствует. В результате пожара остановлена центральная котельная, обеспечивающая теплом 26 жил. домов и 33 объекта производственного соцкульбыта. Без тепла остались 3 698 чел. (из них 1 208 детей). Пострадавшие были эвакуированы в соседние населённые пункты и в г. Якутск. Причина НППБ при выполнении свар. работ. | D8: Федеральный | F8: 3698 | G8: 1208 | I8: 36924 | J8: Усть-Янский муниципальный район | K8: =YEAR(I8) -> 2001 | L8: Техногенные пожары
A9: 8 | B9: 1.8. Аварии на коммунальных системах жизнеобеспечения | C9: 03.02.01г. в 02 час. 22 мин. в Ленском районе, г.Ленск, в котельной "Школьная" на котле КСВД произошел разрыв передней водяной камеры и выброс пароводяной смеси. Пострадало 4 человека, доставлены в больницу, из них двое скончались. | D9: Локальный | E9: 2 | F9: 4 | I9: 36925 | J9: Ленский муниципальный район | K9: =YEAR(I9) -> 2001 | L9: Аварии в отопительный сезон
A10: 9 | B10: 1.2.5. Пожары в зданиях (сооружениях) жилого, административного, учебно - воспитательного, социального, культурно - досугового назначения, здравоохранения | C10: 04.02.01г. в 14 час.50 мин. в Алданском районе, п.Ленинский, по улице Ленина,51, произошел пожар в жилом доме. В результате пожара погибли 3 человека: гр.Разумовская В. М. – 1941 г.р., Косых А. Ф.- 1940 г.р. и Разумовский Ю. В. – 1945 г. р. Причина пожара – неосторожность при курении. | D10: Локальный | E10: 3 | I10: 36926 | J10: Алданский муниципальный район | K10: =YEAR(I10) -> 2001 | L10: Аварии в отопительный сезон
A11: 10 | B11: 1.2.5. Пожары в зданиях (сооружениях) жилого, административного, учебно - воспитательного, социального, культурно - досугового назначения, здравоохранения | C11: 09.02.01г. в 12час.24 мин. в Мирнинском районе, мкр.Романовка,13, произошел пожар в частном доме. Погибло 3 человека. | D11: Локальный | E11: 3 | I11: 36931 | J11: Мирнинский муниципальный район | K11: =YEAR(I11) -> 2001 | L11: Техногенные пожары
A12: 11 | B12: 1.8. Аварии на коммунальных системах жизнеобеспечения | C12: 15.02.01г. в 15час. 15мин. в Верхоянском районе, с.Сайды произошла авария в ДЭС. В результате аварии вода слита с теплотрасс с 57 жилых домов, в которых проживает 435 человек. | D12: Региональный | F12: 435 | I12: 36937 | J12: Верхоянский муниципальный район | K12: =YEAR(I12) -> 2001 | L12: Аварии в отопительный сезон
A13: 12 | B13: 1.2.1. Пожары в зданиях,сооружениях, установках (в т.ч. магистральные газо -, нефте -, продуктопроводы) производственного назначения. | C13: 15.02.01г. в 00ч.30мин. в Таттинском районе, с.Ытык - Кель произошел пожар в центральной котельной. В результате пожара пострадала правая часть здания.В результате пожара погиб гр.Попов В.Н. - 1956 г.р. - оператор. Без тепла остались 17 жилых дома (659 чел.), 7 производственных объектов. Пострадавшие расселены по родственникам и знакомым. | D13: Федеральный | E13: 1 | F13: 659 | I13: 36937 | J13: Таттинский муниципальный район | K13: =YEAR(I13) -> 2001 | L13: Техногенные пожары
A14: 13 | B14: 1.2.5. Пожары в зданиях (сооружениях) жилого, административного, учебно - воспитательного, социального, культурно - досугового назначения, здравоохранения | C14: 18.02.01г. в 05час.40мин.в Таттинском районе, с.Харбалах, произошел пожар в частном доме. В результате пожара дом уничтожен по всей площади. В результате пожара погибло 2 человека и пострадало 5 человек (из них 3 дети) (размещены по родственникам). | D14: Локальный | E14: 2 | F14: 5 | G14: 3 | I14: 36940 | J14: Таттинский муниципальный район | K14: =YEAR(I14) -> 2001 | L14: Техногенные пожары
A15: 14 | B15: 1.8. Аварии на коммунальных системах жизнеобеспечения | C15: 27.02.01г. в 21 час.08 мин. в Амгинском районе, с.Чыпчылган, произошел взрыв котла на квартальной котельной. В результате взрыва произошел пожар. Котельная отапливала 10 жилых домов, гранильную фабрику, здания школы, гараж, мед. пункт, АТС и библиотеку. Пострадавшие размещены по родственникам и знакомым. | D15: Муниципальный | I15: 36949 | J15: Амгинский муниципальный район | K15: =YEAR(I15) -> 2001 | L15: Аварии в отопительный сезон
A16: 15 | B16: 1.2.5. Пожары в зданиях (сооружениях) жилого, административного, учебно - воспитательного, социального, культурно - досугового назначения, здравоохранения | C16: 06.03.01г. В Алданском районе, г.Алдан, по улице Доставалова, произошел пожар в частном доме. В результате пожара погибло 2 человека. | D16: Локальный | E16: 2 | I16: 36956 | J16: Алданский муниципальный район | K16: =YEAR(I16) -> 2001 | L16: Техногенные пожары
A17: 16 | B17: 3.1.4. Отравления людей. | C17: 17.03.01г. в г.Якутске, по улице Ногина, 6, произошло отравление жидкостью "стеклоочистителем"( содержит метанол) в частном доме. В результате отравления погибли гр.Филиппов А.В. и гр.Власов А. Доставлены в тяжелом состоянии 2 человека в больницу. | D17: Локальный | E17: 2 | F17: 2 | I17: 36967 | J17: Городской округ Город Якутск | K17: =YEAR(I17) -> 2001 | L17: Отравления
A18: 17 | B18: 1.2.5. Пожары в зданиях (сооружениях) жилого, административного, учебно - воспитательного, социального, культурно - досугового назначения, здравоохранения | C18: 17.04.01г. в 02час.02мин. в п.Марха, произошел пожар в общежитии Мархинского завода строительных материалов и конструкций. В результате пожара огнем уничтожено общежитие по всей площади.В результате пожара погибло 2 человека и 3 человека доставлены в больницу с ожогами различной степени тяжести. | D18: Локальный | E18: 2 | F18: 3 | I18: 36998 | J18: Городской округ Город Якутск | K18: =YEAR(I18) -> 2001 | L18: Техногенные пожары
A19: 18 | B19: 1.2.5. Пожары в зданиях (сооружениях) жилого, административного, учебно - воспитательного, социального, культурно - досугового назначения, здравоохранения | C19: 18.04.01г. В 03 час.43 мин в Намском районе, с.Намцы, произошел пожар в частном доме. На месте пожара обнаружено 2 трупа: гр.Звонкова В. В.- БОМЖ. Личность второго погибшего устанавливается.Причина, ущерб, виновник пожара устанавливаются. | D19: Локальный | E19: 2 | I19: 36999 | J19: Намский муниципальный район | K19: =YEAR(I19) -> 2001 | L19: Техногенные пожары
A20: 19 | B20: 1.8. Аварии на коммунальных системах жизнеобеспечения | C20: 16.04.01г. в Усть - Майском орайоне, п.Эльдикан, произошло авария на системе теплоснабжения. В результате аварии произошло разморожение 17 объектов : из них 14 жил. домов, 2 административных зданий и 1 промышленный объект. | D20: Муниципальный | I20: 36997 | J20: Усть-Майский муниципальный район | K20: =YEAR(I20) -> 2001 | L20: Аварии в отопительный сезон
A21: 20 | B21: 1.2.5. Пожары в зданиях (сооружениях) жилого, административного, учебно - воспитательного, социального, культурно - досугового назначения, здравоохранения | C21: 03.07.01г. в Аллайховском районе, п.Чокурдах, произошёл пожар в жилом доме. В результате пожара огнем уничтожен дом по всей площади. В результате пожара погибло 2 человека и пострадало 98 человек Пострадавшие расселены по знакомым и родственниками. Причина пожара неосторожное обращение с огнем. (Детская шалость). Материальный ущерб составляет 4.345.071 руб. | D21: Локальный | E21: 2 | F21: 98 | I21: 37075 | J21: Аллаиховский муниципальный район | K21: =YEAR(I21) -> 2001 | L21: Техногенные пожары
A22: 21 | B22: 2.2.1. Оползни, обвалы, осыпи | C22: 18.08.01г. 23 час.00 мин. в Мирнинском районе, г.Мирный, в пионерском лагере «Орлёнок» пропали 3 девочки. В результате поисков были найдены в заваленной землей пещере в 100 м. от пионерского лагеря на беРегиональныйу реки Малая Ботуобуя. В результате принятых мер медиков по восстановлении жизнедеятельности детей положительного результата не дали. (Ахчыгнырова Женя – 1989 г.р., Иванова Анна – 1987 г.р., Малова Даша – 1992 г.р.) | D22: Локальный | E22: 3 | I22: 37121 | J22: Мирнинский муниципальный район | K22: =YEAR(I22) -> 2001 | L22: Разрушения дорожного полотна, моста
A23: 22 | B23: 1.1.3. - 1.1.4. Кораблекрушения, аварии, повреждения грузовых, пассажирских судов, судов атомного флота, маломерных судов и судов флота рыбной промышленности, повреждения судами беРегиональныйовых, гидротехнических и других объектов. | C23: 20.10.01. в Мирнинском районе, с.Сюлдюкюр, на реке Вилюй, в результате опрокидывания лодки утонули 2 человека: гр.Мингазов А.Г-1977г.р. и гр Дудников Ф.Н. - 1974 г.р. | D23: Локальный | E23: 2 | I23: 37184 | J23: Мирнинский муниципальный район | K23: =YEAR(I23) -> 2001 | L23: Дорожно-транспортные происшествия, на водном транспорте, АСР
A24: 23 | B24: 1.1.5. - 1.1.6. Авиационные и ракетно - космические катастрофы и аварии в аэропортах, на стартовых площадках и в населеных пунктах и вне аэропортов, стартовых площадок и населенных пунктов. | C24: 9.11.01г. в 09 час.42 мин. в Нерюнгринском районе, п.Чульман из аэропорта п.Чульман вылетел вертолет Ми-8 №27021 авиакомпании «Дельта-К», на боту находилось 11 человек включая экипаж и 1320 кг. груза. В назначенное время Ми-8 №27021 не вышел на связь. На поиск вертолета вылетел Ми-8 №22750. 11.11.01г. оперативной группой МЧС РС(Я) было найдено место крушение Ми-8 азимут-110 гр. Дальность-104 км. В результате осмотра место катастрофы обнаружено 11 трупов. | D24: Муниципальный | E24: 11 | I24: 37204 | J24: Нерюнгринский муниципальный район | K24: =YEAR(I24) -> 2001 | L24: Авиационные инциденты
A25: 24 | B25: 1.2.5. Пожары в зданиях (сооружениях) жилого, административного, учебно - воспитательного, социального, культурно - досугового назначения, здравоохранения | C25: 15.11.01г. в 20 час. 15 мин. в Верхоянском районе, п.Верхоянск, по ул. Бабушкина, 37, произошел пожар в жилом доме. В результате пожара дом уничтожен по всей площади. На месте пожара обнаружено три трупа (двое мужчин, одна женщина). | D25: Локальный | E25: 3 | I25: 37210 | J25: Верхоянский муниципальный район | K25: =YEAR(I25) -> 2001 | L25: Техногенные пожары
A26: 25 | B26: 1.1.8. Транспортные катастрофы и аварии на мостах, переправах, в тоннелях, горных вырабатках, на железнодорожных переездах. | C26: 24.11.01г. в Верхневилюйском районе, п.Верхневилюйск, при переправе через реку Вилюй провалились под лед и затонули две а\машины (УАЗ и ЗИЛ). В результате происшествия погибли 4 человека: гр. Иванов Д. М.- 1948 г. р., гр.Тихонов Н. В. - 1954 г. р., гр.Степанов Н. С. 1977 г. р. и гр.Сергеев Е. Е. 1972 г. р. | D26: Локальный | E26: 4 | I26: 37219 | J26: Верхневилюйский муниципальный район | K26: =YEAR(I26) -> 2001 | L26: Дорожно-транспортные происшествия, на водном транспорте, АСР
A27: 26 | B27: 1.2.1. Пожары в зданиях,сооружениях, установках (в т.ч. магистральные газо -, нефте -, продуктопроводы) производственного назначения. | C27: 17.01.02г. в 00 час.25 мин.в Ленском районе, п.Пеледуй, произошел пожар в котельной. Котельная принадлежит Пеледуйскому ССРЗ. В результате пожара уничтожено 10 тонн нефти, повреждена крыша насосной станции, вышло из строя 2 сетевых насоса. Получил ожоги различной степени тяжести грЯремский -ст.мастер смены доставлен в больницу. Без тепла остались 140 семей, промзона, дет.сад, профилакторий, музыкальная школа, старое здание школы. | D27: Региональный | F27: 420 | I27: 37273 | J27: Ленский муниципальный район | K27: =YEAR(I27) -> 2002 | L27: Техногенные пожары
A28: 27 | B28: 1.8. Аварии на коммунальных системах жизнеобеспечения | C28: 12.02.02 г. в 13ч.00 мин. в Нижнеколымском районе, п.Черский, прекращена подача электроэнергии от АО «Чукотэнерго», обесточены котельные. В 14ч.10 мин. подача электроэнергии подана на все объекты. После запуска котельных, котельную № 4 (сырая нефть) в рабочий режим ввести не удалось. Без тепла остались 30жилых домов, здания Сахателеком, больницы, школы, детсада ЖКХ . | D28: Муниципальный | I28: 37299 | J28: Нижнеколымский муниципальный район | K28: =YEAR(I28) -> 2002 | L28: Аварии в отопительный сезон
A29: 28 | B29: 1.2.1. Пожары в зданиях,сооружениях, установках (в т.ч. магистральные газо -, нефте -, продуктопроводы) производственного назначения. | C29: 22.09.02г. 21 час.30 мин. в Таттинском районе, с.Баяга, произошел пожар в квартальной котельной. В результате пожара огнем котельная уничтожено по всей площади.Без тепла остались контора местной администрации, дом культуры, почта, АТС, музшкола, ср.школа (240 учеников), мастерская школы, школьный музей (2 здания), гараж, начальная школа (84 ученика), спортзал, рынок. | D29: Региональный | F29: 324 | I29: 37521 | J29: Таттинский муниципальный район | K29: =YEAR(I29) -> 2002 | L29: Техногенные пожары
A30: 29 | B30: 1.8. Аварии на коммунальных системах жизнеобеспечения | C30: 28.11.02 в 15 час. 15 мин. в Алданском районе, п.Солнечный, из-за погодных условий произошло отключение электроэнергии подстанции № 5. Без электроэнергии остались котельные. В результате аварии без тепла остались 89 жилых дома, (2 300 чел.), детский сад, школа. 28.11.02.в 15ч. 45 мин. неисправность устранена, подана электроэнергия на все объекты | D30: Федеральный | F30: 2300 | I30: 37588 | J30: Алданский муниципальный район | K30: =YEAR(I30) -> 2002 | L30: Аварии в отопительный сезон
A31: 30 | B31: 1.8. Аварии на коммунальных системах жизнеобеспечения | C31: 30.11.02г. в 18 час. 00 мин. в Вилюйском районе, п.Кысыл - Сыр, из-за неисправности остановлен паровой котел в котельной. В результате аварии 2 водовода и 2 спутника длинной 300 м. были разморожены. Без тепла остались 937 квартир, где проживают 1200 человек. | D31: Федеральный | F31: 1200 | I31: 37590 | J31: Вилюйский муниципальный район | K31: =YEAR(I31) -> 2002 | L31: Аварии в отопительный сезон
A32: 31 | B32: 1.8. Аварии на коммунальных системах жизнеобеспечения | C32: 03.12.02г. в 18 час.24 мин. в Мирнинском районе, с.Таас - Юрях, произведена аварийная остановка котельной. В результате аварии без тепла остались школа,амбулатория, хлебопекарня, детсад,почта, здание администрации, магазина, клуб, около 80 жилых индивидуальных домов. В селе проживает 615 жителей. | D32: Федеральный | F32: 615 | I32: 37593 | J32: Мирнинский муниципальный район | K32: =YEAR(I32) -> 2002 | L32: Аварии в отопительный сезон
A33: 32 | B33: 1.8. Аварии на коммунальных системах жизнеобеспечения | C33: 06.12.02г. в Ленском районе, г.Ленск, из-за короткого замыкания силового кабеля в головной подстанции микрорайона «Мухтуя» были остановлены 4 котельные. В результате остановки котельных без тепла остались 11 жилых домов. 10.02.02г. с02 ч30 мин в котельной "Доярушка"прекращена подача воды по причине перемерзания водовода. Без тепла осталось 13 жилых домов ( 238 жильцов). | D33: Региональный | F33: 238 | I33: 37596 | J33: Ленский муниципальный район | K33: =YEAR(I33) -> 2002 | L33: Аварии в отопительный сезон
A34: 33 | B34: 1.8. Аварии на коммунальных системах жизнеобеспечения | C34: 19.12.02 г. в 14час. 30 мин. в г.Якутске на ЯГРЭС произошло аварийное отключение ГТУ №3 по причине «низкий уровень в демпферном баке ТГ-3». По автоматической разгрузке отключилась ВЛ –110 кВ Л - № 101. В резульате аварии остались без энергоснабжения: г. Якутск и его пригороды, улусы: Амгинский, Чурапчинский, Горный, Хангаласский, Намский, Мегино-Кангаласский, Усть-Алданский, Таттинский, Томпонский. В работе осталась только Якутская ТЭЦ. В 16ч. 40мин подано напряжение на объекты ГУП «Водоканал».С 16час. 55мин. проводилось постепенное подключение потребителей электроэнергии в г. Якутске.С 17ч. 20мин.подана электроэнергия в улусы: Горный, Хангаласский, Намский. В 18ч. 05мин подана электроэнергия до центров улусов: Амгинского, Чурапчинского, Мегино-Кангаласского, Усть-Алданского, Таттинского, Томпонского. | D34: Муниципальный | I34: 37609 | J34: Городской округ Город Якутск | K34: =YEAR(I34) -> 2002 | L34: Аварии в отопительный сезон
A35: 34 | B35: 1.2.1. Пожары в зданиях,сооружениях, установках (в т.ч. магистральные газо -, нефте -, продуктопроводы) производственного назначения. | C35: 01.01.03г. Таттинский район, с.Туора - Кель, произошел пожар в котельной. В результате пожара котельная уничтожена полностью. Котельная отапливала жилых домов, среднюю и начальную школу, сельский дом культуры. Нарушена жизнедеятельность 13 чел., в т.ч. 4 детей. Пострадавшее население размещено по родственникам и знакомым. | D35: Муниципальный | F35: 13 | I35: 37622 | J35: Таттинский муниципальный район | K35: =YEAR(I35) -> 2003 | L35: Техногенные пожары
A36: 35 | B36: 1.8. Аварии на коммунальных системах жизнеобеспечения | C36: 01.01.03г. Кобяйский район, с.Кобяй , в результате утечки бытового газа погибла семья из 6 человек: гр.Сметанин В.Н. -1964 г.р., гр.Сметанина М.Д.- 1964 г.р., гр.Сметанин Н.В. -1982г.р., гр.Сметанина Е.В.- 1993 г.р., гр.Сметанин А.В. -2001 г.р. и гр.Эверстов А.И.- 1989 г.р. | D36: Локальный | E36: 6/2 | I36: 37622 | J36: Кобяйский муниципальный район | K36: =YEAR(I36) -> 2003 | L36: Аварии в отопительный сезон
A37: 36 | B37: 3.1.4. Отравление людей | C37: 02.01.03г. в Среднеколымском районе, с.Сватай, произошло отравление антифризом. В результате отравления в ЦУБ г.Среднеколымска были направлены самолетом 7 несовершенолетних жителей, из них двое скончались в пути. По данным емкость с антифризом была найдена одним из подростков в гараже коллективного хозяйства “Сватайский”. В результате отравления погибли 2 человека: гр. Тырылгин А.С.-17 лет и гр.Антипин В.В.-14 лет. Пострадали 5 человек: гр.Колесов Д.Н.-17 лет, гр.Слепцов А.В.- 15 лет, гр.Павлов В.В.-15 лет, гр.Колесов С.Е.-14 лет, и гр.Оконешникова М.О.-17 лет. | D37: Локальный | E37: 2 | F37: 5 | I37: 37623 | J37: Среднеколымский муниципальный район | K37: =YEAR(I37) -> 2003 | L37: Отравления
A38: 37 | B38: 1.2.5. Пожары в зданиях (сооружениях) жилого, административного, учебно - воспитательного, социального, культурно - досугового назначения, здравоохранения | C38: 09.01.03г. в 05 час.05 мин. в Мегино - Кангаласском районе, с.Техтюр, произошел пожар в средней школе. В результате пожара школа уничтожена огнем по всей площади. Пострадавших нет. Ущерб 250 000 рублей. Причина, виновник устанавливается, возбуждено уголовное дело | D38: Локальный | I38: 37630 | J38: Мегино-Кангаласский муниципальный район | K38: =YEAR(I38) -> 2003 | L38: Техногенные пожары
A39: 38 | B39: 1.2.5. Пожары в зданиях (сооружениях) жилого, административного, учебно - воспитательного, социального, культурно - досугового назначения, здравоохранения | C39: 14.01.03г. в 09ч.10мин. в Алданском районе, п.Безымянный, по ул.Дорожная,7, произошел пожар частном доме. В результате пожара огнем уничтожен дом по всей площади. На месте пожара погибли гр.Чуб А. М. - 1936 г.р. и гр.Чуб Г.А. - 1964 г.р. Причина пожара – НППБ при эксплуатации электронагрева-тельных приборов. Виновник, ущерб устанавливаются. | D39: Локальный | E39: 2 | I39: 37635 | J39: Алданский муниципальный район | K39: =YEAR(I39) -> 2003 | L39: Техногенные пожары
A40: 39 | B40: 1.2.5. Пожары в зданиях (сооружениях) жилого, административного, учебно - воспитательного, социального, культурно - досугового назначения, здравоохранения | C40: 16.01.03г. в 07 час.14 мин. в Ленском районе, г.Ленск, по ул. Пролетарская, 55, произошел пожар в частном доме. В результате пожара уничтожена по всей площади стена и крыша дома. На месте пожара погибли 2 человека: гр.Комаров С.А.-1957 г.р. и гр.Ермакова Л.А. -1962 г.р. Трое пострадавших в состоянии средней тяжести доставлены в ЦРБ. На месте пожара работает СОГ. | D40: Локальный | E40: 2 | F40: 3 | I40: 37637 | J40: Ленский муниципальный район | K40: =YEAR(I40) -> 2003 | L40: Техногенные пожары
A41: 40 | B41: 1.1.7. Аварии (катастрофы) на автодорогах (крупные дорожно - транспортные аварии и катастрофы) | C41: 18.01.03г. в 11час.30мин. в г.Якутске на 7 км Покровского тракта произошло столкновение автомобилей “Тойота-Спринтер” и “УАЗ-39629”. В результате ДТП в автомобиле “Тойота-Спринтер”погибли 3 человека, пострадали 3 человека (доставлены в Республиканскую больницу). Причина, виновник, ущерб устанавливаются. | D41: Локальный | E41: 3 | F41: 3 | I41: 37639 | J41: Городской округ Город Якутск | K41: =YEAR(I41) -> 2003 | L41: Дорожно-транспортные происшествия, на водном транспорте, АСР
A42: 41 | B42: 1.2.5. Пожары в зданиях (сооружениях) жилого, административного, учебно - воспитательного, социального, культурно - досугового назначения, здравоохранения | C42: 23.01.03г. в 00час.06мин. в Алданском райое, г.Алдан, по улице Горького,70, произошел пожар в здании Районного военкомата. Здание приспособлено под жилые помещения (квартиры) и административные помещения Райвоенкомата. В результате пожара огнем уничтожено здание по всей площади. Погибших и пострадавших нет.Причина пожара - НППБ при эксплуатации бытового электроприбора, виновное лицо- квартиросъемщик. Материальный ущерб устанавливается. | D42: Локальный | I42: 37644 | J42: Алданский муниципальный район | K42: =YEAR(I42) -> 2003 | L42: Дорожно-транспортные происшествия, на водном транспорте, АСР
A43: 42 | B43: 1.8. Аварии на коммунальных системах жизнеобеспечения | C43: 29.01.03г. в 13 час.20 мин. в Усть - Янском районе, с.Казачье из-за повреждении теплотрассы автомашиной УРАЛ слита вода с 250м теплотрассы, 2 жилых домов, гаража, магазина, склада. В жилом доме (проживает 26 человек, из них 8 дети) имеет печное отопление, из 8-квартирного жилого дома 16 жильцов расселено по родственникам и знакомым. | D43: Муниципальный | I43: 37650 | J43: Усть-Янский муниципальный район | K43: =YEAR(I43) -> 2003 | L43: Аварии в отопительный сезон
A44: 43 | B44: 1.2.5. Пожары в зданиях (сооружениях) жилого, административного, учебно - воспитательного, социального, культурно - досугового назначения, здравоохранения | C44: 02.02.03г. в 02ч.54мин. в Мегино - Кангаласском районе, с.Ломтука, по ул. Совхозная, 7, произошел пожар в жилом доме. Пострадали 3 человека: гр.Егоров А. -2001г.р., гр.Егоров А.Р.– 1935г.р. и гр.Дьячковская Е.А. – 1981г.р. Погибли 3 человека: гр.Адамова А. А. -1979г., гр.Андреева В. Н. – 1979г.р. и гр.Вешникова К. М. – 1988г.р. Причина пожара неосторожное обращение с огнем. | D44: Локальный | E44: 3 | F44: 3 | I44: 37654 | J44: Мегино-Кангаласский муниципальный район | K44: =YEAR(I44) -> 2003 | L44: Техногенные пожары
A45: 44 | B45: 1.2.4. Пожары на транспортных средствах ( в т.ч. железнодорожный, водный, втомобильный, воздушный транспорт) | C45: 26.02.03г. в 10 час.00 мин. в В.Вилюйском районе,п.Балагат, в 20 км. от районного центра произошел пожар в кунге автомашины «ЗИЛ» приспособленного под жилье. В результате пожара кунг огнем уничтожен по всей площади. На месте пожара обнаружено три трупа: гр.Касьянова А.В. - 1945 г.р., гр.Казакова М.В. - 1963 г.р. и гр.Михайлова М.Е.- 1960 г.р. Причина пожара неосторожное обращение с огнем в нетрезвом состоянии. | D45: Локальный | E45: 3 | I45: 37678 | J45: Вилюйский муниципальный район | K45: =YEAR(I45) -> 2003 | L45: Дорожно-транспортные происшествия, на водном транспорте, АСР
A46: 45 | B46: 1.2.5. Пожары в зданиях (сооружениях) жилого, административного, учебно - воспитательного, социального, культурно - досугового назначения, здравоохранения | C46: 13.03.03г. в 04 час.01 мин. в г.Якутске, по улице Дзержинского,14, произошел пожар в здании ГУВД. В результате пожара здание уничтожена по всей площади. На месте пожара погибло 2 человека. Причина пожара ………. | D46: Локальный | E46: 2 | I46: 37693 | J46: Городской округ Город Якутск | K46: =YEAR(I46) -> 2003 | L46: Техногенные пожары
A47: 46 | B47: 1.1.8. Транспортные катастрофы и аварии на мостах, переправах, в тоннелях, горных вырабатках, на железнодорожных переездах. | C47: 28.03.03г. в г.Якутске, на Маганском тракте в результате ДТП произошло столкновение автобуса «Паз» с микроавтобусом. В результате пожара пострадало 5 человек из них 2 человека погибло. | D47: Локальный | E47: 2 | F47: 5 | I47: 37708 | J47: Городской округ Город Якутск | K47: =YEAR(I47) -> 2003 | L47: Дорожно-транспортные происшествия, на водном транспорте, АСР
A48: 47 | B48: 1.2.5. Пожары в зданиях (сооружениях) жилого, административного, учебно - воспитательного, социального, культурно - досугового назначения, здравоохранения | C48: 07.04.03г. в 9 час. 10 мин. в Вилюйском районе, с.Сыдыбыл, произошел пожар в средней школе. В результате пожара здание школы уничтожено по всей площади. Пострадало 61 человек, в т.ч. погибли 22 человека, получили травмы различной степени тяжести 14 человек.Причина пожара неосторожное обращение с огнем.Виновник, ущерб устанавливаются. | D48: Региональный | E48: 22 | F48: 61 | I48: 37718 | J48: Вилюйский муниципальный район | K48: =YEAR(I48) -> 2003 | L48: Техногенные пожары
A49: 48 | B49: 1.2.10. Обнаружение (утрата) взрывчатых веществ (боеприпасов) | C49: 15.04.03г. в 10 час. 30 мин. в г. Якутске по улице П.Алексеева, 76, поступило сообщение из ОАО “Якутгазпром” о найденном боевом снаряде (76мм, зенитный, 1942г.). Группой разминирования снаряд был вывезен в карьер горного песка и ликвидирован путем подрыва. | D49: Муниципальный | I49: 37726 | J49: Городской округ Город Якутск | K49: =YEAR(I49) -> 2003 | L49: Взрывы бытового газа, прорывы на газо-магистральной линии
A50: 49 | B50: 2.5.1 Высокие уровни воды (половодье, зажор, затор, дождевой паводок), сель | C50: 23.05.03г. В Хангаласском районе, п.Кытыл - Джура, из - за резкого повышения уроавня воды в зоне затопления оказались 57 жилых домов, 3 промышленных объекта, 246 КРС. Причина - весенний паводок. | D50: Региональный | I50: 37764 | J50: Хангаласский муниципальный район | K50: =YEAR(I50) -> 2003 | L50: Весеннее половодье
A51: 50 | B51: 2.5.1 Высокие уровни воды (половодье, зажор, затор, дождевой паводок), сель | C51: 26.05.05г. в г.Якутске п.Даркылах, в связи с высоким уровнем воды произошло подтопление поселка. Поселок в это время года не населен. | D51: Муниципальный | I51: 38498 | J51: Городской округ Город Якутск | K51: =YEAR(I51) -> 2005 | L51: Весеннее половодье
A52: 51 | B52: 1.2.5. Пожары в зданиях (сооружениях) жилого, административного, учебно - воспитательного, социального, культурно - досугового назначения, здравоохранения | C52: 16.06.03г. в 17 час. 32 мин. в г.Якутске, на 10 км.Сергеляхской шоссе произошел пожар на дачных участках. В результате пожара уничтожео 50 строений, лес на общей площади 8 га. Причина пожара, виновник, ущерб устанавливаются. | D52: Муниципальный | I52: 37788 | J52: Городской округ Город Якутск | K52: =YEAR(I52) -> 2003 | L52: Техногенные пожары
A53: 52 | B53: 1.6. Внезапное обрушение зданий, сооружений, пород | C53: 20.06.03г. в 15 час. 00 мин. в Верхнеколымском районе, п.Зырянка, произошло обрушение жилого дома. В результате обрушения повреждены четыре квартиры. Обрушение произошло из – за просадки фундамента. Жильцы размещены у родственников и знакомых. Пострадало 26 человек ( из них 8 детей). | D53: Муниципальный | F53: 26 | I53: 37792 | J53: Верхнеколымский муниципальный район | K53: =YEAR(I53) -> 2003 | L53: Разрушения дорожного полотна, моста
A54: 53 | B54: 1.2.5. Пожары в зданиях (сооружениях) жилого, административного, учебно - воспитательного, социального, культурно - досугового назначения, здравоохранения | C54: 06.07.03г. в 05 час. 28 мин. в Нюрбинском районе, г. Нюрба, по ул. Жиркова, 6, произошел пожар в частном доме. В результате пожара огнем уничтожен дом по всей площади. На месте пожара обнаружены 3 трупа: гр.Степанов А.С.- 1957 г.р. -БОМР, гр.Николаева М. Н.- 1964 г.р.- БОМР и гр.Сухаринова Маша- 1998 г.р. Получил отравление угарным газом Климов Дьулустан - 2002 г.р., скончался при следовании в больницу. Причина пожара неосторожное обращение с огнем в нетрезвом состоянии. Виновник, ущерб устанавливаются. | D54: Локальный | E54: 4 | I54: 37808 | J54: Нюрбинский муниципальный район | K54: =YEAR(I54) -> 2003 | L54: Техногенные пожары
A55: 54 | B55: 1.1.1. - 1.1.2. Крушение и аварии грузовых и пассажирских поездов и поездов метрополитена | C55: 16.10.03 г. 01 час.32 мин. в Алданском районе, на 70 км. от г.Алдана произошло столкновение снегочиста (СДПМ) и грузового поезда (порожняк). В результате аварии 3 человека получили травмы различной степени тяжести, пострадавшие доставлены в Алданскую городскую больницу. Грузовой поезд следовал от ж.д. станции Нерюнгри. | D55: Локальный | F55: 3 | I55: 37910 | J55: Алданский муниципальный район | K55: =YEAR(I55) -> 2003 | L55: Дорожно-транспортные происшествия, на водном транспорте, АСР
A56: 55 | B56: 1.8. Аварии на коммунальных системах жизнеобеспечения | C56: 31.12.03г. в 17час.30 мин. в Усть - Янском районе, п..Сайылык, произошла авария на квартальной котельной из-за прорыва труб магистральной теплотрассы и утечки теплоносителя.В результате аварии вода слита с теплотрассы (3417м). Котельная отапливала 50 жилых домов (46 жилых домов имеют печное отопление), из них 4 частные дома.(Нарушено условие жизнедеятельности 24 чел.). Пострадавшие размещены по родственникам и знакомым. | D56: Муниципальный | F56: 24 | I56: 37986 | J56: Усть-Янский муниципальный район | K56: =YEAR(I56) -> 2003 | L56: Аварии в отопительный сезон
A57: 56 | B57: 1.2.1. Пожары в зданиях,сооружениях, установках (в т.ч. магистральные газо -, нефте -, продуктопроводы) производственного назначения. | C57: 02.01.04г. в г.Якутске произошел пожар в котельной ГУП «Теплоэнергия». В результате пожара огнем повреждено здание котельной на площади 250 кв.м. Без тепла остались 16 жилых домов. При пожаре в котельной погибла гр.Житаро В. А - 1944 г.р. – оператор. Нарушена жизнедеятельность 227 чел. Причина пожара, виновник не установлено | D57: Муниципальный | E57: 1 | I57: 37988 | J57: Городской округ Город Якутск | K57: =YEAR(I57) -> 2004 | L57: Техногенные пожары
A58: 57 | B58: 1.8. Аварии на коммунальных системах жизнеобеспечения | C58: 20.01.04г. в Кобяйском районе, п.Промышленный из-за повреждения магистрального газопровода остановлена котельная. Без тепла осталось 5 жилых домов (проживает 85 человек), 12 объектов соцкультбыта. Нарушена жизнедеятельность 298 чел., в т.ч. 50 детей. Эвакуировано на МИ-8 в п. Сангар 11 человек чел., в т.ч. 6 детей, размещены в детсаду “Геолог”. | D58: Муниципальный | I58: 38006 | J58: Кобяйский муниципальный район | K58: =YEAR(I58) -> 2004 | L58: Аварии в отопительный сезон
A59: 58 | B59: 2.5.1 Высокие уровни воды (половодье, зажор, затор, дождевой паводок), сель | C59: 10.06. в Ленском районе, п.Витим, в результате обильного выпадения осадков в Иркутской оласти в районе р.Витим, произошел резкий рост уровня воды р.Лена в районе п.Витим. Подтоплен 51 жилой дом, отселены 4 семьи (8чел.), перемыто 2,2 км. поселковых дорог, 15 км. заградительной дамбы, авиаплощадка. | D59: Региональный | I59: 38148 | J59: Ленский муниципальный район | K59: =YEAR(I59) -> 2004 | L59: Летне-осенний паводок
A60: 59 | B60: 1.1.8 Транспортные катастрофы и аварии на мостах, переправах, в тоннелях, горных выроботках, на железнодорожных переездах. | C60: 14.06.04г. в Алданском районе, п.Лебединый, в котловане утонула автомашина с пассажирами. В результате происшествия погибло 3 человека: гр. Меньшикова Н.Д. – 1958 г.р., гр.Цыганков И. О. – 1997 г.р. и гр. Катаманова Т. В. – 1962 г.р. | D60: Локальный | E60: 3/1 | H60: 2 | I60: 38152 | J60: Алданский муниципальный район | K60: =YEAR(I60) -> 2004 | L60: Дорожно-транспортные происшествия, на водном транспорте, АСР
A61: 60 | B61: 2.5.1 Высокие уровни воды (половодье, зажор, затор, дождевой паводок), сель | C61: 23.06.04г. в Верхоянском районе, п.Суордах (р.Дулгалах), п.Барылас (р.Сартанг) из-за обильных осадков и таяния снега в горах произошло подтопление населённых пунктов. Из нас.п.эвакуировано с п.Барылас 12 чел., п.Суордах- 50 чел. в п Батагай. | D61: Региональный | I61: 38161 | J61: Верхоянский муниципальный район | K61: =YEAR(I61) -> 2004 | L61: Летне-осенний паводок
A62: 61 | B62: 2.5.1 Высокие уровни воды (половодье, зажор, затор, дождевой паводок), сель | C62: 23.06.04г. в Верхоянском районе, п.Дулгалах (р.Дулгалах) из-за обильных осадков и таяния снегов в горах произошло подтопление населённого пункта. Подтоплено 55 жилых домов (209 чел.). | D62: Муниципальный | I62: 38161 | J62: Верхоянский муниципальный район | K62: =YEAR(I62) -> 2004 | L62: Летне-осенний паводок
A63: 62 | B63: 2.5.1 Высокие уровни воды (половодье, зажор, затор, дождевой паводок), сель | C63: 25.06.04г. в Верхоянском районе, с.Боронук(р.Яна) из-за обильных осадков и таяния снегов в горах произошло подтопление населённого пункта. Подтоплено 35 жилых дома. (проживает 300чел., в т.ч 120 детей). Пострадавшие эвакуированы из села на звероферму. | D63: Региональный | I63: 38163 | J63: Верхоянский муниципальный район | K63: =YEAR(I63) -> 2004 | L63: Летне-осенний паводок
A64: 63 | B64: 2.5.1 Высокие уровни воды (половодье, зажор, затор, дождевой паводок), сель | C64: 26.06.04г. в Верхоянском районе из-за обильных осадков и таяния снегов в горах, резкого повышения уровня воды р. Яна произошло подтопление г.Верхоянска. Подтоплено 82 жилых дома, в которых проживает 350 чел. | D64: Муниципальный | I64: 38164 | J64: Верхоянский муниципальный район | K64: =YEAR(I64) -> 2004 | L64: Летне-осенний паводок
A65: 64 | B65: 1.1.3. - 1.1.4. Кораблекрушения, аварии, повреждения грузовых, пассажирских судов, судов атомного флота, маломерных судов и судов флота рыбной промышленности, повреждения судами беРегиональныйовых, гидротехнических и других объектов. | C65: 01.08.04г. в Кобяйском районе, п.Сангары, при швартовке к пристани в п. Сангары получил пробоину машинного отделения теплоход «Чусовской», выполняющий рейс Нюрба – Якутск. На борту находилось 35 чел. и 6 членов экипажа. Подтоплено машинное отделение, жертв и пострадавших нет. Пассажиры от эвакуации отказались и находятся на борту, им розданы тёплые вещи. Топлива на борту 1т. 200кг, розлива топлива нет. | D65: Муниципальный | I65: 38200 | J65: Кобяйский муниципальный район | K65: =YEAR(I65) -> 2004 | L65: Дорожно-транспортные происшествия, на водном транспорте, АСР
A66: 65 | B66: 1.2.1. Пожары в зданиях,сооружениях, установках (в т.ч. магистральные газо -, нефте -, продуктопроводы) производственного назначения. | C66: 04.08.04г. в 14час.44мин. в г.Якутске произошел пожар в здании ГРС (газораспределительной станции) ОАО “Якутгазпрома”. В результате пожара ГРЭС и ТЭЦ г.Якутска переведены на жидкое топливо, трубопроводы от ГРС на ГРЭС и газоперерабатывающий завод перекрыты, ведутся работы по перекрытию основного трубопровода и снижению давления газа на ГРС. Информация о пострадавших не поступала. В результате аварии погиб 1 человек. | D66: Локальный | E66: 1 | I66: 38203 | J66: Городской округ Город Якутск | K66: =YEAR(I66) -> 2004 | L66: Техногенные пожары
A67: 66 | B67: 1.1.3. - 1.1.4. Кораблекрушения, аварии, повреждения грузовых, пассажирских судов, судов атомного флота, маломерных судов и судов флота рыбной промышленности, повреждения судами беРегиональныйовых, гидротехнических и других объектов. | C67: 01.09.04г. в 21 час.00 мин в Усть - Янском районе, п.Северный, на 247 км реки Яна в районе нежилого поселка Северный маломерное судно «Гэсстрой» (проект Р-736) приписки Усть – Янской ДЭС Якутскэнерго в составе экипажа.капитан судна Старчевой В. А. рулевой – моторист Мухетдинов А. П. совершил столкновение с затонувшим судном. В результате столкновения получил пробоину и затонул. В результате столкновения погибли 3 человека: гр.Старчевой В. А.-капитан, грХлыстов С. В. и гр.Ларионов Б. - рабочие Якутской фирмы «ремонтдизель». 02.09.04г. выплыл на беРегиональный гр.Мухетдинов А. П. -рулевой моторист. Погибшие были извлечены из каюты и доставлены в морг г. Усть – Куйги. По данному факту возбуждено уголовное дело № 403035 по ст. 263 ч. 3 УК РФ. | D67: Локальный | E67: 3 | I67: 38231 | J67: Усть-Янский муниципальный район | K67: =YEAR(I67) -> 2004 | L67: Дорожно-транспортные происшествия, на водном транспорте, АСР
A68: 67 | B68: 1.2.4. Пожары на транспортных средствах ( в т.ч. железнодорожный, водный, втомобильный, воздушный транспорт) | C68: 16.09.04г.в 21 час 15 мин. в Анабарском районе,п.Юрюн - Хая, во время перекачки топлива произошел взрыв с последующим горением в машинном отделении танкера № 2061 (принадлежность ОАО ЛОРП), порт приписки Пеледуйская ССРЗ (судостроительный ремонтный завод). На танкере осталось 800 т АИ-80 и 1400 т дизельного топлива. На борту находились 12 членов экипажа и представитель нефтебазы. С борта танкера эвакуировано 6 человек экипажа, из них 3 человека в тяжелом состоянии, местонахождение 7 человек не выяснено. Эвакуированы в п. Саскылах 54 ребенка и 6 пострадавших членов экипажа. Население п. Юрюнг-Хая эвакуировано в безопасные места, создана ОГ под руководством главы администрации Поповым П. С. | D68: Локальный | F68: 6 | I68: 38246 | J68: Анабарский национальный (долгано-эвенкийский) муниципальный район | K68: =YEAR(I68) -> 2004 | L68: Дорожно-транспортные происшествия, на водном транспорте, АСР
A69: 68 | B69: 1.1.8 Транспортные катастрофы и аварии на мостах, переправах, в тоннелях, горных выроботках, на железнодорожных переездах. | C69: 17.09.04г.в 13ч.20 мин. на паромной переправе реки Лена в районе п. Кангалассы ( 45 км от г. Якутска) ушёл под воду УАЗ- санитарка гос. № 285. В 14ч.20 мин машина была вытащена на беРегиональный от куда были вытащены 2 детей ( 3-4 лет), 1 мужчина (40-42 лет). 1 женщина (35-40 лет), ведутся поиски ещё одного ребёнка. Причина уточняется. Погибли Потапова Света- 5 лет и Егорова Е. И.Фамилия остальных погибших уточняется.Все проживали в Усть-Алданском районе п.Дюпся. | D69: Локальный | E69: 5/3 | I69: 38247 | J69: Усть-Алданский муниципальный район | K69: =YEAR(I69) -> 2004 | L69: Дорожно-транспортные происшествия, на водном транспорте, АСР
A70: 69 | B70: 1.2.5. Пожары в зданиях (сооружениях) жилого, административного, учебно - воспитательного, социального, культурно - досугового назначения, здравоохранения | C70: 15.11.04г. в г.Якутске, п.Пригородный, произошел пожар в частном доме. В результате пожара огнем уничтожен дом по всей площади. С места пожара была доставлена в ожоговый центр Карамзина С.Е. - 1972 г. р., получила термические ожоги 3-й «А», «Б», 4 степени всего тела, состояние крайне тяжелое. Причина, виновник, ущерб устанавливаются. На месте пожара обнаружены 3 трупа: гр Карамзиной В.В.- 2000 г. р., грСвинобоева В. Л., гр.Карамзиной К. В. - 1996 г. р. | D70: Локальный | E70: 3/1 | F70: 1 | I70: 38306 | J70: Городской округ Город Якутск | K70: =YEAR(I70) -> 2004 | L70: Техногенные пожары
A71: 70 | B71: 1.2.5. Пожары в зданиях (сооружениях) жилого, административного, учебно - воспитательного, социального, культурно - досугового назначения, здравоохранения | C71: 23.11.04г. в Олекминском районе, г.Олекминск, произошел пожар в частном доме.В результате пожара огнём повреждён пол на пл. 2 кв.м. На месте пожара обнаружены 2 взрослых трупа, личность которых устанавливается. | D71: Локальный | E71: 2 | I71: 38314 | J71: Олекминский муниципальный район | K71: =YEAR(I71) -> 2004 | L71: Техногенные пожары
A72: 71 | B72: 1.2.5. Пожары в зданиях (сооружениях) жилого, административного, учебно - воспитательного, социального, культурно - досугового назначения, здравоохранения | C72: 02.12.04г. в г.Якутске, п. Геологов, произошел пожар в частном доме. В результате пожара огнем уничтожен дом по всей площади. На месте пожара обнаружены 2 трупа, личность устанавливается. Эвакуировано 2 человека в ожоговый центр г. Якутска | D72: Локальный | E72: 2 | I72: 38323 | J72: Городской округ Город Якутск | K72: =YEAR(I72) -> 2004 | L72: Техногенные пожары
A73: 72 | B73: 1.2.5. Пожары в зданиях (сооружениях) жилого, административного, учебно - воспитательного, социального, культурно - досугового назначения, здравоохранения | C73: 08.12.04г. в Ленском районе, п.Большой Пеледуй, произошел пожар в жилом доме В результате пожара огнем уничтожен дом по всей площади. В результате пожара погибли 2 человека: гр.Шеин И.Ф. – пенсионер и гр.Шеин А.А. - 1964г. р.- БОМР. | D73: Локальный | E73: 2 | I73: 38329 | J73: Ленский муниципальный район | K73: =YEAR(I73) -> 2004 | L73: Техногенные пожары
A74: 73 | B74: 1.2.5. Пожары в зданиях (сооружениях) жилого, административного, учебно - воспитательного, социального, культурно - досугового назначения, здравоохранения | C74: 09.12.04г. в Сунтарском районе, с.Сунтар, произошел пожар в частном доме. В результате пожара огнем повреждено15 кв. м. На месте пожара обнаружено два трупа (девочки-1,5 года, мальчика-7 лет). Причина, виновник, ущерб пожара устанавливается. | D74: Локальный | E74: 2/2 | I74: 38330 | J74: Сунтарский муниципальный район | K74: =YEAR(I74) -> 2004 | L74: Техногенные пожары
A75: 74 | B75: 1.8. Аварии на коммунальных системах жизнеобеспечения. | C75: 10.12.04г. в 16час.00мин. в Оленекском районе, с.Оленек, из-за нарушения технологического процесса на оборудовании остановлена котельная «Стройучастка». Котельная отапливала: 15 ж/домов, где проживает 50 семей (181 человек из них 80 детей). 5 частных домов имеют печное отопление. Вода из системы отоплении полностью слита. 11.12.04г. в 01 час.50 мин. котельная запущена. | D75: Муниципальный | I75: 38331 | J75: Оленекский эвенкийский национальный муниципальный район | K75: =YEAR(I75) -> 2004 | L75: Аварии в отопительный сезон
A76: 75 | B76: 1.8. Аварии на коммунальных системах жизнеобеспечения. | C76: 20.12.04г. в Булунском районе, п.Тикси, из-за выхода строя основного подпитывающего насоса котельной ГУП ЖКХ была приостановлена работа котельной.В результате аварии не было обеспечено нормальное давление воды на выходе из котельной. В результате аварии разморожено 90 квартир. В квартирах проживает 201 человек (61 дети). | D76: Муниципальный | I76: 38341 | J76: Булунский муниципальный район | K76: =YEAR(I76) -> 2004 | L76: Аварии в отопительный сезон
A77: 76 | B77: 1.2.5. Пожары в зданиях (сооружениях) жилого, административного, учебно - воспитательного, социального, культурно - досугового назначения, здравоохранения | C77: 26.12.04г. 19ч.41 мин. в г.Якутске, по ул. Челюскина, 34, произошел пожар в частном доме. В результате пожара дом уничтожен по всей площади. На месте пожара обнаружены 2 погибших, личность которых устанавливается. | D77: Локальный | E77: 2 | I77: 38347 | J77: Городской округ Город Якутск | K77: =YEAR(I77) -> 2004 | L77: Техногенные пожары
A78: 77 | B78: 1.2.5. Пожары в зданиях (сооружениях) жилого, административного, учебно - воспитательного, социального, культурно - досугового назначения, здравоохранения | C78: 31.12.04г. в 04час.40мин. в Сунтарском районе, с.Толоон, по ул.Новая, 39, произошел пожар в частном доме. В результате пожара дом огнем уничтожен по всей площади. На месте пожара погибли 2 человека: гр.Баишев Е.Я. - 1954г.р. и гр. Баишева В.С. - 1957г.р. Виновник, ущерб, причина пожара устанавливаются | D78: Локальный | E78: 2 | I78: 38352 | J78: Сунтарский муниципальный район | K78: =YEAR(I78) -> 2004 | L78: Техногенные пожары
A79: 78 | B79: 1.2.5. Пожары в зданиях (сооружениях) жилого, административного, учебно - воспитательного, социального, культурно - досугового назначения, здравоохранения | C79: 01.01.05г. Сунтарский район, с.Сунтар, пожар в административном здании приспособленной под жилье. В результате пожара огнем уничтожено здание полностью. На месте пожара погибло 7 чел., в т.ч. 4 реб. Пострадало 3 чел. Спасено 12 человек. Причина пожара нарушение при ЭЭ, виновник - хозяин. | D79: Локальный | E79: 7/4 | F79: 3 | H79: 12 | I79: 38353 | J79: Сунтарский муниципальный район | K79: =YEAR(I79) -> 2005 | L79: Техногенные пожары
A80: 79 | B80: 1.2.5. Пожары в зданиях (сооружениях) жилого, административного, учебно - воспитательного, социального, культурно - досугового назначения, здравоохранения | C80: 04.01.05г. в г.Якутске произошел пожар в общежитии. В результате пожара огнем повреждено общежитие на площади 200 кв.м.На месте пожара погибло 2 чел., пострадал 1 чел. Спасено 2 чел.Причина пожара неосторожность при курении в нетрезвом состоянии. Виновник не установлен. Ущерба нет. | D80: Локальный | E80: 2 | F80: 1 | H80: 2 | I80: 38356 | J80: Городской округ Город Якутск | K80: =YEAR(I80) -> 2005 | L80: Техногенные пожары
A81: 80 | B81: 1.2.5. Пожары в зданиях (сооружениях) жилого, административного, учебно - воспитательного, социального, культурно - досугового назначения, здравоохранения | C81: 08.01.05г. в г.Ленске произошел пожар в частном доме. В результате пожара огнем поврежден дом на площади 80 кв.м..На месте пожара погибло 2 чел. и 1 чел. получил травму. Причина пожапра НППБ при ЭЭ. Виновник хозяин, ущерба нет. | D81: Локальный | E81: 2 | F81: 1 | I81: 38360 | J81: Ленский муниципальный район | K81: =YEAR(I81) -> 2005 | L81: Техногенные пожары
A82: 81 | B82: 1.2.6. Пожары на объектах другого назначения | C82: 09.01.05г. в г.Якутске, п.Жатай, произошел пожар в сторожке кладбища. В результате пожара огнем поврежден кровать на площади 2 кв.м. На месте пожара погибло 2 человека. Причина пожара неосторожножное обращение с огнем.Виновник охранник, ущерба нет. | D82: Локальный | E82: 2 | I82: 38361 | J82: Городской округ Город Якутск | K82: =YEAR(I82) -> 2005 | L82: Техногенные пожары
A83: 82 | B83: 1.2.5. Пожары в зданиях (сооружениях) жилого, административного, учебно - воспитательного, социального, культурно - досугового назначения, здравоохранения | C83: 28.01.05г. в г.Якутске, произошел пожар в жилом доме. В результате пожара огнем поврежден дом на площади 80 кв.м. На месте пожара погиб 1 чел. и 5 чел. получили травму. Причина пожара неосторожное обращение с огнем. Виновник не установлен. Ущерба нет. | D83: Локальный | E83: 1 | F83: 5 | I83: 38380 | J83: Городской округ Город Якутск | K83: =YEAR(I83) -> 2005 | L83: Техногенные пожары
A84: 83 | B84: 1.2.5. Пожары в зданиях (сооружениях) жилого, административного, учебно - воспитательного, социального, культурно - досугового назначения, здравоохранения | C84: 05.02.05г. в Чурапчинском районе, с.Чурапча, произошел пожар в частном доме. В результате пожара огнем поврежден дом на площади 0,5 кв.м. В результате пожара погибло 2 реб.Причина пожара - неосторожное обращение с огнем (детская шалостьс огнем). Виновник ребенок. | D84: Локальный | E84: 2/2 | I84: 38388 | J84: Чурапчинский муниципальный район | K84: =YEAR(I84) -> 2005 | L84: Техногенные пожары
A85: 84 | B85: 1.2.5. Пожары в зданиях (сооружениях) жилого, административного, учебно - воспитательного, социального, культурно - досугового назначения, здравоохранения | C85: 20.02.05г. в Сунтарском районе, с.Шея, произошел пожар в частном доме. В результате пожара огнем уничтожен дом по всей площади. На месте пожара обнаружены 3 трупа, в т.ч. 1 реб. Причина пожара - НППБ при эксплуатации отопительной печи. Виновник - рабочий. Ущерб - 162797 руб. | D85: Локальный | E85: 3/1 | I85: 38403 | J85: Сунтарский муниципальный район | K85: =YEAR(I85) -> 2005 | L85: Техногенные пожары
A86: 85 | B86: 1.2.5. Пожары в зданиях (сооружениях) жилого, административного, учебно - воспитательного, социального, культурно - досугового назначения, здравоохранения | C86: 10.03.05г. в г.Якутске, по пр.Ленина, 5, произошел пожар в Якутском педогогическом колледже. На месте пожара пострадало 4 человека. Причина пожара нарушение монтажа электорооборудования. Виновник не установлен. Ущерб 843000руб. | D86: Локальный | F86: 4 | I86: 38421 | J86: Городской округ Город Якутск | K86: =YEAR(I86) -> 2005 | L86: Техногенные пожары
A87: 86 | B87: 1.2.5. Пожары в зданиях (сооружениях) жилого, административного, учебно - воспитательного, социального, культурно - досугового назначения, здравоохранения | C87: 23.03.05г. в Усть - Майском районе, п.Усть - Миль,произошел пожар в жилом доме. В результате пожара огнем уничтожен дом по всей площади. На месте пожара обнаружено 2 трупа гр.Вербаноль В.П. - 1938 г.р. - пенсионер, гр.Вербаноль Л.И. - 1946 г.р. - пенсионерка. Причина пожара неосторожное обращение с огнем. Виновник не установлен. Ущерба нет. | D87: Локальный | E87: 2 | I87: 38434 | J87: Усть-Майский муниципальный район | K87: =YEAR(I87) -> 2005 | L87: Техногенные пожары
A88: 87 | B88: 1.2.5. Пожары в зданиях (сооружениях) жилого, административного, учебно - воспитательного, социального, культурно - досугового назначения, здравоохранения | C88: 28.03.05г. в Амгинском районе, с.Покровка, произошел пожар в частном доме. В результате пожара огнем поврежден дом на площади 2 кв.м. На месте пожара обнаружено 2 трупа гр.Тирский А.А.. - 1956 г.р. - БОМР, гр.Аносова В.В. - 1940 г.р. - БОМР. Причина пожара неосторожное обращение с огнем при курении, виновник - пенсионер, ущерба нет. | D88: Локальный | E88: 2 | I88: 38439 | J88: Хангаласский муниципальный район | K88: =YEAR(I88) -> 2005 | L88: Техногенные пожары
A89: 88 | B89: 1.1.7. Аварии (катастрофы) на автодорогах (крупные дорожно транспортные аварии и катастрофы) | C89: 12.04.05г. на расстоянии 40км от г. Нюрба произошло ДТП Камаз и УАЗ «санитарка». В результате аварии погибло 3 человека и 2 человека скончались в больнице в течении 12ч. Личности погибших и пострадавших устанавливаются. | D89: Локальный | E89: 5 | I89: 38454 | J89: Нюрбинский муниципальный район | K89: =YEAR(I89) -> 2005 | L89: Дорожно-транспортные происшествия, на водном транспорте, АСР
A90: 89 | B90: 1.2.6. Пожары на объектах другого назначения | C90: 28.04.05г. в Верхневилюйском районе, на местности Харыйалах, произошел пожар в балке лесорубов. В результате пожара огнем уничтожен балок по всей площади. На месте пожара обнаружены 4 трупа гр.Осинова В.Н. - 1953 г.р., гр.Долгунова А.С. - 1959 г.р., гр.Алексеева П. и гр.Егорова К.В. - 1963 г.р. Причина пожара неосторожность при курении. Виновник ущерб устанавливаются. | D90: Локальный | E90: 4 | I90: 38470 | J90: Верхневилюйский муниципальный район | K90: =YEAR(I90) -> 2005 | L90: Техногенные пожары
A91: 90 | B91: 3.1.2. Опасные кишечные инфекции (болезни 1 и 11группы патогенности по СП 1.2.01. 1-94) | C91: 29.04.05г. в Мирнинском районе, п.Удачный, поступили в ЦУБ с массовым отравлением ОКИ 48 человек. Отравление произошло в столовой у работников ГОК г.Удачного из - за несоблюдения санитарной безоапасности. | D91: Муниципальный | F91: 48 | I91: 38471 | J91: Мирнинский муниципальный район | K91: =YEAR(I91) -> 2005 | L91: Отравления
A92: 91 | B92: 1.2.5. Пожары в зданиях (сооружениях) жилого, административного, учебно - воспитательного, социального, культурно - досугового назначения, здравоохранения | C92: 05.05.05г. в Таттинском районе, с.Ытык - Кель, произошел пожар в жилом доме. В результате пожара огнем уничтожен дом по всей площади. На месте пожара обнаружены 3 детей гр.Сысолятиной А.- 1999 г.р., гр.Сысолятиной Дуни - 2000 г.р., гр.Сысолятина Власия - 2003 г.р. Причина пожара короткое замыкание электропроводки. Виновник ущерб устанавливаются. | D92: Локальный | E92: 3/3 | F92: 1 | I92: 38477 | J92: Таттинский муниципальный район | K92: =YEAR(I92) -> 2005 | L92: Техногенные пожары
A93: 92 | B93: 1.2.5. Пожары в зданиях (сооружениях) жилого, административного, учебно - воспитательного, социального, культурно - досугового назначения, здравоохранения | C93: 23.05.05г. в г.Якутске, произошел пожар в частном доме. В результате пожара огнем повреждены строения на площади 70 кв.м. На месте пожара обнаружено 2 трупа: гр.Ли В.Б. - 1947 г.р. и гр.Шилова А.В. - 1962 г.р. Причина, виновник, ущерб устанавливаются. | D93: Локальный | E93: 2 | I93: 38495 | J93: Городской округ Город Якутск | K93: =YEAR(I93) -> 2005 | L93: Техногенные пожары
A94: 93 | B94: 1.2.5. Пожары в зданиях (сооружениях) жилого, административного, учебно - воспитательного, социального, культурно - досугового назначения, здравоохранения | C94: 06.07.05г. в Кобяйском районе, п.Кобяйск, произошел пожар в частной даче. В результате пожара огнем дача уничтожена полностью. На месте пожара обнаружено 2 трупа: гр.Арбугина А.А. - 1977 г.р. и гр.Винокурова В.А. - 1975 г.р. Причина, виновник, ущерб устанавливаются. | D94: Локальный | E94: 2 | I94: 38539 | J94: Кобяйский муниципальный район | K94: =YEAR(I94) -> 2005 | L94: Техногенные пожары
A95: 94 | B95: 2.5.1 Высокие уровни воды (половодье, зажор, затор, дождевой паводок), сель | C95: 01.08.05г. в Верхоянском районе, п.Батагай, в результате проливных дождей произошло частичное подтопление. В результате разлива потоки воды прошли по улицам Ленина и Октябрьская, общая длина промоин 1200 м., повреждено 10 анкерных опор, разрушена дорога-дамба Батагай – аэропорт; нарушена теплоизоляция теплотрасс. Для подачи электроснабжения запущено два дизель-генератора, эл. энергия подается без ограничений (по временной схеме). Технологический процесс объектов жизнеобеспечения населения не нарушен. | D95: Региональный | I95: 38565 | J95: Верхоянский муниципальный район | K95: =YEAR(I95) -> 2005 | L95: Летне-осенний паводок
A96: 95 | B96: 1.6. Внезапное обрушение зданий, сооружений, пород | C96: 01.08.05г. в Нерюнгринском районе, г.Нерюнгри, при разборке здания произошло обрушение кровли. В результате происшествия погибло 3 человека, пострадал 1 человек. Обрушение кровли произошло из - за нарушения ТБ. | D96: Локальный | E96: 3 | F96: 1 | I96: 38565 | J96: Нерюнгринский муниципальный район | K96: =YEAR(I96) -> 2005 | L96: Разрушения дорожного полотна, моста
A97: 96 | B97: 1.2.5. Пожары в зданиях (сооружениях) жилого, административного, учебно - воспитательного, социального, культурно - досугового назначения, здравоохранения | C97: 06.08.05г. в Мирнинском районе, г.Удачный, по улице Строителей, 4, произошел пожар в жилом доме. На месте пожара обнаружено 2 трупа: гр.Кириллова Н.Г. - 1960 г.р. и гр.Кириллова В.Г. - 1964 г.р. Причина пожара НПУ и ЭЭ. Виновник установлен. Ущерб 29 300 руб. | D97: Локальный | E97: 2 | I97: 38570 | J97: Мирнинский муниципальный район | K97: =YEAR(I97) -> 2005 | L97: Техногенные пожары
A98: 97 | B98: 1.2.5. Пожары в зданиях (сооружениях) жилого, административного, учебно - воспитательного, социального, культурно - досугового назначения, здравоохранения | C98: 12.08.05г. в Среднеколымском районе, п.Аргахтах, произошел пожар в Аргахтахской средней школе. В результате пожара школа уничтожена по всей площади. Причина пожара, виновник устанавливаются. Ущерб 10 874 300 руб. | D98: Муниципальный | I98: 38576 | J98: Среднеколымский муниципальный район | K98: =YEAR(I98) -> 2005 | L98: Техногенные пожары
A99: 98 | B99: 1.2.5. Пожары в зданиях (сооружениях) жилого, административного, учебно - воспитательного, социального, культурно - досугового назначения, здравоохранения | C99: 25.08.05г. в Вилюйском районе, с.Хампа, произошел пожар в частном доме. В результате пожара дом уничтожен по всей площади.На месте пожара обнаружены 3 трупа гр.Потапова И.П. - 1955 г.р.., гр.Потапова П.И. - 1986 г.р., гр.Потапова Н.И. - 1987 г.р. В ЦУБ доставлены 3 пострадавших. Причина пожара НПУ и ЭЭ. Виновник установлен. Ущерб 150 000 руб. | D99: Локальный | E99: 3 | F99: 3 | H99: 3 | I99: 38589 | J99: Вилюйский муниципальный район | K99: =YEAR(I99) -> 2005 | L99: Техногенные пожары
A100: 99 | B100: 1.2.5. Пожары в зданиях (сооружениях) жилого, административного, учебно - воспитательного, социального, культурно - досугового назначения, здравоохранения | C100: 30.08.05г. в г.Якутске, произошел пожар в частном доме. В результате пожара дом уничтожен полностью.На месте пожара обнаружены 2 трупа: гр.Берниковой Л.Г. - 1948 г.р.., личность 2-го трупа устанавливается. Получил ожоги грудной клетки гр.Жирков Н.И. Причина пожара неоторожное обращение согнем при курении в нетрезвом состоянии. Виновник установлен. Ущерб устанавливается. | D100: Локальный | E100: 2 | F100: 1 | I100: 38594 | J100: Городской округ Город Якутск | K100: =YEAR(I100) -> 2005 | L100: Техногенные пожары
...

Sheet Анализ_ЧС
A1: Реестр чрезвычайных ситуаций с 2001 года | K1: ВСЕГО
A2: № | B2: Локальный | C2: Муниципальный | D2: Межмуниципальный | E2: Региональный | F2: Межрегиональный | G2: Федеральный | H2: ВСЕГО | J2: Природные ЧС | K2: =H56 -> 435
A3: 2001 | B3: =COUNTIFS(Реестр_ЧС!$D$2:$D$797,Анализ_ЧС!B$2,Реестр_ЧС!$K$2:$K$797,Анализ_ЧС!$A3) -> 16 | C3: =COUNTIFS(Реестр_ЧС!$D$2:$D$797,Анализ_ЧС!C$2,Реестр_ЧС!$K$2:$K$797,Анализ_ЧС!$A3) -> 5 | D3: =COUNTIFS(Реестр_ЧС!$D$2:$D$797,Анализ_ЧС!D$2,Реестр_ЧС!$K$2:$K$797,Анализ_ЧС!$A3) -> 0 | E3: =COUNTIFS(Реестр_ЧС!$D$2:$D$797,Анализ_ЧС!E$2,Реестр_ЧС!$K$2:$K$797,Анализ_ЧС!$A3) -> 1 | F3: =COUNTIFS(Реестр_ЧС!$D$2:$D$797,Анализ_ЧС!F$2,Реестр_ЧС!$K$2:$K$797,Анализ_ЧС!$A3) -> 0 | G3: =COUNTIFS(Реестр_ЧС!$D$2:$D$797,Анализ_ЧС!G$2,Реестр_ЧС!$K$2:$K$797,Анализ_ЧС!$A3) -> 3 | H3: =SUM(B3:G3) -> 25 | J3: Техногенные ЧС | K3: =M84 -> 262
A4: 2002 | B4: =COUNTIFS(Реестр_ЧС!$D$2:$D$797,Анализ_ЧС!B$2,Реестр_ЧС!$K$2:$K$797,Анализ_ЧС!$A4) -> 0 | C4: =COUNTIFS(Реестр_ЧС!$D$2:$D$797,Анализ_ЧС!C$2,Реестр_ЧС!$K$2:$K$797,Анализ_ЧС!$A4) -> 2 | D4: =COUNTIFS(Реестр_ЧС!$D$2:$D$797,Анализ_ЧС!D$2,Реестр_ЧС!$K$2:$K$797,Анализ_ЧС!$A4) -> 0 | E4: =COUNTIFS(Реестр_ЧС!$D$2:$D$797,Анализ_ЧС!E$2,Реестр_ЧС!$K$2:$K$797,Анализ_ЧС!$A4) -> 3 | F4: =COUNTIFS(Реестр_ЧС!$D$2:$D$797,Анализ_ЧС!F$2,Реестр_ЧС!$K$2:$K$797,Анализ_ЧС!$A4) -> 0 | G4: =COUNTIFS(Реестр_ЧС!$D$2:$D$797,Анализ_ЧС!G$2,Реестр_ЧС!$K$2:$K$797,Анализ_ЧС!$A4) -> 3 | H4: =SUM(B4:G4) -> 8 | J4: Биолого-соц ЧС | K4: =F112 -> 35
A5: 2003 | B5: =COUNTIFS(Реестр_ЧС!$D$2:$D$797,Анализ_ЧС!B$2,Реестр_ЧС!$K$2:$K$797,Анализ_ЧС!$A5) -> 13 | C5: =COUNTIFS(Реестр_ЧС!$D$2:$D$797,Анализ_ЧС!C$2,Реестр_ЧС!$K$2:$K$797,Анализ_ЧС!$A5) -> 6 | D5: =COUNTIFS(Реестр_ЧС!$D$2:$D$797,Анализ_ЧС!D$2,Реестр_ЧС!$K$2:$K$797,Анализ_ЧС!$A5) -> 0 | E5: =COUNTIFS(Реестр_ЧС!$D$2:$D$797,Анализ_ЧС!E$2,Реестр_ЧС!$K$2:$K$797,Анализ_ЧС!$A5) -> 2 | F5: =COUNTIFS(Реестр_ЧС!$D$2:$D$797,Анализ_ЧС!F$2,Реестр_ЧС!$K$2:$K$797,Анализ_ЧС!$A5) -> 0 | G5: =COUNTIFS(Реестр_ЧС!$D$2:$D$797,Анализ_ЧС!G$2,Реестр_ЧС!$K$2:$K$797,Анализ_ЧС!$A5) -> 0 | H5: =SUM(B5:G5) -> 21 | J5: Всего | K5: =K2+K3+K4 -> 732
A6: 2004 | B6: =COUNTIFS(Реестр_ЧС!$D$2:$D$797,Анализ_ЧС!B$2,Реестр_ЧС!$K$2:$K$797,Анализ_ЧС!$A6) -> 12 | C6: =COUNTIFS(Реестр_ЧС!$D$2:$D$797,Анализ_ЧС!C$2,Реестр_ЧС!$K$2:$K$797,Анализ_ЧС!$A6) -> 7 | D6: =COUNTIFS(Реестр_ЧС!$D$2:$D$797,Анализ_ЧС!D$2,Реестр_ЧС!$K$2:$K$797,Анализ_ЧС!$A6) -> 0 | E6: =COUNTIFS(Реестр_ЧС!$D$2:$D$797,Анализ_ЧС!E$2,Реестр_ЧС!$K$2:$K$797,Анализ_ЧС!$A6) -> 4 | F6: =COUNTIFS(Реестр_ЧС!$D$2:$D$797,Анализ_ЧС!F$2,Реестр_ЧС!$K$2:$K$797,Анализ_ЧС!$A6) -> 0 | G6: =COUNTIFS(Реестр_ЧС!$D$2:$D$797,Анализ_ЧС!G$2,Реестр_ЧС!$K$2:$K$797,Анализ_ЧС!$A6) -> 0 | H6: =SUM(B6:G6) -> 23
A7: 2005 | B7: =COUNTIFS(Реестр_ЧС!$D$2:$D$797,Анализ_ЧС!B$2,Реестр_ЧС!$K$2:$K$797,Анализ_ЧС!$A7) -> 26 | C7: =COUNTIFS(Реестр_ЧС!$D$2:$D$797,Анализ_ЧС!C$2,Реестр_ЧС!$K$2:$K$797,Анализ_ЧС!$A7) -> 4 | D7: =COUNTIFS(Реестр_ЧС!$D$2:$D$797,Анализ_ЧС!D$2,Реестр_ЧС!$K$2:$K$797,Анализ_ЧС!$A7) -> 0 | E7: =COUNTIFS(Реестр_ЧС!$D$2:$D$797,Анализ_ЧС!E$2,Реестр_ЧС!$K$2:$K$797,Анализ_ЧС!$A7) -> 1 | F7: =COUNTIFS(Реестр_ЧС!$D$2:$D$797,Анализ_ЧС!F$2,Реестр_ЧС!$K$2:$K$797,Анализ_ЧС!$A7) -> 0 | G7: =COUNTIFS(Реестр_ЧС!$D$2:$D$797,Анализ_ЧС!G$2,Реестр_ЧС!$K$2:$K$797,Анализ_ЧС!$A7) -> 0 | H7: =SUM(B7:G7) -> 31
A8: 2006 | B8: =COUNTIFS(Реестр_ЧС!$D$2:$D$797,Анализ_ЧС!B$2,Реестр_ЧС!$K$2:$K$797,Анализ_ЧС!$A8) -> 33 | C8: =COUNTIFS(Реестр_ЧС!$D$2:$D$797,Анализ_ЧС!C$2,Реестр_ЧС!$K$2:$K$797,Анализ_ЧС!$A8) -> 5 | D8: =COUNTIFS(Реестр_ЧС!$D$2:$D$797,Анализ_ЧС!D$2,Реестр_ЧС!$K$2:$K$797,Анализ_ЧС!$A8) -> 0 | E8: =COUNTIFS(Реестр_ЧС!$D$2:$D$797,Анализ_ЧС!E$2,Реестр_ЧС!$K$2:$K$797,Анализ_ЧС!$A8) -> 0 | F8: =COUNTIFS(Реестр_ЧС!$D$2:$D$797,Анализ_ЧС!F$2,Реестр_ЧС!$K$2:$K$797,Анализ_ЧС!$A8) -> 0 | G8: =COUNTIFS(Реестр_ЧС!$D$2:$D$797,Анализ_ЧС!G$2,Реестр_ЧС!$K$2:$K$797,Анализ_ЧС!$A8) -> 0 | H8: =SUM(B8:G8) -> 38
A9: 2007 | B9: =COUNTIFS(Реестр_ЧС!$D$2:$D$797,Анализ_ЧС!B$2,Реестр_ЧС!$K$2:$K$797,Анализ_ЧС!$A9) -> 0 | C9: =COUNTIFS(Реестр_ЧС!$D$2:$D$797,Анализ_ЧС!C$2,Реестр_ЧС!$K$2:$K$797,Анализ_ЧС!$A9) -> 0 | D9: =COUNTIFS(Реестр_ЧС!$D$2:$D$797,Анализ_ЧС!D$2,Реестр_ЧС!$K$2:$K$797,Анализ_ЧС!$A9) -> 0 | E9: =COUNTIFS(Реестр_ЧС!$D$2:$D$797,Анализ_ЧС!E$2,Реестр_ЧС!$K$2:$K$797,Анализ_ЧС!$A9) -> 0 | F9: =COUNTIFS(Реестр_ЧС!$D$2:$D$797,Анализ_ЧС!F$2,Реестр_ЧС!$K$2:$K$797,Анализ_ЧС!$A9) -> 0 | G9: =COUNTIFS(Реестр_ЧС!$D$2:$D$797,Анализ_ЧС!G$2,Реестр_ЧС!$K$2:$K$797,Анализ_ЧС!$A9) -> 0 | H9: =SUM(B9:G9) -> 0
A10: 2008 | B10: =COUNTIFS(Реестр_ЧС!$D$2:$D$797,Анализ_ЧС!B$2,Реестр_ЧС!$K$2:$K$797,Анализ_ЧС!$A10) -> 30 | C10: =COUNTIFS(Реестр_ЧС!$D$2:$D$797,Анализ_ЧС!C$2,Реестр_ЧС!$K$2:$K$797,Анализ_ЧС!$A10) -> 22 | D10: =COUNTIFS(Реестр_ЧС!$D$2:$D$797,Анализ_ЧС!D$2,Реестр_ЧС!$K$2:$K$797,Анализ_ЧС!$A10) -> 3 | E10: =COUNTIFS(Реестр_ЧС!$D$2:$D$797,Анализ_ЧС!E$2,Реестр_ЧС!$K$2:$K$797,Анализ_ЧС!$A10) -> 0 | F10: =COUNTIFS(Реестр_ЧС!$D$2:$D$797,Анализ_ЧС!F$2,Реестр_ЧС!$K$2:$K$797,Анализ_ЧС!$A10) -> 0 | G10: =COUNTIFS(Реестр_ЧС!$D$2:$D$797,Анализ_ЧС!G$2,Реестр_ЧС!$K$2:$K$797,Анализ_ЧС!$A10) -> 0 | H10: =SUM(B10:G10) -> 55
A11: 2009 | B11: =COUNTIFS(Реестр_ЧС!$D$2:$D$797,Анализ_ЧС!B$2,Реестр_ЧС!$K$2:$K$797,Анализ_ЧС!$A11) -> 0 | C11: =COUNTIFS(Реестр_ЧС!$D$2:$D$797,Анализ_ЧС!C$2,Реестр_ЧС!$K$2:$K$797,Анализ_ЧС!$A11) -> 2 | D11: =COUNTIFS(Реестр_ЧС!$D$2:$D$797,Анализ_ЧС!D$2,Реестр_ЧС!$K$2:$K$797,Анализ_ЧС!$A11) -> 0 | E11: =COUNTIFS(Реестр_ЧС!$D$2:$D$797,Анализ_ЧС!E$2,Реестр_ЧС!$K$2:$K$797,Анализ_ЧС!$A11) -> 0 | F11: =COUNTIFS(Реестр_ЧС!$D$2:$D$797,Анализ_ЧС!F$2,Реестр_ЧС!$K$2:$K$797,Анализ_ЧС!$A11) -> 0 | G11: =COUNTIFS(Реестр_ЧС!$D$2:$D$797,Анализ_ЧС!G$2,Реестр_ЧС!$K$2:$K$797,Анализ_ЧС!$A11) -> 0 | H11: =SUM(B11:G11) -> 2
A12: 2010 | B12: =COUNTIFS(Реестр_ЧС!$D$2:$D$797,Анализ_ЧС!B$2,Реестр_ЧС!$K$2:$K$797,Анализ_ЧС!$A12) -> 1 | C12: =COUNTIFS(Реестр_ЧС!$D$2:$D$797,Анализ_ЧС!C$2,Реестр_ЧС!$K$2:$K$797,Анализ_ЧС!$A12) -> 6 | D12: =COUNTIFS(Реестр_ЧС!$D$2:$D$797,Анализ_ЧС!D$2,Реестр_ЧС!$K$2:$K$797,Анализ_ЧС!$A12) -> 0 | E12: =COUNTIFS(Реестр_ЧС!$D$2:$D$797,Анализ_ЧС!E$2,Реестр_ЧС!$K$2:$K$797,Анализ_ЧС!$A12) -> 0 | F12: =COUNTIFS(Реестр_ЧС!$D$2:$D$797,Анализ_ЧС!F$2,Реестр_ЧС!$K$2:$K$797,Анализ_ЧС!$A12) -> 0 | G12: =COUNTIFS(Реестр_ЧС!$D$2:$D$797,Анализ_ЧС!G$2,Реестр_ЧС!$K$2:$K$797,Анализ_ЧС!$A12) -> 0 | H12: =SUM(B12:G12) -> 7
A13: 2011 | B13: =COUNTIFS(Реестр_ЧС!$D$2:$D$797,Анализ_ЧС!B$2,Реестр_ЧС!$K$2:$K$797,Анализ_ЧС!$A13) -> 0 | C13: =COUNTIFS(Реестр_ЧС!$D$2:$D$797,Анализ_ЧС!C$2,Реестр_ЧС!$K$2:$K$797,Анализ_ЧС!$A13) -> 5 | D13: =COUNTIFS(Реестр_ЧС!$D$2:$D$797,Анализ_ЧС!D$2,Реестр_ЧС!$K$2:$K$797,Анализ_ЧС!$A13) -> 1 | E13: =COUNTIFS(Реестр_ЧС!$D$2:$D$797,Анализ_ЧС!E$2,Реестр_ЧС!$K$2:$K$797,Анализ_ЧС!$A13) -> 1 | F13: =COUNTIFS(Реестр_ЧС!$D$2:$D$797,Анализ_ЧС!F$2,Реестр_ЧС!$K$2:$K$797,Анализ_ЧС!$A13) -> 0 | G13: =COUNTIFS(Реестр_ЧС!$D$2:$D$797,Анализ_ЧС!G$2,Реестр_ЧС!$K$2:$K$797,Анализ_ЧС!$A13) -> 0 | H13: =SUM(B13:G13) -> 7
A14: 2012 | B14: =COUNTIFS(Реестр_ЧС!$D$2:$D$797,Анализ_ЧС!B$2,Реестр_ЧС!$K$2:$K$797,Анализ_ЧС!$A14) -> 5 | C14: =COUNTIFS(Реестр_ЧС!$D$2:$D$797,Анализ_ЧС!C$2,Реестр_ЧС!$K$2:$K$797,Анализ_ЧС!$A14) -> 17 | D14: =COUNTIFS(Реестр_ЧС!$D$2:$D$797,Анализ_ЧС!D$2,Реестр_ЧС!$K$2:$K$797,Анализ_ЧС!$A14) -> 2 | E14: =COUNTIFS(Реестр_ЧС!$D$2:$D$797,Анализ_ЧС!E$2,Реестр_ЧС!$K$2:$K$797,Анализ_ЧС!$A14) -> 4 | F14: =COUNTIFS(Реестр_ЧС!$D$2:$D$797,Анализ_ЧС!F$2,Реестр_ЧС!$K$2:$K$797,Анализ_ЧС!$A14) -> 0 | G14: =COUNTIFS(Реестр_ЧС!$D$2:$D$797,Анализ_ЧС!G$2,Реестр_ЧС!$K$2:$K$797,Анализ_ЧС!$A14) -> 0 | H14: =SUM(B14:G14) -> 28
A15: 2013 | B15: =COUNTIFS(Реестр_ЧС!$D$2:$D$797,Анализ_ЧС!B$2,Реестр_ЧС!$K$2:$K$797,Анализ_ЧС!$A15) -> 0 | C15: =COUNTIFS(Реестр_ЧС!$D$2:$D$797,Анализ_ЧС!C$2,Реестр_ЧС!$K$2:$K$797,Анализ_ЧС!$A15) -> 7 | D15: =COUNTIFS(Реестр_ЧС!$D$2:$D$797,Анализ_ЧС!D$2,Реестр_ЧС!$K$2:$K$797,Анализ_ЧС!$A15) -> 3 | E15: =COUNTIFS(Реестр_ЧС!$D$2:$D$797,Анализ_ЧС!E$2,Реестр_ЧС!$K$2:$K$797,Анализ_ЧС!$A15) -> 6 | F15: =COUNTIFS(Реестр_ЧС!$D$2:$D$797,Анализ_ЧС!F$2,Реестр_ЧС!$K$2:$K$797,Анализ_ЧС!$A15) -> 0 | G15: =COUNTIFS(Реестр_ЧС!$D$2:$D$797,Анализ_ЧС!G$2,Реестр_ЧС!$K$2:$K$797,Анализ_ЧС!$A15) -> 0 | H15: =SUM(B15:G15) -> 16
A16: 2014 | B16: =COUNTIFS(Реестр_ЧС!$D$2:$D$797,Анализ_ЧС!B$2,Реестр_ЧС!$K$2:$K$797,Анализ_ЧС!$A16) -> 1 | C16: =COUNTIFS(Реестр_ЧС!$D$2:$D$797,Анализ_ЧС!C$2,Реестр_ЧС!$K$2:$K$797,Анализ_ЧС!$A16) -> 6 | D16: =COUNTIFS(Реестр_ЧС!$D$2:$D$797,Анализ_ЧС!D$2,Реестр_ЧС!$K$2:$K$797,Анализ_ЧС!$A16) -> 0 | E16: =COUNTIFS(Реестр_ЧС!$D$2:$D$797,Анализ_ЧС!E$2,Реестр_ЧС!$K$2:$K$797,Анализ_ЧС!$A16) -> 5 | F16: =COUNTIFS(Реестр_ЧС!$D$2:$D$797,Анализ_ЧС!F$2,Реестр_ЧС!$K$2:$K$797,Анализ_ЧС!$A16) -> 0 | G16: =COUNTIFS(Реестр_ЧС!$D$2:$D$797,Анализ_ЧС!G$2,Реестр_ЧС!$K$2:$K$797,Анализ_ЧС!$A16) -> 0 | H16: =SUM(B16:G16) -> 12
A17: 2015 | B17: =COUNTIFS(Реестр_ЧС!$D$2:$D$797,Анализ_ЧС!B$2,Реестр_ЧС!$K$2:$K$797,Анализ_ЧС!$A17) -> 3 | C17: =COUNTIFS(Реестр_ЧС!$D$2:$D$797,Анализ_ЧС!C$2,Реестр_ЧС!$K$2:$K$797,Анализ_ЧС!$A17) -> 3 | D17: =COUNTIFS(Реестр_ЧС!$D$2:$D$797,Анализ_ЧС!D$2,Реестр_ЧС!$K$2:$K$797,Анализ_ЧС!$A17) -> 0 | E17: =COUNTIFS(Реестр_ЧС!$D$2:$D$797,Анализ_ЧС!E$2,Реестр_ЧС!$K$2:$K$797,Анализ_ЧС!$A17) -> 0 | F17: =COUNTIFS(Реестр_ЧС!$D$2:$D$797,Анализ_ЧС!F$2,Реестр_ЧС!$K$2:$K$797,Анализ_ЧС!$A17) -> 0 | G17: =COUNTIFS(Реестр_ЧС!$D$2:$D$797,Анализ_ЧС!G$2,Реестр_ЧС!$K$2:$K$797,Анализ_ЧС!$A17) -> 0 | H17: =SUM(B17:G17) -> 6
... A20: 2018 | B20: =COUNTIFS(Реестр_ЧС!$D$2:$D$797,Анализ_ЧС!B$2,Реестр_ЧС!$K$2:$K$797,Анализ_ЧС!$A20) -> 1 | C20: =COUNTIFS(Реестр_ЧС!$D$2:$D$797,Анализ_ЧС!C$2,Реестр_ЧС!$K$2:$K$797,Анализ_ЧС!$A20) -> 65 | D20: =COUNTIFS(Реестр_ЧС!$D$2:$D$797,Анализ_ЧС!D$2,Реестр_ЧС!$K$2:$K$797,Анализ_ЧС!$A20) -> 5 | E20: =COUNTIFS(Реестр_ЧС!$D$2:$D$797,Анализ_ЧС!E$2,Реестр_ЧС!$K$2:$K$797,Анализ_ЧС!$A20) -> 9 | F20: =COUNTIFS(Реестр_ЧС!$D$2:$D$797,Анализ_ЧС!F$2,Реестр_ЧС!$K$2:$K$797,Анализ_ЧС!$A20) -> 0 | G20: =COUNTIFS(Реестр_ЧС!$D$2:$D$797,Анализ_ЧС!G$2,Реестр_ЧС!$K$2:$K$797,Анализ_ЧС!$A20) -> 1 | H20: =SUM(B20:G20) -> 81
A21: 2019 | B21: =COUNTIFS(Реестр_ЧС!$D$2:$D$797,Анализ_ЧС!B$2,Реестр_ЧС!$K$2:$K$797,Анализ_ЧС!$A21) -> 2 | C21: =COUNTIFS(Реестр_ЧС!$D$2:$D$797,Анализ_ЧС!C$2,Реестр_ЧС!$K$2:$K$797,Анализ_ЧС!$A21) -> 53 | D21: =COUNTIFS(Реестр_ЧС!$D$2:$D$797,Анализ_ЧС!D$2,Реестр_ЧС!$K$2:$K$797,Анализ_ЧС!$A21) -> 3 | E21: =COUNTIFS(Реестр_ЧС!$D$2:$D$797,Анализ_ЧС!E$2,Реестр_ЧС!$K$2:$K$797,Анализ_ЧС!$A21) -> 1 | F21: =COUNTIFS(Реестр_ЧС!$D$2:$D$797,Анализ_ЧС!F$2,Реестр_ЧС!$K$2:$K$797,Анализ_ЧС!$A21) -> 0 | G21: =COUNTIFS(Реестр_ЧС!$D$2:$D$797,Анализ_ЧС!G$2,Реестр_ЧС!$K$2:$K$797,Анализ_ЧС!$A21) -> 0 | H21: =SUM(B21:G21) -> 59 | J21: Кол-во ошибок | K21: =I28-K5 -> 2
A22: 2020 | B22: =COUNTIFS(Реестр_ЧС!$D$2:$D$797,Анализ_ЧС!B$2,Реестр_ЧС!$K$2:$K$797,Анализ_ЧС!$A22) -> 0 | C22: =COUNTIFS(Реестр_ЧС!$D$2:$D$797,Анализ_ЧС!C$2,Реестр_ЧС!$K$2:$K$797,Анализ_ЧС!$A22) -> 46 | D22: =COUNTIFS(Реестр_ЧС!$D$2:$D$797,Анализ_ЧС!D$2,Реестр_ЧС!$K$2:$K$797,Анализ_ЧС!$A22) -> 2 | E22: =COUNTIFS(Реестр_ЧС!$D$2:$D$797,Анализ_ЧС!E$2,Реестр_ЧС!$K$2:$K$797,Анализ_ЧС!$A22) -> 1 | F22: =COUNTIFS(Реестр_ЧС!$D$2:$D$797,Анализ_ЧС!F$2,Реестр_ЧС!$K$2:$K$797,Анализ_ЧС!$A22) -> 0 | G22: =COUNTIFS(Реестр_ЧС!$D$2:$D$797,Анализ_ЧС!G$2,Реестр_ЧС!$K$2:$K$797,Анализ_ЧС!$A22) -> 0 | H22: =SUM(B22:G22) -> 49
A23: 2021 | B23: =COUNTIFS(Реестр_ЧС!$D$2:$D$797,Анализ_ЧС!B$2,Реестр_ЧС!$K$2:$K$797,Анализ_ЧС!$A23) -> 0 | C23: =COUNTIFS(Реестр_ЧС!$D$2:$D$797,Анализ_ЧС!C$2,Реестр_ЧС!$K$2:$K$797,Анализ_ЧС!$A23) -> 45 | D23: =COUNTIFS(Реестр_ЧС!$D$2:$D$797,Анализ_ЧС!D$2,Реестр_ЧС!$K$2:$K$797,Анализ_ЧС!$A23) -> 0 | E23: =COUNTIFS(Реестр_ЧС!$D$2:$D$797,Анализ_ЧС!E$2,Реестр_ЧС!$K$2:$K$797,Анализ_ЧС!$A23) -> 3 | F23: =COUNTIFS(Реестр_ЧС!$D$2:$D$797,Анализ_ЧС!F$2,Реестр_ЧС!$K$2:$K$797,Анализ_ЧС!$A23) -> 1 | G23: =COUNTIFS(Реестр_ЧС!$D$2:$D$797,Анализ_ЧС!G$2,Реестр_ЧС!$K$2:$K$797,Анализ_ЧС!$A23) -> 0 | H23: =SUM(B23:G23) -> 49
A24: 2022 | B24: =COUNTIFS(Реестр_ЧС!$D$2:$D$797,Анализ_ЧС!B$2,Реестр_ЧС!$K$2:$K$797,Анализ_ЧС!$A24) -> 1 | C24: =COUNTIFS(Реестр_ЧС!$D$2:$D$797,Анализ_ЧС!C$2,Реестр_ЧС!$K$2:$K$797,Анализ_ЧС!$A24) -> 35 | D24: =COUNTIFS(Реестр_ЧС!$D$2:$D$797,Анализ_ЧС!D$2,Реестр_ЧС!$K$2:$K$797,Анализ_ЧС!$A24) -> 0 | E24: =COUNTIFS(Реестр_ЧС!$D$2:$D$797,Анализ_ЧС!E$2,Реестр_ЧС!$K$2:$K$797,Анализ_ЧС!$A24) -> 2 | F24: =COUNTIFS(Реестр_ЧС!$D$2:$D$797,Анализ_ЧС!F$2,Реестр_ЧС!$K$2:$K$797,Анализ_ЧС!$A24) -> 0 | G24: =COUNTIFS(Реестр_ЧС!$D$2:$D$797,Анализ_ЧС!G$2,Реестр_ЧС!$K$2:$K$797,Анализ_ЧС!$A24) -> 1 | H24: =SUM(B24:G24) -> 39
A25: 2023 | B25: =COUNTIFS(Реестр_ЧС!$D$2:$D$797,Анализ_ЧС!B$2,Реестр_ЧС!$K$2:$K$797,Анализ_ЧС!$A25) -> 1 | C25: =COUNTIFS(Реестр_ЧС!$D$2:$D$797,Анализ_ЧС!C$2,Реестр_ЧС!$K$2:$K$797,Анализ_ЧС!$A25) -> 31 | D25: =COUNTIFS(Реестр_ЧС!$D$2:$D$797,Анализ_ЧС!D$2,Реестр_ЧС!$K$2:$K$797,Анализ_ЧС!$A25) -> 0 | E25: =COUNTIFS(Реестр_ЧС!$D$2:$D$797,Анализ_ЧС!E$2,Реестр_ЧС!$K$2:$K$797,Анализ_ЧС!$A25) -> 1 | F25: =COUNTIFS(Реестр_ЧС!$D$2:$D$797,Анализ_ЧС!F$2,Реестр_ЧС!$K$2:$K$797,Анализ_ЧС!$A25) -> 1 | G25: =COUNTIFS(Реестр_ЧС!$D$2:$D$797,Анализ_ЧС!G$2,Реестр_ЧС!$K$2:$K$797,Анализ_ЧС!$A25) -> 0 | H25: =SUM(B25:G25) -> 34
A26: 2024 | B26: =COUNTIFS(Реестр_ЧС!$D$2:$D$797,Анализ_ЧС!B$2,Реестр_ЧС!$K$2:$K$797,Анализ_ЧС!$A26) -> 0 | C26: =COUNTIFS(Реестр_ЧС!$D$2:$D$797,Анализ_ЧС!C$2,Реестр_ЧС!$K$2:$K$797,Анализ_ЧС!$A26) -> 45 | D26: =COUNTIFS(Реестр_ЧС!$D$2:$D$797,Анализ_ЧС!D$2,Реестр_ЧС!$K$2:$K$797,Анализ_ЧС!$A26) -> 0 | E26: =COUNTIFS(Реестр_ЧС!$D$2:$D$797,Анализ_ЧС!E$2,Реестр_ЧС!$K$2:$K$797,Анализ_ЧС!$A26) -> 2 | F26: =COUNTIFS(Реестр_ЧС!$D$2:$D$797,Анализ_ЧС!F$2,Реестр_ЧС!$K$2:$K$797,Анализ_ЧС!$A26) -> 0 | G26: =COUNTIFS(Реестр_ЧС!$D$2:$D$797,Анализ_ЧС!G$2,Реестр_ЧС!$K$2:$K$797,Анализ_ЧС!$A26) -> 2 | H26: =SUM(B26:G26) -> 49
A27: 2025 | B27: =COUNTIFS(Реестр_ЧС!$D$2:$D$797,Анализ_ЧС!B$2,Реестр_ЧС!$K$2:$K$797,Анализ_ЧС!$A27) -> 2 | C27: =COUNTIFS(Реестр_ЧС!$D$2:$D$797,Анализ_ЧС!C$2,Реестр_ЧС!$K$2:$K$797,Анализ_ЧС!$A27) -> 21 | D27: =COUNTIFS(Реестр_ЧС!$D$2:$D$797,Анализ_ЧС!D$2,Реестр_ЧС!$K$2:$K$797,Анализ_ЧС!$A27) -> 0 | E27: =COUNTIFS(Реестр_ЧС!$D$2:$D$797,Анализ_ЧС!E$2,Реестр_ЧС!$K$2:$K$797,Анализ_ЧС!$A27) -> 1 | F27: =COUNTIFS(Реестр_ЧС!$D$2:$D$797,Анализ_ЧС!F$2,Реестр_ЧС!$K$2:$K$797,Анализ_ЧС!$A27) -> 0 | G27: =COUNTIFS(Реестр_ЧС!$D$2:$D$797,Анализ_ЧС!G$2,Реестр_ЧС!$K$2:$K$797,Анализ_ЧС!$A27) -> 0 | H27: =SUM(B27:G27) -> 24
A28: Итого | B28: =SUM(B3:B27) -> 153 | C28: =SUM(C3:C27) -> 497 | D28: =SUM(D3:D27) -> 20 | E28: =SUM(E3:E27) -> 49 | F28: =SUM(F3:F27) -> 2 | G28: =SUM(G3:G27) -> 11 | H28: =SUM(B3:G27) -> 732 | I28: 734 | J28: по нумерации Реестр_ЧС
A29: Реестр природных ЧС
B30: Весеннее половодье | C30: Неблагоприятные погодные условия | D30: Летне-осенний паводок | E30: Природные пожары | F30: Засуха | G30: Землетрясение | H30: ВСЕГО
A31: 2001 | B31: =COUNTIFS(Реестр_ЧС!$L$2:$L$797,Анализ_ЧС!B$30,Реестр_ЧС!$K$2:$K$797,Анализ_ЧС!$A31) -> 0 | C31: =COUNTIFS(Реестр_ЧС!$L$2:$L$797,Анализ_ЧС!C$30,Реестр_ЧС!$K$2:$K$797,Анализ_ЧС!$A31) -> 0 | D31: =COUNTIFS(Реестр_ЧС!$L$2:$L$797,Анализ_ЧС!D$30,Реестр_ЧС!$K$2:$K$797,Анализ_ЧС!$A31) -> 0 | E31: =COUNTIFS(Реестр_ЧС!$L$2:$L$797,Анализ_ЧС!E$30,Реестр_ЧС!$K$2:$K$797,Анализ_ЧС!$A31) -> 0 | F31: =COUNTIFS(Реестр_ЧС!$L$2:$L$797,Анализ_ЧС!F$30,Реестр_ЧС!$K$2:$K$797,Анализ_ЧС!$A31) -> 0 | G31: =COUNTIFS(Реестр_ЧС!$L$2:$L$797,Анализ_ЧС!G$30,Реестр_ЧС!$K$2:$K$797,Анализ_ЧС!$A31) -> 0 | H31: =SUM(B31:G31) -> 0
A32: 2002 | B32: =COUNTIFS(Реестр_ЧС!$L$2:$L$797,Анализ_ЧС!B$30,Реестр_ЧС!$K$2:$K$797,Анализ_ЧС!$A32) -> 0 | C32: =COUNTIFS(Реестр_ЧС!$L$2:$L$797,Анализ_ЧС!C$30,Реестр_ЧС!$K$2:$K$797,Анализ_ЧС!$A32) -> 0 | D32: =COUNTIFS(Реестр_ЧС!$L$2:$L$797,Анализ_ЧС!D$30,Реестр_ЧС!$K$2:$K$797,Анализ_ЧС!$A32) -> 0 | E32: =COUNTIFS(Реестр_ЧС!$L$2:$L$797,Анализ_ЧС!E$30,Реестр_ЧС!$K$2:$K$797,Анализ_ЧС!$A32) -> 0 | F32: =COUNTIFS(Реестр_ЧС!$L$2:$L$797,Анализ_ЧС!F$30,Реестр_ЧС!$K$2:$K$797,Анализ_ЧС!$A32) -> 0 | G32: =COUNTIFS(Реестр_ЧС!$L$2:$L$797,Анализ_ЧС!G$30,Реестр_ЧС!$K$2:$K$797,Анализ_ЧС!$A32) -> 0 | H32: =SUM(B32:G32) -> 0
A33: 2003 | B33: =COUNTIFS(Реестр_ЧС!$L$2:$L$797,Анализ_ЧС!B$30,Реестр_ЧС!$K$2:$K$797,Анализ_ЧС!$A33) -> 1 | C33: =COUNTIFS(Реестр_ЧС!$L$2:$L$797,Анализ_ЧС!C$30,Реестр_ЧС!$K$2:$K$797,Анализ_ЧС!$A33) -> 0 | D33: =COUNTIFS(Реестр_ЧС!$L$2:$L$797,Анализ_ЧС!D$30,Реестр_ЧС!$K$2:$K$797,Анализ_ЧС!$A33) -> 0 | E33: =COUNTIFS(Реестр_ЧС!$L$2:$L$797,Анализ_ЧС!E$30,Реестр_ЧС!$K$2:$K$797,Анализ_ЧС!$A33) -> 0 | F33: =COUNTIFS(Реестр_ЧС!$L$2:$L$797,Анализ_ЧС!F$30,Реестр_ЧС!$K$2:$K$797,Анализ_ЧС!$A33) -> 0 | G33: =COUNTIFS(Реестр_ЧС!$L$2:$L$797,Анализ_ЧС!G$30,Реестр_ЧС!$K$2:$K$797,Анализ_ЧС!$A33) -> 0 | H33: =SUM(B33:G33) -> 1
A34: 2004 | B34: =COUNTIFS(Реестр_ЧС!$L$2:$L$797,Анализ_ЧС!B$30,Реестр_ЧС!$K$2:$K$797,Анализ_ЧС!$A34) -> 0 | C34: =COUNTIFS(Реестр_ЧС!$L$2:$L$797,Анализ_ЧС!C$30,Реестр_ЧС!$K$2:$K$797,Анализ_ЧС!$A34) -> 0 | D34: =COUNTIFS(Реестр_ЧС!$L$2:$L$797,Анализ_ЧС!D$30,Реестр_ЧС!$K$2:$K$797,Анализ_ЧС!$A34) -> 5 | E34: =COUNTIFS(Реестр_ЧС!$L$2:$L$797,Анализ_ЧС!E$30,Реестр_ЧС!$K$2:$K$797,Анализ_ЧС!$A34) -> 1 | F34: =COUNTIFS(Реестр_ЧС!$L$2:$L$797,Анализ_ЧС!F$30,Реестр_ЧС!$K$2:$K$797,Анализ_ЧС!$A34) -> 0 | G34: =COUNTIFS(Реестр_ЧС!$L$2:$L$797,Анализ_ЧС!G$30,Реестр_ЧС!$K$2:$K$797,Анализ_ЧС!$A34) -> 0 | H34: =SUM(B34:G34) -> 6
A35: 2005 | B35: =COUNTIFS(Реестр_ЧС!$L$2:$L$797,Анализ_ЧС!B$30,Реестр_ЧС!$K$2:$K$797,Анализ_ЧС!$A35) -> 1 | C35: =COUNTIFS(Реестр_ЧС!$L$2:$L$797,Анализ_ЧС!C$30,Реестр_ЧС!$K$2:$K$797,Анализ_ЧС!$A35) -> 0 | D35: =COUNTIFS(Реестр_ЧС!$L$2:$L$797,Анализ_ЧС!D$30,Реестр_ЧС!$K$2:$K$797,Анализ_ЧС!$A35) -> 1 | E35: =COUNTIFS(Реестр_ЧС!$L$2:$L$797,Анализ_ЧС!E$30,Реестр_ЧС!$K$2:$K$797,Анализ_ЧС!$A35) -> 0 | F35: =COUNTIFS(Реестр_ЧС!$L$2:$L$797,Анализ_ЧС!F$30,Реестр_ЧС!$K$2:$K$797,Анализ_ЧС!$A35) -> 0 | G35: =COUNTIFS(Реестр_ЧС!$L$2:$L$797,Анализ_ЧС!G$30,Реестр_ЧС!$K$2:$K$797,Анализ_ЧС!$A35) -> 0 | H35: =SUM(B35:G35) -> 2
A36: 2006 | B36: =COUNTIFS(Реестр_ЧС!$L$2:$L$797,Анализ_ЧС!B$30,Реестр_ЧС!$K$2:$K$797,Анализ_ЧС!$A36) -> 0 | C36: =COUNTIFS(Реестр_ЧС!$L$2:$L$797,Анализ_ЧС!C$30,Реестр_ЧС!$K$2:$K$797,Анализ_ЧС!$A36) -> 1 | D36: =COUNTIFS(Реестр_ЧС!$L$2:$L$797,Анализ_ЧС!D$30,Реестр_ЧС!$K$2:$K$797,Анализ_ЧС!$A36) -> 2 | E36: =COUNTIFS(Реестр_ЧС!$L$2:$L$797,Анализ_ЧС!E$30,Реестр_ЧС!$K$2:$K$797,Анализ_ЧС!$A36) -> 0 | F36: =COUNTIFS(Реестр_ЧС!$L$2:$L$797,Анализ_ЧС!F$30,Реестр_ЧС!$K$2:$K$797,Анализ_ЧС!$A36) -> 0 | G36: =COUNTIFS(Реестр_ЧС!$L$2:$L$797,Анализ_ЧС!G$30,Реестр_ЧС!$K$2:$K$797,Анализ_ЧС!$A36) -> 3 | H36: =SUM(B36:G36) -> 6
A37: 2007 | B37: =COUNTIFS(Реестр_ЧС!$L$2:$L$797,Анализ_ЧС!B$30,Реестр_ЧС!$K$2:$K$797,Анализ_ЧС!$A37) -> 0 | C37: =COUNTIFS(Реестр_ЧС!$L$2:$L$797,Анализ_ЧС!C$30,Реестр_ЧС!$K$2:$K$797,Анализ_ЧС!$A37) -> 0 | D37: =COUNTIFS(Реестр_ЧС!$L$2:$L$797,Анализ_ЧС!D$30,Реестр_ЧС!$K$2:$K$797,Анализ_ЧС!$A37) -> 0 | E37: =COUNTIFS(Реестр_ЧС!$L$2:$L$797,Анализ_ЧС!E$30,Реестр_ЧС!$K$2:$K$797,Анализ_ЧС!$A37) -> 0 | F37: =COUNTIFS(Реестр_ЧС!$L$2:$L$797,Анализ_ЧС!F$30,Реестр_ЧС!$K$2:$K$797,Анализ_ЧС!$A37) -> 0 | G37: =COUNTIFS(Реестр_ЧС!$L$2:$L$797,Анализ_ЧС!G$30,Реестр_ЧС!$K$2:$K$797,Анализ_ЧС!$A37) -> 0 | H37: =SUM(B37:G37) -> 0
A38: 2008 | B38: =COUNTIFS(Реестр_ЧС!$L$2:$L$797,Анализ_ЧС!B$30,Реестр_ЧС!$K$2:$K$797,Анализ_ЧС!$A38) -> 7 | C38: =COUNTIFS(Реестр_ЧС!$L$2:$L$797,Анализ_ЧС!C$30,Реестр_ЧС!$K$2:$K$797,Анализ_ЧС!$A38) -> 0 | D38: =COUNTIFS(Реестр_ЧС!$L$2:$L$797,Анализ_ЧС!D$30,Реестр_ЧС!$K$2:$K$797,Анализ_ЧС!$A38) -> 1 | E38: =COUNTIFS(Реестр_ЧС!$L$2:$L$797,Анализ_ЧС!E$30,Реестр_ЧС!$K$2:$K$797,Анализ_ЧС!$A38) -> 1 | F38: =COUNTIFS(Реестр_ЧС!$L$2:$L$797,Анализ_ЧС!F$30,Реестр_ЧС!$K$2:$K$797,Анализ_ЧС!$A38) -> 0 | G38: =COUNTIFS(Реестр_ЧС!$L$2:$L$797,Анализ_ЧС!G$30,Реестр_ЧС!$K$2:$K$797,Анализ_ЧС!$A38) -> 0 | H38: =SUM(B38:G38) -> 9
A39: 2009 | B39: =COUNTIFS(Реестр_ЧС!$L$2:$L$797,Анализ_ЧС!B$30,Реестр_ЧС!$K$2:$K$797,Анализ_ЧС!$A39) -> 0 | C39: =COUNTIFS(Реестр_ЧС!$L$2:$L$797,Анализ_ЧС!C$30,Реестр_ЧС!$K$2:$K$797,Анализ_ЧС!$A39) -> 0 | D39: =COUNTIFS(Реестр_ЧС!$L$2:$L$797,Анализ_ЧС!D$30,Реестр_ЧС!$K$2:$K$797,Анализ_ЧС!$A39) -> 0 | E39: =COUNTIFS(Реестр_ЧС!$L$2:$L$797,Анализ_ЧС!E$30,Реестр_ЧС!$K$2:$K$797,Анализ_ЧС!$A39) -> 0 | F39: =COUNTIFS(Реестр_ЧС!$L$2:$L$797,Анализ_ЧС!F$30,Реестр_ЧС!$K$2:$K$797,Анализ_ЧС!$A39) -> 0 | G39: =COUNTIFS(Реестр_ЧС!$L$2:$L$797,Анализ_ЧС!G$30,Реестр_ЧС!$K$2:$K$797,Анализ_ЧС!$A39) -> 0 | H39: =SUM(B39:G39) -> 0
A40: 2010 | B40: =COUNTIFS(Реестр_ЧС!$L$2:$L$797,Анализ_ЧС!B$30,Реестр_ЧС!$K$2:$K$797,Анализ_ЧС!$A40) -> 5 | C40: =COUNTIFS(Реестр_ЧС!$L$2:$L$797,Анализ_ЧС!C$30,Реестр_ЧС!$K$2:$K$797,Анализ_ЧС!$A40) -> 0 | D40: =COUNTIFS(Реестр_ЧС!$L$2:$L$797,Анализ_ЧС!D$30,Реестр_ЧС!$K$2:$K$797,Анализ_ЧС!$A40) -> 0 | E40: =COUNTIFS(Реестр_ЧС!$L$2:$L$797,Анализ_ЧС!E$30,Реестр_ЧС!$K$2:$K$797,Анализ_ЧС!$A40) -> 0 | F40: =COUNTIFS(Реестр_ЧС!$L$2:$L$797,Анализ_ЧС!F$30,Реестр_ЧС!$K$2:$K$797,Анализ_ЧС!$A40) -> 0 | G40: =COUNTIFS(Реестр_ЧС!$L$2:$L$797,Анализ_ЧС!G$30,Реестр_ЧС!$K$2:$K$797,Анализ_ЧС!$A40) -> 0 | H40: =SUM(B40:G40) -> 5
A41: 2011 | B41: =COUNTIFS(Реестр_ЧС!$L$2:$L$797,Анализ_ЧС!B$30,Реестр_ЧС!$K$2:$K$797,Анализ_ЧС!$A41) -> 4 | C41: =COUNTIFS(Реестр_ЧС!$L$2:$L$797,Анализ_ЧС!C$30,Реестр_ЧС!$K$2:$K$797,Анализ_ЧС!$A41) -> 0 | D41: =COUNTIFS(Реестр_ЧС!$L$2:$L$797,Анализ_ЧС!D$30,Реестр_ЧС!$K$2:$K$797,Анализ_ЧС!$A41) -> 0 | E41: =COUNTIFS(Реестр_ЧС!$L$2:$L$797,Анализ_ЧС!E$30,Реестр_ЧС!$K$2:$K$797,Анализ_ЧС!$A41) -> 2 | F41: =COUNTIFS(Реестр_ЧС!$L$2:$L$797,Анализ_ЧС!F$30,Реестр_ЧС!$K$2:$K$797,Анализ_ЧС!$A41) -> 0 | G41: =COUNTIFS(Реестр_ЧС!$L$2:$L$797,Анализ_ЧС!G$30,Реестр_ЧС!$K$2:$K$797,Анализ_ЧС!$A41) -> 0 | H41: =SUM(B41:G41) -> 6
A42: 2012 | B42: =COUNTIFS(Реестр_ЧС!$L$2:$L$797,Анализ_ЧС!B$30,Реестр_ЧС!$K$2:$K$797,Анализ_ЧС!$A42) -> 10 | C42: =COUNTIFS(Реестр_ЧС!$L$2:$L$797,Анализ_ЧС!C$30,Реестр_ЧС!$K$2:$K$797,Анализ_ЧС!$A42) -> 0 | D42: =COUNTIFS(Реестр_ЧС!$L$2:$L$797,Анализ_ЧС!D$30,Реестр_ЧС!$K$2:$K$797,Анализ_ЧС!$A42) -> 1 | E42: =COUNTIFS(Реестр_ЧС!$L$2:$L$797,Анализ_ЧС!E$30,Реестр_ЧС!$K$2:$K$797,Анализ_ЧС!$A42) -> 12 | F42: =COUNTIFS(Реестр_ЧС!$L$2:$L$797,Анализ_ЧС!F$30,Реестр_ЧС!$K$2:$K$797,Анализ_ЧС!$A42) -> 0 | G42: =COUNTIFS(Реестр_ЧС!$L$2:$L$797,Анализ_ЧС!G$30,Реестр_ЧС!$K$2:$K$797,Анализ_ЧС!$A42) -> 0 | H42: =SUM(B42:G42) -> 23
... A55: 2025 | B55: =COUNTIFS(Реестр_ЧС!$L$2:$L$797,Анализ_ЧС!B$30,Реестр_ЧС!$K$2:$K$797,Анализ_ЧС!$A55) -> 2 | C55: =COUNTIFS(Реестр_ЧС!$L$2:$L$797,Анализ_ЧС!C$30,Реестр_ЧС!$K$2:$K$797,Анализ_ЧС!$A55) -> 0 | D55: =COUNTIFS(Реестр_ЧС!$L$2:$L$797,Анализ_ЧС!D$30,Реестр_ЧС!$K$2:$K$797,Анализ_ЧС!$A55) -> 4 | E55: =COUNTIFS(Реестр_ЧС!$L$2:$L$797,Анализ_ЧС!E$30,Реестр_ЧС!$K$2:$K$797,Анализ_ЧС!$A55) -> 9 | F55: =COUNTIFS(Реестр_ЧС!$L$2:$L$797,Анализ_ЧС!F$30,Реестр_ЧС!$K$2:$K$797,Анализ_ЧС!$A55) -> 0 | G55: =COUNTIFS(Реестр_ЧС!$L$2:$L$797,Анализ_ЧС!G$30,Реестр_ЧС!$K$2:$K$797,Анализ_ЧС!$A55) -> 0 | H55: =SUM(B55:G55) -> 15
A56: Итого | B56: =SUM(B31:B55) -> 139 | C56: =SUM(C31:C55) -> 12 | D56: =SUM(D31:D55) -> 80 | E56: =SUM(E31:E55) -> 197 | F56: =SUM(F31:F55) -> 4 | G56: =SUM(G31:G55) -> 3 | H56: =SUM(H31:H55) -> 435
A57: Реестр техногенных ЧС
B58: Дорожно-транспортные происшествия, на водном транспорте, АСР | C58: Разрушения дорожного полотна, моста | D58: Угроза аварии на ГТС | E58: Авиационные инциденты | F58: Объекты энергоснабжения | G58: Аварии на горных предприятиях | H58: Техногенные пожары | I58: Аварии в отопительный сезон | J58: Разлив нефтепродуктов | K58: Взрывы бытового газа, прорывы на газо-магистральной линии | L58: Поисковые работы | M58: Всего
A59: 2001 | B59: =COUNTIFS(Реестр_ЧС!$L$2:$L$797,Анализ_ЧС!B$58,Реестр_ЧС!$K$2:$K$797,Анализ_ЧС!$A59) -> 3 | C59: =COUNTIFS(Реестр_ЧС!$L$2:$L$797,Анализ_ЧС!C$58,Реестр_ЧС!$K$2:$K$797,Анализ_ЧС!$A59) -> 1 | D59: =COUNTIFS(Реестр_ЧС!$L$2:$L$797,Анализ_ЧС!D$58,Реестр_ЧС!$K$2:$K$797,Анализ_ЧС!$A59) -> 0 | E59: =COUNTIFS(Реестр_ЧС!$L$2:$L$797,Анализ_ЧС!E$58,Реестр_ЧС!$K$2:$K$797,Анализ_ЧС!$A59) -> 1 | F59: =COUNTIFS(Реестр_ЧС!$L$2:$L$797,Анализ_ЧС!F$58,Реестр_ЧС!$K$2:$K$797,Анализ_ЧС!$A59) -> 0 | G59: =COUNTIFS(Реестр_ЧС!$L$2:$L$797,Анализ_ЧС!G$58,Реестр_ЧС!$K$2:$K$797,Анализ_ЧС!$A59) -> 0 | H59: =COUNTIFS(Реестр_ЧС!$L$2:$L$797,Анализ_ЧС!H$58,Реестр_ЧС!$K$2:$K$797,Анализ_ЧС!$A59) -> 11 | I59: =COUNTIFS(Реестр_ЧС!$L$2:$L$797,Анализ_ЧС!I$58,Реестр_ЧС!$K$2:$K$797,Анализ_ЧС!$A59) -> 8 | ... L59: =COUNTIFS(Реестр_ЧС!$L$2:$L$797,Анализ_ЧС!L$58,Реестр_ЧС!$K$2:$K$797,Анализ_ЧС!$A59) -> 0 | M59: =SUM(B59:L59) -> 24
A60: 2002 | B60: =COUNTIFS(Реестр_ЧС!$L$2:$L$797,Анализ_ЧС!B$58,Реестр_ЧС!$K$2:$K$797,Анализ_ЧС!$A60) -> 0 | C60: =COUNTIFS(Реестр_ЧС!$L$2:$L$797,Анализ_ЧС!C$58,Реестр_ЧС!$K$2:$K$797,Анализ_ЧС!$A60) -> 0 | D60: =COUNTIFS(Реестр_ЧС!$L$2:$L$797,Анализ_ЧС!D$58,Реестр_ЧС!$K$2:$K$797,Анализ_ЧС!$A60) -> 0 | E60: =COUNTIFS(Реестр_ЧС!$L$2:$L$797,Анализ_ЧС!E$58,Реестр_ЧС!$K$2:$K$797,Анализ_ЧС!$A60) -> 0 | F60: =COUNTIFS(Реестр_ЧС!$L$2:$L$797,Анализ_ЧС!F$58,Реестр_ЧС!$K$2:$K$797,Анализ_ЧС!$A60) -> 0 | G60: =COUNTIFS(Реестр_ЧС!$L$2:$L$797,Анализ_ЧС!G$58,Реестр_ЧС!$K$2:$K$797,Анализ_ЧС!$A60) -> 0 | H60: =COUNTIFS(Реестр_ЧС!$L$2:$L$797,Анализ_ЧС!H$58,Реестр_ЧС!$K$2:$K$797,Анализ_ЧС!$A60) -> 2 | I60: =COUNTIFS(Реестр_ЧС!$L$2:$L$797,Анализ_ЧС!I$58,Реестр_ЧС!$K$2:$K$797,Анализ_ЧС!$A60) -> 6 | ... L60: =COUNTIFS(Реестр_ЧС!$L$2:$L$797,Анализ_ЧС!L$58,Реестр_ЧС!$K$2:$K$797,Анализ_ЧС!$A60) -> 0 | M60: =SUM(B60:L60) -> 8
A61: 2003 | B61: =COUNTIFS(Реестр_ЧС!$L$2:$L$797,Анализ_ЧС!B$58,Реестр_ЧС!$K$2:$K$797,Анализ_ЧС!$A61) -> 5 | C61: =COUNTIFS(Реестр_ЧС!$L$2:$L$797,Анализ_ЧС!C$58,Реестр_ЧС!$K$2:$K$797,Анализ_ЧС!$A61) -> 1 | D61: =COUNTIFS(Реестр_ЧС!$L$2:$L$797,Анализ_ЧС!D$58,Реестр_ЧС!$K$2:$K$797,Анализ_ЧС!$A61) -> 0 | E61: =COUNTIFS(Реестр_ЧС!$L$2:$L$797,Анализ_ЧС!E$58,Реестр_ЧС!$K$2:$K$797,Анализ_ЧС!$A61) -> 0 | F61: =COUNTIFS(Реестр_ЧС!$L$2:$L$797,Анализ_ЧС!F$58,Реестр_ЧС!$K$2:$K$797,Анализ_ЧС!$A61) -> 0 | G61: =COUNTIFS(Реестр_ЧС!$L$2:$L$797,Анализ_ЧС!G$58,Реестр_ЧС!$K$2:$K$797,Анализ_ЧС!$A61) -> 0 | H61: =COUNTIFS(Реестр_ЧС!$L$2:$L$797,Анализ_ЧС!H$58,Реестр_ЧС!$K$2:$K$797,Анализ_ЧС!$A61) -> 9 | I61: =COUNTIFS(Реестр_ЧС!$L$2:$L$797,Анализ_ЧС!I$58,Реестр_ЧС!$K$2:$K$797,Анализ_ЧС!$A61) -> 3 | ... L61: =COUNTIFS(Реестр_ЧС!$L$2:$L$797,Анализ_ЧС!L$58,Реестр_ЧС!$K$2:$K$797,Анализ_ЧС!$A61) -> 0 | M61: =SUM(B61:L61) -> 19
A62: 2004 | B62: =COUNTIFS(Реестр_ЧС!$L$2:$L$797,Анализ_ЧС!B$58,Реестр_ЧС!$K$2:$K$797,Анализ_ЧС!$A62) -> 5 | C62: =COUNTIFS(Реестр_ЧС!$L$2:$L$797,Анализ_ЧС!C$58,Реестр_ЧС!$K$2:$K$797,Анализ_ЧС!$A62) -> 0 | D62: =COUNTIFS(Реестр_ЧС!$L$2:$L$797,Анализ_ЧС!D$58,Реестр_ЧС!$K$2:$K$797,Анализ_ЧС!$A62) -> 0 | E62: =COUNTIFS(Реестр_ЧС!$L$2:$L$797,Анализ_ЧС!E$58,Реестр_ЧС!$K$2:$K$797,Анализ_ЧС!$A62) -> 0 | F62: =COUNTIFS(Реестр_ЧС!$L$2:$L$797,Анализ_ЧС!F$58,Реестр_ЧС!$K$2:$K$797,Анализ_ЧС!$A62) -> 0 | G62: =COUNTIFS(Реестр_ЧС!$L$2:$L$797,Анализ_ЧС!G$58,Реестр_ЧС!$K$2:$K$797,Анализ_ЧС!$A62) -> 0 | H62: =COUNTIFS(Реестр_ЧС!$L$2:$L$797,Анализ_ЧС!H$58,Реестр_ЧС!$K$2:$K$797,Анализ_ЧС!$A62) -> 9 | I62: =COUNTIFS(Реестр_ЧС!$L$2:$L$797,Анализ_ЧС!I$58,Реестр_ЧС!$K$2:$K$797,Анализ_ЧС!$A62) -> 3 | ... L62: =COUNTIFS(Реестр_ЧС!$L$2:$L$797,Анализ_ЧС!L$58,Реестр_ЧС!$K$2:$K$797,Анализ_ЧС!$A62) -> 0 | M62: =SUM(B62:L62) -> 17
A63: 2005 | B63: =COUNTIFS(Реестр_ЧС!$L$2:$L$797,Анализ_ЧС!B$58,Реестр_ЧС!$K$2:$K$797,Анализ_ЧС!$A63) -> 1 | C63: =COUNTIFS(Реестр_ЧС!$L$2:$L$797,Анализ_ЧС!C$58,Реестр_ЧС!$K$2:$K$797,Анализ_ЧС!$A63) -> 1 | D63: =COUNTIFS(Реестр_ЧС!$L$2:$L$797,Анализ_ЧС!D$58,Реестр_ЧС!$K$2:$K$797,Анализ_ЧС!$A63) -> 0 | E63: =COUNTIFS(Реестр_ЧС!$L$2:$L$797,Анализ_ЧС!E$58,Реестр_ЧС!$K$2:$K$797,Анализ_ЧС!$A63) -> 1 | F63: =COUNTIFS(Реестр_ЧС!$L$2:$L$797,Анализ_ЧС!F$58,Реестр_ЧС!$K$2:$K$797,Анализ_ЧС!$A63) -> 0 | G63: =COUNTIFS(Реестр_ЧС!$L$2:$L$797,Анализ_ЧС!G$58,Реестр_ЧС!$K$2:$K$797,Анализ_ЧС!$A63) -> 0 | H63: =COUNTIFS(Реестр_ЧС!$L$2:$L$797,Анализ_ЧС!H$58,Реестр_ЧС!$K$2:$K$797,Анализ_ЧС!$A63) -> 25 | I63: =COUNTIFS(Реестр_ЧС!$L$2:$L$797,Анализ_ЧС!I$58,Реестр_ЧС!$K$2:$K$797,Анализ_ЧС!$A63) -> 0 | ... L63: =COUNTIFS(Реестр_ЧС!$L$2:$L$797,Анализ_ЧС!L$58,Реестр_ЧС!$K$2:$K$797,Анализ_ЧС!$A63) -> 0 | M63: =SUM(B63:L63) -> 28
A64: 2006 | B64: =COUNTIFS(Реестр_ЧС!$L$2:$L$797,Анализ_ЧС!B$58,Реестр_ЧС!$K$2:$K$797,Анализ_ЧС!$A64) -> 3 | C64: =COUNTIFS(Реестр_ЧС!$L$2:$L$797,Анализ_ЧС!C$58,Реестр_ЧС!$K$2:$K$797,Анализ_ЧС!$A64) -> 0 | D64: =COUNTIFS(Реестр_ЧС!$L$2:$L$797,Анализ_ЧС!D$58,Реестр_ЧС!$K$2:$K$797,Анализ_ЧС!$A64) -> 0 | E64: =COUNTIFS(Реестр_ЧС!$L$2:$L$797,Анализ_ЧС!E$58,Реестр_ЧС!$K$2:$K$797,Анализ_ЧС!$A64) -> 1 | F64: =COUNTIFS(Реестр_ЧС!$L$2:$L$797,Анализ_ЧС!F$58,Реестр_ЧС!$K$2:$K$797,Анализ_ЧС!$A64) -> 0 | G64: =COUNTIFS(Реестр_ЧС!$L$2:$L$797,Анализ_ЧС!G$58,Реестр_ЧС!$K$2:$K$797,Анализ_ЧС!$A64) -> 0 | H64: =COUNTIFS(Реестр_ЧС!$L$2:$L$797,Анализ_ЧС!H$58,Реестр_ЧС!$K$2:$K$797,Анализ_ЧС!$A64) -> 25 | I64: =COUNTIFS(Реестр_ЧС!$L$2:$L$797,Анализ_ЧС!I$58,Реестр_ЧС!$K$2:$K$797,Анализ_ЧС!$A64) -> 0 | ... L64: =COUNTIFS(Реестр_ЧС!$L$2:$L$797,Анализ_ЧС!L$58,Реестр_ЧС!$K$2:$K$797,Анализ_ЧС!$A64) -> 0 | M64: =SUM(B64:L64) -> 31
A65: 2007 | B65: =COUNTIFS(Реестр_ЧС!$L$2:$L$797,Анализ_ЧС!B$58,Реестр_ЧС!$K$2:$K$797,Анализ_ЧС!$A65) -> 0 | C65: =COUNTIFS(Реестр_ЧС!$L$2:$L$797,Анализ_ЧС!C$58,Реестр_ЧС!$K$2:$K$797,Анализ_ЧС!$A65) -> 0 | D65: =COUNTIFS(Реестр_ЧС!$L$2:$L$797,Анализ_ЧС!D$58,Реестр_ЧС!$K$2:$K$797,Анализ_ЧС!$A65) -> 0 | E65: =COUNTIFS(Реестр_ЧС!$L$2:$L$797,Анализ_ЧС!E$58,Реестр_ЧС!$K$2:$K$797,Анализ_ЧС!$A65) -> 0 | F65: =COUNTIFS(Реестр_ЧС!$L$2:$L$797,Анализ_ЧС!F$58,Реестр_ЧС!$K$2:$K$797,Анализ_ЧС!$A65) -> 0 | G65: =COUNTIFS(Реестр_ЧС!$L$2:$L$797,Анализ_ЧС!G$58,Реестр_ЧС!$K$2:$K$797,Анализ_ЧС!$A65) -> 0 | H65: =COUNTIFS(Реестр_ЧС!$L$2:$L$797,Анализ_ЧС!H$58,Реестр_ЧС!$K$2:$K$797,Анализ_ЧС!$A65) -> 0 | I65: =COUNTIFS(Реестр_ЧС!$L$2:$L$797,Анализ_ЧС!I$58,Реестр_ЧС!$K$2:$K$797,Анализ_ЧС!$A65) -> 0 | ... L65: =COUNTIFS(Реестр_ЧС!$L$2:$L$797,Анализ_ЧС!L$58,Реестр_ЧС!$K$2:$K$797,Анализ_ЧС!$A65) -> 0 | M65: =SUM(B65:L65) -> 0
A66: 2008 | B66: =COUNTIFS(Реестр_ЧС!$L$2:$L$797,Анализ_ЧС!B$58,Реестр_ЧС!$K$2:$K$797,Анализ_ЧС!$A66) -> 1 | C66: =COUNTIFS(Реестр_ЧС!$L$2:$L$797,Анализ_ЧС!C$58,Реестр_ЧС!$K$2:$K$797,Анализ_ЧС!$A66) -> 0 | D66: =COUNTIFS(Реестр_ЧС!$L$2:$L$797,Анализ_ЧС!D$58,Реестр_ЧС!$K$2:$K$797,Анализ_ЧС!$A66) -> 0 | E66: =COUNTIFS(Реестр_ЧС!$L$2:$L$797,Анализ_ЧС!E$58,Реестр_ЧС!$K$2:$K$797,Анализ_ЧС!$A66) -> 0 | F66: =COUNTIFS(Реестр_ЧС!$L$2:$L$797,Анализ_ЧС!F$58,Реестр_ЧС!$K$2:$K$797,Анализ_ЧС!$A66) -> 1 | G66: =COUNTIFS(Реестр_ЧС!$L$2:$L$797,Анализ_ЧС!G$58,Реестр_ЧС!$K$2:$K$797,Анализ_ЧС!$A66) -> 0 | H66: =COUNTIFS(Реестр_ЧС!$L$2:$L$797,Анализ_ЧС!H$58,Реестр_ЧС!$K$2:$K$797,Анализ_ЧС!$A66) -> 19 | I66: =COUNTIFS(Реестр_ЧС!$L$2:$L$797,Анализ_ЧС!I$58,Реестр_ЧС!$K$2:$K$797,Анализ_ЧС!$A66) -> 3 | ... L66: =COUNTIFS(Реестр_ЧС!$L$2:$L$797,Анализ_ЧС!L$58,Реестр_ЧС!$K$2:$K$797,Анализ_ЧС!$A66) -> 0 | M66: =SUM(B66:L66) -> 24
A67: 2009 | B67: =COUNTIFS(Реестр_ЧС!$L$2:$L$797,Анализ_ЧС!B$58,Реестр_ЧС!$K$2:$K$797,Анализ_ЧС!$A67) -> 0 | C67: =COUNTIFS(Реестр_ЧС!$L$2:$L$797,Анализ_ЧС!C$58,Реестр_ЧС!$K$2:$K$797,Анализ_ЧС!$A67) -> 0 | D67: =COUNTIFS(Реестр_ЧС!$L$2:$L$797,Анализ_ЧС!D$58,Реестр_ЧС!$K$2:$K$797,Анализ_ЧС!$A67) -> 0 | E67: =COUNTIFS(Реестр_ЧС!$L$2:$L$797,Анализ_ЧС!E$58,Реестр_ЧС!$K$2:$K$797,Анализ_ЧС!$A67) -> 2 | F67: =COUNTIFS(Реестр_ЧС!$L$2:$L$797,Анализ_ЧС!F$58,Реестр_ЧС!$K$2:$K$797,Анализ_ЧС!$A67) -> 0 | G67: =COUNTIFS(Реестр_ЧС!$L$2:$L$797,Анализ_ЧС!G$58,Реестр_ЧС!$K$2:$K$797,Анализ_ЧС!$A67) -> 0 | H67: =COUNTIFS(Реестр_ЧС!$L$2:$L$797,Анализ_ЧС!H$58,Реестр_ЧС!$K$2:$K$797,Анализ_ЧС!$A67) -> 0 | I67: =COUNTIFS(Реестр_ЧС!$L$2:$L$797,Анализ_ЧС!I$58,Реестр_ЧС!$K$2:$K$797,Анализ_ЧС!$A67) -> 0 | ... L67: =COUNTIFS(Реестр_ЧС!$L$2:$L$797,Анализ_ЧС!L$58,Реестр_ЧС!$K$2:$K$797,Анализ_ЧС!$A67) -> 0 | M67: =SUM(B67:L67) -> 2
A68: 2010 | B68: =COUNTIFS(Реестр_ЧС!$L$2:$L$797,Анализ_ЧС!B$58,Реестр_ЧС!$K$2:$K$797,Анализ_ЧС!$A68) -> 1 | C68: =COUNTIFS(Реестр_ЧС!$L$2:$L$797,Анализ_ЧС!C$58,Реестр_ЧС!$K$2:$K$797,Анализ_ЧС!$A68) -> 0 | D68: =COUNTIFS(Реестр_ЧС!$L$2:$L$797,Анализ_ЧС!D$58,Реестр_ЧС!$K$2:$K$797,Анализ_ЧС!$A68) -> 0 | E68: =COUNTIFS(Реестр_ЧС!$L$2:$L$797,Анализ_ЧС!E$58,Реестр_ЧС!$K$2:$K$797,Анализ_ЧС!$A68) -> 0 | F68: =COUNTIFS(Реестр_ЧС!$L$2:$L$797,Анализ_ЧС!F$58,Реестр_ЧС!$K$2:$K$797,Анализ_ЧС!$A68) -> 0 | G68: =COUNTIFS(Реестр_ЧС!$L$2:$L$797,Анализ_ЧС!G$58,Реестр_ЧС!$K$2:$K$797,Анализ_ЧС!$A68) -> 0 | H68: =COUNTIFS(Реестр_ЧС!$L$2:$L$797,Анализ_ЧС!H$58,Реестр_ЧС!$K$2:$K$797,Анализ_ЧС!$A68) -> 0 | I68: =COUNTIFS(Реестр_ЧС!$L$2:$L$797,Анализ_ЧС!I$58,Реестр_ЧС!$K$2:$K$797,Анализ_ЧС!$A68) -> 0 | ... L68: =COUNTIFS(Реестр_ЧС!$L$2:$L$797,Анализ_ЧС!L$58,Реестр_ЧС!$K$2:$K$797,Анализ_ЧС!$A68) -> 0 | M68: =SUM(B68:L68) -> 2
A69: 2011 | B69: =COUNTIFS(Реестр_ЧС!$L$2:$L$797,Анализ_ЧС!B$58,Реестр_ЧС!$K$2:$K$797,Анализ_ЧС!$A69) -> 0 | C69: =COUNTIFS(Реестр_ЧС!$L$2:$L$797,Анализ_ЧС!C$58,Реестр_ЧС!$K$2:$K$797,Анализ_ЧС!$A69) -> 1 | D69: =COUNTIFS(Реестр_ЧС!$L$2:$L$797,Анализ_ЧС!D$58,Реестр_ЧС!$K$2:$K$797,Анализ_ЧС!$A69) -> 0 | E69: =COUNTIFS(Реестр_ЧС!$L$2:$L$797,Анализ_ЧС!E$58,Реестр_ЧС!$K$2:$K$797,Анализ_ЧС!$A69) -> 0 | F69: =COUNTIFS(Реестр_ЧС!$L$2:$L$797,Анализ_ЧС!F$58,Реестр_ЧС!$K$2:$K$797,Анализ_ЧС!$A69) -> 0 | G69: =COUNTIFS(Реестр_ЧС!$L$2:$L$797,Анализ_ЧС!G$58,Реестр_ЧС!$K$2:$K$797,Анализ_ЧС!$A69) -> 0 | H69: =COUNTIFS(Реестр_ЧС!$L$2:$L$797,Анализ_ЧС!H$58,Реестр_ЧС!$K$2:$K$797,Анализ_ЧС!$A69) -> 0 | I69: =COUNTIFS(Реестр_ЧС!$L$2:$L$797,Анализ_ЧС!I$58,Реестр_ЧС!$K$2:$K$797,Анализ_ЧС!$A69) -> 0 | ... L69: =COUNTIFS(Реестр_ЧС!$L$2:$L$797,Анализ_ЧС!L$58,Реестр_ЧС!$K$2:$K$797,Анализ_ЧС!$A69) -> 0 | M69: =SUM(B69:L69) -> 1
A70: 2012 | B70: =COUNTIFS(Реестр_ЧС!$L$2:$L$797,Анализ_ЧС!B$58,Реестр_ЧС!$K$2:$K$797,Анализ_ЧС!$A70) -> 1 | C70: =COUNTIFS(Реестр_ЧС!$L$2:$L$797,Анализ_ЧС!C$58,Реестр_ЧС!$K$2:$K$797,Анализ_ЧС!$A70) -> 0 | D70: =COUNTIFS(Реестр_ЧС!$L$2:$L$797,Анализ_ЧС!D$58,Реестр_ЧС!$K$2:$K$797,Анализ_ЧС!$A70) -> 0 | E70: =COUNTIFS(Реестр_ЧС!$L$2:$L$797,Анализ_ЧС!E$58,Реестр_ЧС!$K$2:$K$797,Анализ_ЧС!$A70) -> 1 | F70: =COUNTIFS(Реестр_ЧС!$L$2:$L$797,Анализ_ЧС!F$58,Реестр_ЧС!$K$2:$K$797,Анализ_ЧС!$A70) -> 0 | G70: =COUNTIFS(Реестр_ЧС!$L$2:$L$797,Анализ_ЧС!G$58,Реестр_ЧС!$K$2:$K$797,Анализ_ЧС!$A70) -> 1 | H70: =COUNTIFS(Реестр_ЧС!$L$2:$L$797,Анализ_ЧС!H$58,Реестр_ЧС!$K$2:$K$797,Анализ_ЧС!$A70) -> 1 | I70: =COUNTIFS(Реестр_ЧС!$L$2:$L$797,Анализ_ЧС!I$58,Реестр_ЧС!$K$2:$K$797,Анализ_ЧС!$A70) -> 1 | ... L70: =COUNTIFS(Реестр_ЧС!$L$2:$L$797,Анализ_ЧС!L$58,Реестр_ЧС!$K$2:$K$797,Анализ_ЧС!$A70) -> 0 | M70: =SUM(B70:L70) -> 5
... A83: 2025 | B83: =COUNTIFS(Реестр_ЧС!$L$2:$L$797,Анализ_ЧС!B$58,Реестр_ЧС!$K$2:$K$797,Анализ_ЧС!$A83) -> 1 | C83: =COUNTIFS(Реестр_ЧС!$L$2:$L$797,Анализ_ЧС!C$58,Реестр_ЧС!$K$2:$K$797,Анализ_ЧС!$A83) -> 3 | D83: =COUNTIFS(Реестр_ЧС!$L$2:$L$797,Анализ_ЧС!D$58,Реестр_ЧС!$K$2:$K$797,Анализ_ЧС!$A83) -> 0 | E83: =COUNTIFS(Реестр_ЧС!$L$2:$L$797,Анализ_ЧС!E$58,Реестр_ЧС!$K$2:$K$797,Анализ_ЧС!$A83) -> 0 | F83: =COUNTIFS(Реестр_ЧС!$L$2:$L$797,Анализ_ЧС!F$58,Реестр_ЧС!$K$2:$K$797,Анализ_ЧС!$A83) -> 0 | G83: =COUNTIFS(Реестр_ЧС!$L$2:$L$797,Анализ_ЧС!G$58,Реестр_ЧС!$K$2:$K$797,Анализ_ЧС!$A83) -> 0 | H83: =COUNTIFS(Реестр_ЧС!$L$2:$L$797,Анализ_ЧС!H$58,Реестр_ЧС!$K$2:$K$797,Анализ_ЧС!$A83) -> 1 | I83: =COUNTIFS(Реестр_ЧС!$L$2:$L$797,Анализ_ЧС!I$58,Реестр_ЧС!$K$2:$K$797,Анализ_ЧС!$A83) -> 1 | ... L83: =COUNTIFS(Реестр_ЧС!$L$2:$L$797,Анализ_ЧС!L$58,Реестр_ЧС!$K$2:$K$797,Анализ_ЧС!$A83) -> 1 | M83: =SUM(B83:L83) -> 7
A84: Итого | B84: =SUM(B59:B83) -> 33 | C84: =SUM(C59:C83) -> 26 | D84: =SUM(D59:D83) -> 10 | E84: =SUM(E59:E83) -> 9 | F84: =SUM(F59:F83) -> 4 | G84: =SUM(G59:G83) -> 2 | H84: =SUM(H59:H83) -> 104 | I84: =SUM(I59:I83) -> 32 | ... M84: =SUM(M59:M83) -> 262
A85: Реестр биолого-социальные ЧС
B86: Связанные с нападением диких животных | C86: Заболевание животных | D86: Отравления | E86: Лесное хозяйство | F86: ВСЕГО
A87: 2001 | B87: =COUNTIFS(Реестр_ЧС!$L$2:$L$797,Анализ_ЧС!B$86,Реестр_ЧС!$K$2:$K$797,Анализ_ЧС!$A87) -> 0 | C87: =COUNTIFS(Реестр_ЧС!$L$2:$L$797,Анализ_ЧС!C$86,Реестр_ЧС!$K$2:$K$797,Анализ_ЧС!$A87) -> 0 | D87: =COUNTIFS(Реестр_ЧС!$L$2:$L$797,Анализ_ЧС!D$86,Реестр_ЧС!$K$2:$K$797,Анализ_ЧС!$A87) -> 1 | E87: =COUNTIFS(Реестр_ЧС!$L$2:$L$797,Анализ_ЧС!E$86,Реестр_ЧС!$K$2:$K$797,Анализ_ЧС!$A87) -> 0 | F87: =SUM(B87:E87) -> 1
A88: 2002 | B88: =COUNTIFS(Реестр_ЧС!$L$2:$L$797,Анализ_ЧС!B$86,Реестр_ЧС!$K$2:$K$797,Анализ_ЧС!$A88) -> 0 | C88: =COUNTIFS(Реестр_ЧС!$L$2:$L$797,Анализ_ЧС!C$86,Реестр_ЧС!$K$2:$K$797,Анализ_ЧС!$A88) -> 0 | D88: =COUNTIFS(Реестр_ЧС!$L$2:$L$797,Анализ_ЧС!D$86,Реестр_ЧС!$K$2:$K$797,Анализ_ЧС!$A88) -> 0 | E88: =COUNTIFS(Реестр_ЧС!$L$2:$L$797,Анализ_ЧС!E$86,Реестр_ЧС!$K$2:$K$797,Анализ_ЧС!$A88) -> 0 | F88: =SUM(B88:E88) -> 0
A89: 2003 | B89: =COUNTIFS(Реестр_ЧС!$L$2:$L$797,Анализ_ЧС!B$86,Реестр_ЧС!$K$2:$K$797,Анализ_ЧС!$A89) -> 0 | C89: =COUNTIFS(Реестр_ЧС!$L$2:$L$797,Анализ_ЧС!C$86,Реестр_ЧС!$K$2:$K$797,Анализ_ЧС!$A89) -> 0 | D89: =COUNTIFS(Реестр_ЧС!$L$2:$L$797,Анализ_ЧС!D$86,Реестр_ЧС!$K$2:$K$797,Анализ_ЧС!$A89) -> 1 | E89: =COUNTIFS(Реестр_ЧС!$L$2:$L$797,Анализ_ЧС!E$86,Реестр_ЧС!$K$2:$K$797,Анализ_ЧС!$A89) -> 0 | F89: =SUM(B89:E89) -> 1
A90: 2004 | B90: =COUNTIFS(Реестр_ЧС!$L$2:$L$797,Анализ_ЧС!B$86,Реестр_ЧС!$K$2:$K$797,Анализ_ЧС!$A90) -> 0 | C90: =COUNTIFS(Реестр_ЧС!$L$2:$L$797,Анализ_ЧС!C$86,Реестр_ЧС!$K$2:$K$797,Анализ_ЧС!$A90) -> 0 | D90: =COUNTIFS(Реестр_ЧС!$L$2:$L$797,Анализ_ЧС!D$86,Реестр_ЧС!$K$2:$K$797,Анализ_ЧС!$A90) -> 0 | E90: =COUNTIFS(Реестр_ЧС!$L$2:$L$797,Анализ_ЧС!E$86,Реестр_ЧС!$K$2:$K$797,Анализ_ЧС!$A90) -> 0 | F90: =SUM(B90:E90) -> 0
A91: 2005 | B91: =COUNTIFS(Реестр_ЧС!$L$2:$L$797,Анализ_ЧС!B$86,Реестр_ЧС!$K$2:$K$797,Анализ_ЧС!$A91) -> 0 | C91: =COUNTIFS(Реестр_ЧС!$L$2:$L$797,Анализ_ЧС!C$86,Реестр_ЧС!$K$2:$K$797,Анализ_ЧС!$A91) -> 0 | D91: =COUNTIFS(Реестр_ЧС!$L$2:$L$797,Анализ_ЧС!D$86,Реестр_ЧС!$K$2:$K$797,Анализ_ЧС!$A91) -> 1 | E91: =COUNTIFS(Реестр_ЧС!$L$2:$L$797,Анализ_ЧС!E$86,Реестр_ЧС!$K$2:$K$797,Анализ_ЧС!$A91) -> 0 | F91: =SUM(B91:E91) -> 1
A92: 2006 | B92: =COUNTIFS(Реестр_ЧС!$L$2:$L$797,Анализ_ЧС!B$86,Реестр_ЧС!$K$2:$K$797,Анализ_ЧС!$A92) -> 0 | C92: =COUNTIFS(Реестр_ЧС!$L$2:$L$797,Анализ_ЧС!C$86,Реестр_ЧС!$K$2:$K$797,Анализ_ЧС!$A92) -> 0 | D92: =COUNTIFS(Реестр_ЧС!$L$2:$L$797,Анализ_ЧС!D$86,Реестр_ЧС!$K$2:$K$797,Анализ_ЧС!$A92) -> 1 | E92: =COUNTIFS(Реестр_ЧС!$L$2:$L$797,Анализ_ЧС!E$86,Реестр_ЧС!$K$2:$K$797,Анализ_ЧС!$A92) -> 0 | F92: =SUM(B92:E92) -> 1
A93: 2007 | B93: =COUNTIFS(Реестр_ЧС!$L$2:$L$797,Анализ_ЧС!B$86,Реестр_ЧС!$K$2:$K$797,Анализ_ЧС!$A93) -> 0 | C93: =COUNTIFS(Реестр_ЧС!$L$2:$L$797,Анализ_ЧС!C$86,Реестр_ЧС!$K$2:$K$797,Анализ_ЧС!$A93) -> 0 | D93: =COUNTIFS(Реестр_ЧС!$L$2:$L$797,Анализ_ЧС!D$86,Реестр_ЧС!$K$2:$K$797,Анализ_ЧС!$A93) -> 0 | E93: =COUNTIFS(Реестр_ЧС!$L$2:$L$797,Анализ_ЧС!E$86,Реестр_ЧС!$K$2:$K$797,Анализ_ЧС!$A93) -> 0 | F93: =SUM(B93:E93) -> 0
A94: 2008 | B94: =COUNTIFS(Реестр_ЧС!$L$2:$L$797,Анализ_ЧС!B$86,Реестр_ЧС!$K$2:$K$797,Анализ_ЧС!$A94) -> 0 | C94: =COUNTIFS(Реестр_ЧС!$L$2:$L$797,Анализ_ЧС!C$86,Реестр_ЧС!$K$2:$K$797,Анализ_ЧС!$A94) -> 22 | D94: =COUNTIFS(Реестр_ЧС!$L$2:$L$797,Анализ_ЧС!D$86,Реестр_ЧС!$K$2:$K$797,Анализ_ЧС!$A94) -> 0 | E94: =COUNTIFS(Реестр_ЧС!$L$2:$L$797,Анализ_ЧС!E$86,Реестр_ЧС!$K$2:$K$797,Анализ_ЧС!$A94) -> 0 | F94: =SUM(B94:E94) -> 22
A95: 2009 | B95: =COUNTIFS(Реестр_ЧС!$L$2:$L$797,Анализ_ЧС!B$86,Реестр_ЧС!$K$2:$K$797,Анализ_ЧС!$A95) -> 0 | C95: =COUNTIFS(Реестр_ЧС!$L$2:$L$797,Анализ_ЧС!C$86,Реестр_ЧС!$K$2:$K$797,Анализ_ЧС!$A95) -> 0 | D95: =COUNTIFS(Реестр_ЧС!$L$2:$L$797,Анализ_ЧС!D$86,Реестр_ЧС!$K$2:$K$797,Анализ_ЧС!$A95) -> 0 | E95: =COUNTIFS(Реестр_ЧС!$L$2:$L$797,Анализ_ЧС!E$86,Реестр_ЧС!$K$2:$K$797,Анализ_ЧС!$A95) -> 0 | F95: =SUM(B95:E95) -> 0
A96: 2010 | B96: =COUNTIFS(Реестр_ЧС!$L$2:$L$797,Анализ_ЧС!B$86,Реестр_ЧС!$K$2:$K$797,Анализ_ЧС!$A96) -> 0 | C96: =COUNTIFS(Реестр_ЧС!$L$2:$L$797,Анализ_ЧС!C$86,Реестр_ЧС!$K$2:$K$797,Анализ_ЧС!$A96) -> 0 | D96: =COUNTIFS(Реестр_ЧС!$L$2:$L$797,Анализ_ЧС!D$86,Реестр_ЧС!$K$2:$K$797,Анализ_ЧС!$A96) -> 0 | E96: =COUNTIFS(Реестр_ЧС!$L$2:$L$797,Анализ_ЧС!E$86,Реестр_ЧС!$K$2:$K$797,Анализ_ЧС!$A96) -> 0 | F96: =SUM(B96:E96) -> 0
A97: 2011 | B97: =COUNTIFS(Реестр_ЧС!$L$2:$L$797,Анализ_ЧС!B$86,Реестр_ЧС!$K$2:$K$797,Анализ_ЧС!$A97) -> 0 | C97: =COUNTIFS(Реестр_ЧС!$L$2:$L$797,Анализ_ЧС!C$86,Реестр_ЧС!$K$2:$K$797,Анализ_ЧС!$A97) -> 0 | D97: =COUNTIFS(Реестр_ЧС!$L$2:$L$797,Анализ_ЧС!D$86,Реестр_ЧС!$K$2:$K$797,Анализ_ЧС!$A97) -> 0 | E97: =COUNTIFS(Реестр_ЧС!$L$2:$L$797,Анализ_ЧС!E$86,Реестр_ЧС!$K$2:$K$797,Анализ_ЧС!$A97) -> 0 | F97: =SUM(B97:E97) -> 0
A98: 2012 | B98: =COUNTIFS(Реестр_ЧС!$L$2:$L$797,Анализ_ЧС!B$86,Реестр_ЧС!$K$2:$K$797,Анализ_ЧС!$A98) -> 0 | C98: =COUNTIFS(Реестр_ЧС!$L$2:$L$797,Анализ_ЧС!C$86,Реестр_ЧС!$K$2:$K$797,Анализ_ЧС!$A98) -> 0 | D98: =COUNTIFS(Реестр_ЧС!$L$2:$L$797,Анализ_ЧС!D$86,Реестр_ЧС!$K$2:$K$797,Анализ_ЧС!$A98) -> 0 | E98: =COUNTIFS(Реестр_ЧС!$L$2:$L$797,Анализ_ЧС!E$86,Реестр_ЧС!$K$2:$K$797,Анализ_ЧС!$A98) -> 0 | F98: =SUM(B98:E98) -> 0
... A111: 2025 | B111: =COUNTIFS(Реестр_ЧС!$L$2:$L$797,Анализ_ЧС!B$86,Реестр_ЧС!$K$2:$K$797,Анализ_ЧС!$A111) -> 0 | C111: =COUNTIFS(Реестр_ЧС!$L$2:$L$797,Анализ_ЧС!C$86,Реестр_ЧС!$K$2:$K$797,Анализ_ЧС!$A111) -> 0 | D111: =COUNTIFS(Реестр_ЧС!$L$2:$L$797,Анализ_ЧС!D$86,Реестр_ЧС!$K$2:$K$797,Анализ_ЧС!$A111) -> 1 | E111: =COUNTIFS(Реестр_ЧС!$L$2:$L$797,Анализ_ЧС!E$86,Реестр_ЧС!$K$2:$K$797,Анализ_ЧС!$A111) -> 1 | F111: =SUM(B111:E111) -> 2
A112: Итого | B112: =SUM(B87:B111) -> 4 | C112: =SUM(C87:C111) -> 23 | D112: =SUM(D87:D111) -> 5 | E112: =SUM(E87:E111) -> 3 | F112: =SUM(F87:F111) -> 35
B114: * Данные ГБУ РС(Я) "Служба спасения Республики Саха (Якутия)

Sheet Реестр_затопленных_домов
A1: Дата (дд.мм.гггг) | B1: Наименование реки | C1: Наименование района | D1: Наименование населенного пункта | E1: Район (проверка) | F1: Наслег (проверка) | G1: Н.п. измененный | H1: ОКТМО | I1: Тип дома (частный дом, многоквартирный дом) | J1: Адрес* | K1: Адрес* (по ФИАС) | L1: Уровень воды (значение уровня воды от пола дома), см | N1: Кол-во ошибок "#н/д" | O1: =COUNTIF(H:H,"#н/д") -> 0
A2: 45780 | B2: р. Дюктюенэ, р. Хар-Балаган | C2: Горный район, МО "Шологонский наслег" | D2: с. Ерт | E2: =VLOOKUP(H2,[1]ОКТМО!B:J,6,0) -> Горный муниципальный район | F2: =VLOOKUP(H2,[1]ОКТМО!B:J,9,0) -> Шологонский наслег | G2: =VLOOKUP(H2,[1]ОКТМО!B:M,12,0) -> Ерт | H2: 98620465101 | I2: 2-х квартирный ИЖД | J2: ул. Чаранская д.2 | K2: Республика Саха (Якутия), м.р-н Горный, с.п. Шологонский наслег, с Ерт, ул Чаранская, д. 2 | L2: 1022 | N2: Кол-во "не н.п." | O2: =COUNTIF(H:H,"не н.п.") -> 0
E3: =VLOOKUP(H3,[1]ОКТМО!B:J,6,0) -> Горный муниципальный район | F3: =VLOOKUP(H3,[1]ОКТМО!B:J,9,0) -> Шологонский наслег | G3: =VLOOKUP(H3,[1]ОКТМО!B:M,12,0) -> Ерт | H3: 98620465101 | K3: Республика Саха (Якутия), м.р-н Горный, с.п. Шологонский наслег, с Ерт, ул Чаранская, д. 4 | L3: 1022
A4: 45790 | B4: р. Оччугуй Ботуобуйа | C4: Мирнинский район, МО "Чуонинский наслег" | D4: с. Арылах | E4: =VLOOKUP(H4,[1]ОКТМО!B:J,6,0) -> Мирнинский муниципальный район | F4: =VLOOKUP(H4,[1]ОКТМО!B:J,9,0) -> Чуонинский наслег | G4: =VLOOKUP(H4,[1]ОКТМО!B:M,12,0) -> Арылах | H4: 98631450101 | I4: 8 дворовых территорий | J4: ул. Набережная д.3, 6, 8, 12, 13 14, 18, 19. | K4: Республика Саха (Якутия), м.р-н Мирнинский, с.п. Чуонинский наслег, с Арылах, ул Центральная, д. 3 | L4: 40
E5: =VLOOKUP(H5,[1]ОКТМО!B:J,6,0) -> Мирнинский муниципальный район | F5: =VLOOKUP(H5,[1]ОКТМО!B:J,9,0) -> Чуонинский наслег | G5: =VLOOKUP(H5,[1]ОКТМО!B:M,12,0) -> Арылах | H5: 98631450101 | K5: Республика Саха (Якутия), м.р-н Мирнинский, с.п. Чуонинский наслег, с Арылах, ул Центральная, д. 6 | L5: 40
E6: =VLOOKUP(H6,[1]ОКТМО!B:J,6,0) -> Мирнинский муниципальный район | F6: =VLOOKUP(H6,[1]ОКТМО!B:J,9,0) -> Чуонинский наслег | G6: =VLOOKUP(H6,[1]ОКТМО!B:M,12,0) -> Арылах | H6: 98631450101 | K6: Республика Саха (Якутия), м.р-н Мирнинский, с.п. Чуонинский наслег, с Арылах, ул Центральная, д. 8 | L6: 40
E7: =VLOOKUP(H7,[1]ОКТМО!B:J,6,0) -> Мирнинский муниципальный район | F7: =VLOOKUP(H7,[1]ОКТМО!B:J,9,0) -> Чуонинский наслег | G7: =VLOOKUP(H7,[1]ОКТМО!B:M,12,0) -> Арылах | H7: 98631450101 | K7: Республика Саха (Якутия), м.р-н Мирнинский, с.п. Чуонинский наслег, с Арылах, ул Центральная, д. 12 | L7: 40
E8: =VLOOKUP(H8,[1]ОКТМО!B:J,6,0) -> Мирнинский муниципальный район | F8: =VLOOKUP(H8,[1]ОКТМО!B:J,9,0) -> Чуонинский наслег | G8: =VLOOKUP(H8,[1]ОКТМО!B:M,12,0) -> Арылах | H8: 98631450101 | K8: Республика Саха (Якутия), м.р-н Мирнинский, с.п. Чуонинский наслег, с Арылах, ул Центральная, д. 13 | L8: 40
E9: =VLOOKUP(H9,[1]ОКТМО!B:J,6,0) -> Мирнинский муниципальный район | F9: =VLOOKUP(H9,[1]ОКТМО!B:J,9,0) -> Чуонинский наслег | G9: =VLOOKUP(H9,[1]ОКТМО!B:M,12,0) -> Арылах | H9: 98631450101 | K9: Республика Саха (Якутия), м.р-н Мирнинский, с.п. Чуонинский наслег, с Арылах, ул Центральная, д. 14 | L9: 40
E10: =VLOOKUP(H10,[1]ОКТМО!B:J,6,0) -> Мирнинский муниципальный район | F10: =VLOOKUP(H10,[1]ОКТМО!B:J,9,0) -> Чуонинский наслег | G10: =VLOOKUP(H10,[1]ОКТМО!B:M,12,0) -> Арылах | H10: 98631450101 | K10: Республика Саха (Якутия), м.р-н Мирнинский, с.п. Чуонинский наслег, с Арылах, ул Центральная, д. 18 | L10: 40
E11: =VLOOKUP(H11,[1]ОКТМО!B:J,6,0) -> Мирнинский муниципальный район | F11: =VLOOKUP(H11,[1]ОКТМО!B:J,9,0) -> Чуонинский наслег | G11: =VLOOKUP(H11,[1]ОКТМО!B:M,12,0) -> Арылах | H11: 98631450101 | K11: Республика Саха (Якутия), м.р-н Мирнинский, с.п. Чуонинский наслег, с Арылах, ул Центральная, д. 19 | L11: 40
A12: 45797 | B12: р. Вилюй | C12: Вилюйский район СП "Халбакинский наслег" | D12: с. Староватово | E12: =VLOOKUP(H12,[1]ОКТМО!B:J,6,0) -> Вилюйский муниципальный район | F12: =VLOOKUP(H12,[1]ОКТМО!B:J,9,0) -> Халбакинский наслег | G12: =VLOOKUP(H12,[1]ОКТМО!B:M,12,0) -> Староватово | H12: 98618462106 | I12: 1 ИЖД, 9 дворовых территорий
A13: 45797 | B13: р. Колыма | C13: Среднеколымский район МО "Срнеднеколымский район" | D13: г. Среднеколымск | E13: =VLOOKUP(H13,[1]ОКТМО!B:J,6,0) -> Среднеколымский муниципальный район | F13: =VLOOKUP(H13,[1]ОКТМО!B:J,9,0) -> город Среднеколымск | G13: =VLOOKUP(H13,[1]ОКТМО!B:M,12,0) -> Среднеколымск | H13: 98646101001 | I13: 7 МКД, 32 ИЖД | L13: 1270
A14: 45810 | B14: р. Колыма | C14: Нижнеколымский район МО "Походский наслег" | D14: с. Походск | E14: =VLOOKUP(H14,[1]ОКТМО!B:J,6,0) -> Нижнеколымский муниципальный район | F14: =VLOOKUP(H14,[1]ОКТМО!B:J,9,0) -> Походский наслег | G14: =VLOOKUP(H14,[1]ОКТМО!B:M,12,0) -> Походск | H14: 98637424101 | I14: 2 ИЖД, 22 двор/терр. | J14: ул. Комсомольская д.15, ул. Набережная д.1 | K14: Республика Саха (Якутия), м.р-н Нижнеколымский, с.п. Походский наслег, с Походск, ул Комсомольская, д. 15 | L14: 999
E15: =VLOOKUP(H15,[1]ОКТМО!B:J,6,0) -> Нижнеколымский муниципальный район | F15: =VLOOKUP(H15,[1]ОКТМО!B:J,9,0) -> Походский наслег | G15: =VLOOKUP(H15,[1]ОКТМО!B:M,12,0) -> Походск | H15: 98637424101 | K15: Республика Саха (Якутия), м.р-н Нижнеколымский, с.п. Походский наслег, с Походск, ул Набережная, д. 1
A16: 45810 | B16: р. Алдан | C16: Алданский район МО "Чагдинский наслег" | D16: с. Чагда | E16: =VLOOKUP(H16,[1]ОКТМО!B:J,6,0) -> Алданский муниципальный район | F16: =VLOOKUP(H16,[1]ОКТМО!B:J,9,0) -> Чагдинский наслег | G16: =VLOOKUP(H16,[1]ОКТМО!B:M,12,0) -> Чагда | H16: 98603460101 | I16: 11 ИЖД, 13 двор/терр. | J16: ул. Набережная д. 3,7,27,21; ул. Советская д. 1,3,5; ул. Матросова д. 21,25; ул. Подгорная д.4; ул. Авиапорт д.5 кв 1, д.6 кв 1,2; ул. Комсомольская д.2 кв 2, д.6 кв 1,2; ул. Октябрьская д.16; ул. Учурская 32. | L16: 1682
E17: =VLOOKUP(H17,[1]ОКТМО!B:J,6,0) -> Алданский муниципальный район | F17: =VLOOKUP(H17,[1]ОКТМО!B:J,9,0) -> Чагдинский наслег | G17: =VLOOKUP(H17,[1]ОКТМО!B:M,12,0) -> Чагда | H17: 98603460101
A18: 45810 | B18: р. Алдан | C18: Усть-Майский район | D18: с. Белькачи | E18: =VLOOKUP(H18,[1]ОКТМО!B:J,6,0) -> Усть-Майский муниципальный район | F18: =VLOOKUP(H18,[1]ОКТМО!B:J,9,0) -> село Белькачи | G18: =VLOOKUP(H18,[1]ОКТМО!B:M,12,0) -> Белькачи | H18: 98654405101 | I18: 7 дворовых территорий | L18: 2316
A19: 45812 | B19: р. Алдан | C19: Усть-Майский район | D19: с. Усть-Миль | E19: =VLOOKUP(H19,[1]ОКТМО!B:J,6,0) -> Усть-Майский муниципальный район | F19: =VLOOKUP(H19,[1]ОКТМО!B:J,9,0) -> село Усть-Миль | G19: =VLOOKUP(H19,[1]ОКТМО!B:M,12,0) -> Усть-Миль | H19: 98654415101 | I19: 1 огородный участок | J19: ул. Алданский д.1 | L19: 1553
A20: 45812 | B20: р. Алдан | C20: Усть-Майский район МО "Эжанский национальный наслег" | D20: с. Эжанцы | E20: =VLOOKUP(H20,[1]ОКТМО!B:J,6,0) -> Усть-Майский муниципальный район | F20: =VLOOKUP(H20,[1]ОКТМО!B:J,9,0) -> Эжанский национальный наслег | G20: =VLOOKUP(H20,[1]ОКТМО!B:M,12,0) -> Эжанцы | H20: 98654425101 | I20: 27 дворовых территорий | J20: ул. Алданская д.1, 5; ул. А.Иванова д. 31, 33, 23, 21, 17, 19, 15, 13/1, 13, 11, 9, 1, 3, 5; ул. Ул. Боярова д. 2, 4, 6; ул. Александры Атласовой д. 16, 16/1, 18; ул. Победы д. 1/1, 4, 8/1, 12,24 | L20: 1301
A21: 45812 | B21: р. Алдан | C21: Усть-Майский район | D21: пгт. Эльдикан | E21: =VLOOKUP(H21,[1]ОКТМО!B:J,6,0) -> Усть-Майский муниципальный район | F21: =VLOOKUP(H21,[1]ОКТМО!B:J,9,0) -> поселок Эльдикан | G21: =VLOOKUP(H21,[1]ОКТМО!B:M,12,0) -> Эльдикан | H21: 98654164051 | I21: 2 ИЖД, 52 двор/терр. | J21: ул. Советская д.23, 24; ул. Чапаева д.2 | L21: 1516
A22: 45812 | B22: р. Алдан, оз.Мэккэ | C22: Усть-Майский район МО "Кюпский национальный наслег" | D22: с. Кюпцы | E22: =VLOOKUP(H22,[1]ОКТМО!B:J,6,0) -> Усть-Майский муниципальный район | F22: =VLOOKUP(H22,[1]ОКТМО!B:J,9,0) -> Кюпский эвенкийский национальный наслег | G22: =VLOOKUP(H22,[1]ОКТМО!B:M,12,0) -> Кюпцы | H22: 98654410101 | I22: 3 ИЖД, 28 двор/терр. | J22: ул. Советская д.40, 28, 28/1, 30, 30/2, 32, 34, 42; ул. Молодежная д.1, 2/1, 2/2, 3, 5, 6, 7, 8, ул. Атласова д.4, ул. Озерная д.3, 4, ул. Мэккинская д.7, 12, 14, 16; ул. Лесная д.5, 6, 7, 6/1, пер. Березовый | L22: 1319
A23: 45812 | B23: р. Алдан | C23: Усть-Майский район | D23: пгт. Усть-Мая | E23: =VLOOKUP(H23,[1]ОКТМО!B:J,6,0) -> Усть-Майский муниципальный район | F23: =VLOOKUP(H23,[1]ОКТМО!B:J,9,0) -> поселок Усть-Мая | G23: =VLOOKUP(H23,[1]ОКТМО!B:M,12,0) -> Усть-Мая | H23: 98654151051 | I23: 8 ИЖД, 28 двор/терр. | J23: ул. Набережная, ул. Горького
A24: 45814 | B24: р. Алдан | C24: Томпонский район МО"Охот-Перевозовский наслег" | D24: с. Охотский Перевоз | E24: =VLOOKUP(H24,[1]ОКТМО!B:J,6,0) -> Томпонский муниципальный район | F24: =VLOOKUP(H24,[1]ОКТМО!B:J,9,0) -> Охот-Перевозовский наслег | G24: =VLOOKUP(H24,[1]ОКТМО!B:M,12,0) -> Охотский-Перевоз | H24: 98650425101 | I24: 5 дворовых территорий | L24: 1214
A25: 45851 | B25: р. Индигирка | C25: Оймяконский район МО "Сордоннохский наслег | D25: с. Орто-Балаган | E25: =VLOOKUP(H25,[1]ОКТМО!B:J,6,0) -> Оймяконский муниципальный район | F25: =VLOOKUP(H25,[1]ОКТМО!B:J,9,0) -> Сордоннохский национальный наслег | G25: =VLOOKUP(H25,[1]ОКТМО!B:M,12,0) -> Орто-Балаган | H25: 98639427101 | I25: 32 ИЖД и двор/терр. | L25: 477
A26: 45853 | B26: р. Индигирка | C26: Оймяконский район МО "2-й Борогонский наслег" | D26: с. Томтор | E26: =VLOOKUP(H26,[1]ОКТМО!B:J,6,0) -> Оймяконский муниципальный район | F26: =VLOOKUP(H26,[1]ОКТМО!B:J,9,0) -> Борогонский 2-й наслег | G26: =VLOOKUP(H26,[1]ОКТМО!B:M,12,0) -> Томтор | H26: 98639410101 | I26: 98 дворовых территорий | L26: 477
A27: 45853 | B27: р. Индигирка | C27: Оймяконский район ГП "Поселок Усть-Нера" | D27: пгт. Усть-Нера | E27: =VLOOKUP(H27,[1]ОКТМО!B:J,6,0) -> Оймяконский муниципальный район | F27: =VLOOKUP(H27,[1]ОКТМО!B:J,9,0) -> поселок Усть-Нера | G27: =VLOOKUP(H27,[1]ОКТМО!B:M,12,0) -> Усть-Нера | H27: 98639151051 | I27: 36 ИЖД и двор/терр. | L27: 477
A28: 45853 | B28: р. Индигирка | C28: Оймяконский район МО "Оймякон Полюс Холода" | D28: с. Оймякон | E28: =VLOOKUP(H28,[1]ОКТМО!B:J,6,0) -> Оймяконский муниципальный район | F28: =VLOOKUP(H28,[1]ОКТМО!B:J,9,0) -> Оймякон Полюс Холода | G28: =VLOOKUP(H28,[1]ОКТМО!B:M,12,0) -> Оймякон | H28: 98639405101 | I28: 118 ИЖД и двор/терр | L28: 477
A29: 45853 | B29: р. Индигирка | C29: Оймяконский район МО "Оймякон Полюс Холода" | D29: с. Берег-Юрдя | E29: =VLOOKUP(H29,[1]ОКТМО!B:J,6,0) -> Оймяконский муниципальный район | F29: =VLOOKUP(H29,[1]ОКТМО!B:J,9,0) -> Оймякон Полюс Холода | G29: =VLOOKUP(H29,[1]ОКТМО!B:M,12,0) -> Берег-Юрдя | H29: 98639405106 | I29: 23 ИЖД, 21 двор/терр
A30: 45853 | B30: р. Индигирка | C30: Оймяконский район МО "Оймякон Полюс Холода" | D30: с. Хара-Тумул | E30: =VLOOKUP(H30,[1]ОКТМО!B:J,6,0) -> Оймяконский муниципальный район | F30: =VLOOKUP(H30,[1]ОКТМО!B:J,9,0) -> Оймякон Полюс Холода | G30: =VLOOKUP(H30,[1]ОКТМО!B:M,12,0) -> Хара-Тумул | H30: 98639405111 | I30: 24 ИЖД (выше пола 13 ИЖД, по оклад 11 ИЖД)
A31: 45853 | B31: р. Индигирка | C31: Абыйский район МО СП "Майорский национальный наслег" | D31: с. Куберганя | E31: =VLOOKUP(H31,[1]ОКТМО!B:J,6,0) -> Абыйский муниципальный район | F31: =VLOOKUP(H31,[1]ОКТМО!B:J,9,0) -> Майорский национальный наслег | G31: =VLOOKUP(H31,[1]ОКТМО!B:M,12,0) -> Куберганя | H31: 98601409101 | I31: 12 ИЖД, 8 МКД, 21 двор/терр. | L31: 1675
A32: 45856 | B32: р. Индигирка | C32: Оймяконский район МО "Терютский наслег" | D32: с. Терють | E32: =VLOOKUP(H32,[1]ОКТМО!B:J,6,0) -> Оймяконский муниципальный район | F32: =VLOOKUP(H32,[1]ОКТМО!B:J,9,0) -> Терютский наслег | G32: =VLOOKUP(H32,[1]ОКТМО!B:M,12,0) -> Терют | H32: 98639432101 | I32: 5 дворовых территорий
A33: 45856 | B33: р. Индигирка | C33: Момский район МО "Момский национальный наслег" | D33: с. Хонуу | E33: =VLOOKUP(H33,[1]ОКТМО!B:J,6,0) -> Момский муниципальный район | F33: =VLOOKUP(H33,[1]ОКТМО!B:J,9,0) -> Момский национальный наслег | G33: =VLOOKUP(H33,[1]ОКТМО!B:M,12,0) -> Хонуу | H33: 98633423101 | I33: 26 дворовых территорий | J33: ул. Озерная, ул. Береговая, ул. Строителей, ул. Западная, ул. В. Лебедева, ул. Стростина, ул. Тарабукина, ул. Аф. Старкова, ул. Дачная, ул. Советская | L33: 477
A34: 45856 | B34: р. Индигирка | C34: Момский район МО "Индигирский национальный наслег" | D34: с. Буор-Сысы | E34: =VLOOKUP(H34,[1]ОКТМО!B:J,6,0) -> Момский муниципальный район | F34: =VLOOKUP(H34,[1]ОКТМО!B:J,9,0) -> Индигирский национальный наслег | G34: =VLOOKUP(H34,[1]ОКТМО!B:M,12,0) -> Буор-Сысы | H34: 98633414101 | I34: 5 ИЖД, 27 двор/терр. | L34: 477
A35: 45856 | B35: р. Индигирка р. Мома, р. Тарын | C35: Момский район "МО Соболохский национальный наслег" | D35: с. Соболох | E35: =VLOOKUP(H35,[1]ОКТМО!B:J,6,0) -> Момский муниципальный район | F35: =VLOOKUP(H35,[1]ОКТМО!B:J,9,0) -> Соболохский национальный наслег | G35: =VLOOKUP(H35,[1]ОКТМО!B:M,12,0) -> Соболох | H35: 98633428101 | I35: 2 дворовые территории | J35: ул. Лесная, ул. Тихона Толомона | L35: 477
A36: 45888 | B36: р. Индигирка | C36: Оймяконский район МО" Оймякон Полюс Холода" | D36: с. Оймякон | E36: =VLOOKUP(H36,[1]ОКТМО!B:J,6,0) -> Оймяконский муниципальный район | F36: =VLOOKUP(H36,[1]ОКТМО!B:J,9,0) -> Оймякон Полюс Холода | G36: =VLOOKUP(H36,[1]ОКТМО!B:M,12,0) -> Оймякон | H36: 98639405101 | I36: 15 дворовых территорий | L36: 475
A37: 45888 | B37: р. Индигирка | C37: Оймяконский район МО "Сордоннохский наслег" | D37: с. Орто-Балаган | E37: =VLOOKUP(H37,[1]ОКТМО!B:J,6,0) -> Оймяконский муниципальный район | F37: =VLOOKUP(H37,[1]ОКТМО!B:J,9,0) -> Сордоннохский национальный наслег | G37: =VLOOKUP(H37,[1]ОКТМО!B:M,12,0) -> Орто-Балаган | H37: 98639427101 | I37: 8 ИЖС дворовые территории, 1 МКД 4-х кв.дом. | J37: ул. Лесная д14 кв 1, ул. Лесная д.4/1, ул. Солнечная д.6, 8, 12, 13, 15, ул. Лесная д.6, ул. Светлая д.4. | L37: 46
A38: 45424 | B38: р. Лена | C38: Олекминский район, СП "Дельгейский наслег" | D38: с. Иннях | E38: =VLOOKUP(H38,[1]ОКТМО!B:J,6,0) -> Олекминский муниципальный район | F38: =VLOOKUP(H38,[1]ОКТМО!B:J,9,0) -> Дельгейский наслег | G38: =VLOOKUP(H38,[1]ОКТМО!B:M,12,0) -> Иннях | H38: 98641415106 | I38: 7 ИЖД
A39: 45424 | B39: р. Лена | C39: Олекминский район | D39: с. Дельгей | E39: =VLOOKUP(H39,[1]ОКТМО!B:J,6,0) -> Олекминский муниципальный район | F39: =VLOOKUP(H39,[1]ОКТМО!B:J,9,0) -> Дельгейский наслег | G39: =VLOOKUP(H39,[1]ОКТМО!B:M,12,0) -> Дельгей | H39: 98641415101 | I39: 2 ИЖД | L39: 1120
A40: 45424 | B40: р. Лена | C40: Олекминский район | D40: с. Бирюк | E40: =VLOOKUP(H40,[1]ОКТМО!B:J,6,0) -> Олекминский муниципальный район | F40: =VLOOKUP(H40,[1]ОКТМО!B:J,9,0) -> Нерюктяйинский 1-й наслег | G40: =VLOOKUP(H40,[1]ОКТМО!B:M,12,0) -> Бирюк | H40: 98641445106 | I40: 44 ИЖД
A41: 45424 | B41: р. Лена | C41: Олекминский район | D41: с. Нерюктяйинск 1 | E41: =VLOOKUP(H41,[1]ОКТМО!B:J,6,0) -> Олекминский муниципальный район | F41: =VLOOKUP(H41,[1]ОКТМО!B:J,9,0) -> Нерюктяйинский 1-й наслег | G41: =VLOOKUP(H41,[1]ОКТМО!B:M,12,0) -> Нерюктяйинск 1-й | H41: 98641445101 | I41: 50 ИЖД
A42: 45424 | B42: р. Лена | C42: Олекминский район | D42: с. Нерюктяйинск 2 | E42: =VLOOKUP(H42,[1]ОКТМО!B:J,6,0) -> Олекминский муниципальный район | F42: =VLOOKUP(H42,[1]ОКТМО!B:J,9,0) -> Нерюктяйинский 2-й наслег | G42: =VLOOKUP(H42,[1]ОКТМО!B:M,12,0) -> Нерюктяйинск 2-й | H42: 98641450101 | I42: 15 ИЖД, 26 двор/терр.
A43: 45424 | B43: р. Лена | C43: Олекминский район | D43: с. Кыллах | E43: =VLOOKUP(H43,[1]ОКТМО!B:J,6,0) -> Олекминский муниципальный район | F43: =VLOOKUP(H43,[1]ОКТМО!B:J,9,0) -> Кыллахский наслег | G43: =VLOOKUP(H43,[1]ОКТМО!B:M,12,0) -> Кыллах | H43: 98641430101 | I43: 32 ИЖД, 42 двор/терр.
A44: 45424 | B44: р. Лена | C44: Олекминский район | D44: с. Хоринцы | E44: =VLOOKUP(H44,[1]ОКТМО!B:J,6,0) -> Олекминский муниципальный район | F44: =VLOOKUP(H44,[1]ОКТМО!B:J,9,0) -> Хоринский наслег | G44: =VLOOKUP(H44,[1]ОКТМО!B:M,12,0) -> Хоринцы | H44: 98641485101 | I44: 38 ИЖД, 43 двор/терр.
A45: 45424 | B45: р. Лена | C45: Олекминский район | D45: с. Балаганннах | E45: =VLOOKUP(H45,[1]ОКТМО!B:J,6,0) -> Верхневилюйский муниципальный район | F45: =VLOOKUP(H45,[1]ОКТМО!B:J,9,0) -> Балаганнахский наслег | G45: =VLOOKUP(H45,[1]ОКТМО!B:M,12,0) -> Балаганнах | H45: 98614402101 | I45: 4 ИЖД
A46: 45425 | B46: р. Вилюй | C46: Нюрбинский район | D46: с. Жархан | E46: =VLOOKUP(H46,[1]ОКТМО!B:J,6,0) -> Нюрбинский муниципальный район | F46: =VLOOKUP(H46,[1]ОКТМО!B:J,9,0) -> Жарханский наслег | G46: =VLOOKUP(H46,[1]ОКТМО!B:M,12,0) -> Жархан | H46: 98626415101 | I46: 3 ИЖД, 2 МКД, 8 двор/терр.
A47: 45425 | B47: р. Вилюй | C47: Нюрбинский район | D47: г. Нюрба | E47: =VLOOKUP(H47,[1]ОКТМО!B:J,6,0) -> Нюрбинский муниципальный район | F47: =VLOOKUP(H47,[1]ОКТМО!B:J,9,0) -> город Нюрба | G47: =VLOOKUP(H47,[1]ОКТМО!B:M,12,0) -> Нюрба | H47: 98626101001 | I47: 1 ИЖД, 1 МКД, 2 двор/терр.
A48: 45430 | B48: р. Лена | C48: Намский район, 2-Хомустахский наслег | D48: с. Хатас | E48: =VLOOKUP(H48,[1]ОКТМО!B:J,6,0) -> Намский муниципальный район | F48: =VLOOKUP(H48,[1]ОКТМО!B:J,9,0) -> Хомустахский 2-й наслег | G48: =VLOOKUP(H48,[1]ОКТМО!B:M,12,0) -> Хатас | H48: 98635466101 | I48: 35 ИЖД, 55 двор/терр, 7 летних домов
A49: 45430 | B49: р. Лена | C49: Намский район, Ленский наслег | D49: с. Намцы | E49: =VLOOKUP(H49,[1]ОКТМО!B:J,6,0) -> Намский муниципальный район | F49: =VLOOKUP(H49,[1]ОКТМО!B:J,9,0) -> Ленский наслег | G49: =VLOOKUP(H49,[1]ОКТМО!B:M,12,0) -> Намцы | H49: 98635425101 | I49: 6 ИЖД, 21 двор/терр.
A50: 45430 | B50: р. Лена | C50: Намский район, Партизанский наслег | D50: с. Партизан | E50: =VLOOKUP(H50,[1]ОКТМО!B:J,6,0) -> Намский муниципальный район | F50: =VLOOKUP(H50,[1]ОКТМО!B:J,9,0) -> Партизанский наслег | G50: =VLOOKUP(H50,[1]ОКТМО!B:M,12,0) -> Партизан | H50: 98635435101 | I50: 14 ИЖД, 1 МКД, 61 двор/терр, 2 нежилых дома
A51: 45430 | B51: р. Лена | C51: Намский район, Хамагаттинский наслег | D51: с. Крест-Кытыл | E51: =VLOOKUP(H51,[1]ОКТМО!B:J,6,0) -> Намский муниципальный район | F51: =VLOOKUP(H51,[1]ОКТМО!B:J,9,0) -> Хамагаттинский наслег | G51: =VLOOKUP(H51,[1]ОКТМО!B:M,12,0) -> Крест-Кытыл | H51: 98635450101 | I51: 14 ИЖД, 1 МКД, 25 двор/терр, 2 нежилых дома, 2 дачных дома
... A53: 45430 | B53: р. Лена | C53: Намский район, Хатын Арынский наслег | D53: с. Кысыл-Деревня | E53: =VLOOKUP(H53,[1]ОКТМО!B:J,6,0) -> Намский муниципальный район | F53: =VLOOKUP(H53,[1]ОКТМО!B:J,9,0) -> Хатын-Арынский наслег | G53: =VLOOKUP(H53,[1]ОКТМО!B:M,12,0) -> Кысыл-Деревня | H53: 98635455111 | I53: 7 ИЖД, 1 МКД, 13 двор/терр.
A54: 45430 | B54: р. Лена | C54: Намский район, Бетюнский наслег | D54: с. Бютяй Юрдя | E54: =VLOOKUP(H54,[1]ОКТМО!B:J,6,0) -> Намский муниципальный район | F54: =VLOOKUP(H54,[1]ОКТМО!B:J,9,0) -> Бетюнский наслег | G54: =VLOOKUP(H54,[1]ОКТМО!B:M,12,0) -> Бютяй-Юрдя | H54: 98635410101 | I54: 38 ИЖД, 45 двор/терр. | L54: до оклада 4 дома
A55: 45430 | B55: р. Лена | C55: Намский район, Модутский наслег | D55: с. Тумул | E55: =VLOOKUP(H55,[1]ОКТМО!B:J,6,0) -> Намский муниципальный район | F55: =VLOOKUP(H55,[1]ОКТМО!B:J,9,0) -> Модутский наслег | G55: =VLOOKUP(H55,[1]ОКТМО!B:M,12,0) -> Тумул | H55: 98635430101 | I55: 125 ИЖД, 3 МКД, 176 двор/терр.
A56: 45430 | B56: р. Лена | C56: Намский район, Арбынский наслег | D56: с. Сыгыннах | E56: =VLOOKUP(H56,[1]ОКТМО!B:J,6,0) -> Намский муниципальный район | F56: =VLOOKUP(H56,[1]ОКТМО!B:J,9,0) -> Арбынский наслег | G56: =VLOOKUP(H56,[1]ОКТМО!B:M,12,0) -> Сыгыннах | H56: 98635405101 | I56: 29 ИЖД, 2 МКД 2-х, 4-х квартирных жилых дома, 64 двор/терр.
A57: 45430 | B57: р. Лена | C57: Намский район, Хатырыкский наслег | D57: с. Столбы | E57: =VLOOKUP(H57,[1]ОКТМО!B:J,6,0) -> Намский муниципальный район | F57: =VLOOKUP(H57,[1]ОКТМО!B:J,9,0) -> Хатырыкский наслег | G57: =VLOOKUP(H57,[1]ОКТМО!B:M,12,0) -> Столбы | H57: 98635460101 | I57: 243 ИЖД, 16 МКД, 247 двор/терр. | L57: 243 ИЖД выше пола
A58: 45430 | B58: р. Лена | C58: Намский район, Маймагинский наслег | D58: с. Маймага | E58: =VLOOKUP(H58,[1]ОКТМО!B:J,6,0) -> Намский муниципальный район | F58: =VLOOKUP(H58,[1]ОКТМО!B:J,9,0) -> Маймагинский наслег | G58: =VLOOKUP(H58,[1]ОКТМО!B:M,12,0) -> Маймага | H58: 98635470101 | I58: 42 ИЖД, 47 двор/терр.
A59: 45430 | B59: р. Лена | C59: Намский район, Кебекенский наслег | D59: с. Харыялах | E59: =VLOOKUP(H59,[1]ОКТМО!B:J,6,0) -> Намский муниципальный район | F59: =VLOOKUP(H59,[1]ОКТМО!B:J,9,0) -> Кебекенский наслег | G59: =VLOOKUP(H59,[1]ОКТМО!B:M,12,0) -> Харыялах | H59: 98635420101 | I59: 1 ИЖД, 4 двор/терр.
A60: 45431 | B60: р. Лена | C60: Намский район, Едейский наслег | D60: с. Ымыяхтах | E60: =VLOOKUP(H60,[1]ОКТМО!B:J,6,0) -> Намский муниципальный район | F60: =VLOOKUP(H60,[1]ОКТМО!B:J,9,0) -> Едейский наслег | G60: =VLOOKUP(H60,[1]ОКТМО!B:M,12,0) -> Ымыяхтах | H60: 98635415101 | I60: 4 дворовых территорий
A61: 45431 | B61: р. Лена | C61: Намский район, Никольский наслег | D61: с. Никольский | E61: =VLOOKUP(H61,[1]ОКТМО!B:J,6,0) -> Намский муниципальный район | F61: =VLOOKUP(H61,[1]ОКТМО!B:J,9,0) -> Никольский наслег | G61: =VLOOKUP(H61,[1]ОКТМО!B:M,12,0) -> Никольский | H61: 98635432101 | I61: 5 дворовых территорий
A62: 45431 | B62: р. Лена | C62: Намский район, Хатын Арынский наслег | D62: с. Аппаны | E62: =VLOOKUP(H62,[1]ОКТМО!B:J,6,0) -> Намский муниципальный район | F62: =VLOOKUP(H62,[1]ОКТМО!B:J,9,0) -> Хатын-Арынский наслег | G62: =VLOOKUP(H62,[1]ОКТМО!B:M,12,0) -> Аппаны | H62: 98635455101 | I62: 19 ИЖД, 3 МКД, 44 двор/терр.
A63: 45431 | B63: р. Лена | C63: Намский район, Фрунзенский наслег | D63: с. Фрунзе | E63: =VLOOKUP(H63,[1]ОКТМО!B:J,6,0) -> Намский муниципальный район | F63: =VLOOKUP(H63,[1]ОКТМО!B:J,9,0) -> Фрунзенский наслег | G63: =VLOOKUP(H63,[1]ОКТМО!B:M,12,0) -> Фрунзе | H63: 98635447101 | I63: 3 нежилых дома
A64: 45442 | B64: р. Анабар | C64: Анабарский район | D64: с. Саскылах | E64: =VLOOKUP(H64,[1]ОКТМО!B:J,6,0) -> Анабарский национальный (долгано-эвенкийский) муниципальный район | F64: =VLOOKUP(H64,[1]ОКТМО!B:J,9,0) -> Саскылахский национальный (эвенкийский) наслег | G64: =VLOOKUP(H64,[1]ОКТМО!B:M,12,0) -> Саскылах | H64: 98610411101 | I64: 2 ИЖД, 1 общежитие, 13 МКД. | J64: ул. Ильи Спиридонова д.1, 2, 5; ул. Авиаторов 3/3, 9/1 ч/д; ул. Авиаторов д.2/1, 7, 8, 12 МКД, ул. Авиаторов 9, 10, ул. Мира д.3 МКД. | L64: 1093
A65: 45540 | B65: р. Индигирка | C65: Оймяконский район, МО "Сордоннохский наслег" | D65: с. Сордоннох | E65: =VLOOKUP(H65,[1]ОКТМО!B:J,6,0) -> Оймяконский муниципальный район | F65: =VLOOKUP(H65,[1]ОКТМО!B:J,9,0) -> Сордоннохский национальный наслег | G65: =VLOOKUP(H65,[1]ОКТМО!B:M,12,0) -> Орто-Балаган | H65: 98639427101 | I65: 1 дворовая территория 4х-квартирного дома | J65: ул. Лесная д.2
A66: 45540 | B66: р. Индигирка | C66: Оймяконский район, МО "Оймякон Полюс Холода" | D66: с. Оймякон | E66: =VLOOKUP(H66,[1]ОКТМО!B:J,6,0) -> Оймяконский муниципальный район | F66: =VLOOKUP(H66,[1]ОКТМО!B:J,9,0) -> Оймякон Полюс Холода | G66: =VLOOKUP(H66,[1]ОКТМО!B:M,12,0) -> Оймякон | H66: 98639405101 | I66: 6 ИЖД, 2х-квартирный дом - 2, 4х-квартирный дом 1. | J66: ул. Центральная 34/1, 32; ул. Индигирская 12 кв 1, 19 корпус 1, 9, 10, 13; Ул. Набережная 4, 5.
A67: 45051 | B67: р. Хаар-Балаган | C67: Горный район, МО "Шологонский наслег" | D67: с. Ерт | E67: =VLOOKUP(H67,[1]ОКТМО!B:J,6,0) -> Горный муниципальный район | F67: =VLOOKUP(H67,[1]ОКТМО!B:J,9,0) -> Шологонский наслег | G67: =VLOOKUP(H67,[1]ОКТМО!B:M,12,0) -> Ерт | H67: 98620465101 | I67: 6 МКД, 16 двор/терр. | J67: МКД ул. Н.Р. Степанова д.26, ул. Чаранская д.1, 1/1, 2, 4, 6; ул. Тарасова 2а
A68: 45052 | C68: Горный район, МО "Одунунский наслег" | D68: с. Магарас | E68: =VLOOKUP(H68,[1]ОКТМО!B:J,6,0) -> Горный муниципальный район | F68: =VLOOKUP(H68,[1]ОКТМО!B:J,9,0) -> Одунунский наслег | G68: =VLOOKUP(H68,[1]ОКТМО!B:M,12,0) -> Магарас | H68: 98620449101 | I68: 3 ИЖД, 16 двор/терр. | J68: ул. Южная д.8, 8/1
A69: 45052 | B69: р. Дюктюенэ | C69: Горный район МО "Атамайский наслег" | D69: с. Бяс-Кюель | E69: =VLOOKUP(H69,[1]ОКТМО!B:J,6,0) -> Горный муниципальный район | F69: =VLOOKUP(H69,[1]ОКТМО!B:J,9,0) -> Атамайский наслег | G69: =VLOOKUP(H69,[1]ОКТМО!B:M,12,0) -> Бясь-Кюель | H69: 98620405101 | I69: 4 ИЖД, 15 двор/терр. | J69: ул. Речная д.2, 6, переулок Артык д.4, ул. Лонгинова д13.
A70: 45053 | B70: р. Тиэрэ | C70: Мегино-Кангаласский район, МО "Батаринский 1-й наслег" | D70: с. Бедимя | E70: =VLOOKUP(H70,[1]ОКТМО!B:J,6,0) -> Мегино-Кангаласский муниципальный район | F70: =VLOOKUP(H70,[1]ОКТМО!B:J,9,0) -> Батаринский 1-й наслег | G70: =VLOOKUP(H70,[1]ОКТМО!B:M,12,0) -> Бедемё | H70: 98629406101 | I70: 29 дворовых территорий | J70: ул. Молодежная д.6, 8, 10,12,14,16,18,20,22, 23, 24,25,б/н, ул. Батаринская д.9, 11, 13, 15,17,19,19/1, 21, 25,27/1,29,31,33, ул. Героя Попова д. 30, 32, 34,
A71: 45053 | B71: р. Саадахтаах | C71: Мегино-Кангаласский район, МО "Хоробутский наслег" | D71: с. Хоробут | E71: =VLOOKUP(H71,[1]ОКТМО!B:J,6,0) -> Мегино-Кангаласский муниципальный район | F71: =VLOOKUP(H71,[1]ОКТМО!B:J,9,0) -> Хоробутский наслег | G71: =VLOOKUP(H71,[1]ОКТМО!B:M,12,0) -> Хоробут | H71: 98629430101 | I71: 4 ИЖД, 17 двор/терр. | J71: ул. 40 лет Победы д. 18,16,14,8,2,5,7,17,19,21,10,10/1,23, ул. Дмитрия Таас д. 30,26,19,23, ул. Советская д. 17
A72: 45055 | B72: р. Хочо, р. Ар5аа, р. Илин | C72: Мегино-Кангаласский район, МО "Нахаринский 2-й наслег" | D72: с. Хочо | E72: =VLOOKUP(H72,[1]ОКТМО!B:J,6,0) -> Мегино-Кангаласский муниципальный район | F72: =VLOOKUP(H72,[1]ОКТМО!B:J,9,0) -> Нахаринский 2-й наслег | G72: =VLOOKUP(H72,[1]ОКТМО!B:M,12,0) -> Хочо | H72: 98629440101 | I72: 16 дворовых территорий | J72: ул. Колхозная д. 6 кв 2, д.6 кв 1, д.4 кв 2, д.2 кв 2, д.2 кв 1: ул. Советская д. 1 кв 1, д.1 кв 2,д.1 кв 3, д.1 кв 4, ул. Пионерская д. 6, 8, 10, 12, 14, ул. Пинерская д.7 МКД
A73: 45055 | B73: Кутэр Саахтаах | C73: Мегино-Кангаласский район, МО "Ходоринский наслег" | D73: с. Чуйя | E73: =VLOOKUP(H73,[1]ОКТМО!B:J,6,0) -> Мегино-Кангаласский муниципальный район | F73: =VLOOKUP(H73,[1]ОКТМО!B:J,9,0) -> Ходоринский наслег | G73: =VLOOKUP(H73,[1]ОКТМО!B:M,12,0) -> Чюйя | H73: 98629463101 | I73: 6 дворовых территорий | J73: ул. Школьная д. 3, 5, 7, 9; ул. Комсомольская д. 8/3, 6/2 | K73: Республика Саха (Якутия), м.р-н Мегино-Кангаласский, с.п. Ходоринский наслег, с Чюйя, ул Школьная, д. 3
E74: =VLOOKUP(H74,[1]ОКТМО!B:J,6,0) -> Мегино-Кангаласский муниципальный район | F74: =VLOOKUP(H74,[1]ОКТМО!B:J,9,0) -> Ходоринский наслег | G74: =VLOOKUP(H74,[1]ОКТМО!B:M,12,0) -> Чюйя | H74: 98629463101 | K74: Республика Саха (Якутия), м.р-н Мегино-Кангаласский, с.п. Ходоринский наслег, с Чюйя, ул Школьная, д. 5
E75: =VLOOKUP(H75,[1]ОКТМО!B:J,6,0) -> Мегино-Кангаласский муниципальный район | F75: =VLOOKUP(H75,[1]ОКТМО!B:J,9,0) -> Ходоринский наслег | G75: =VLOOKUP(H75,[1]ОКТМО!B:M,12,0) -> Чюйя | H75: 98629463101 | K75: Республика Саха (Якутия), м.р-н Мегино-Кангаласский, с.п. Ходоринский наслег, с Чюйя, ул Школьная, д. 7
E76: =VLOOKUP(H76,[1]ОКТМО!B:J,6,0) -> Мегино-Кангаласский муниципальный район | F76: =VLOOKUP(H76,[1]ОКТМО!B:J,9,0) -> Ходоринский наслег | G76: =VLOOKUP(H76,[1]ОКТМО!B:M,12,0) -> Чюйя | H76: 98629463101 | K76: Республика Саха (Якутия), м.р-н Мегино-Кангаласский, с.п. Ходоринский наслег, с Чюйя, ул Школьная, д. 9
E77: =VLOOKUP(H77,[1]ОКТМО!B:J,6,0) -> Мегино-Кангаласский муниципальный район | F77: =VLOOKUP(H77,[1]ОКТМО!B:J,9,0) -> Ходоринский наслег | G77: =VLOOKUP(H77,[1]ОКТМО!B:M,12,0) -> Чюйя | H77: 98629463101 | K77: Республика Саха (Якутия), м.р-н Мегино-Кангаласский, с.п. Ходоринский наслег, с Чюйя, ул Комсомольская, д. 8/3
E78: =VLOOKUP(H78,[1]ОКТМО!B:J,6,0) -> Мегино-Кангаласский муниципальный район | F78: =VLOOKUP(H78,[1]ОКТМО!B:J,9,0) -> Ходоринский наслег | G78: =VLOOKUP(H78,[1]ОКТМО!B:M,12,0) -> Чюйя | H78: 98629463101 | K78: Республика Саха (Якутия), м.р-н Мегино-Кангаласский, с.п. Ходоринский наслег, с Чюйя, ул Комсомольская, д. 6/2
A79: 45056 | B79: р. Вилюй | C79: Вилюйский район МО "Борогонский наслег" | D79: с. Чай | E79: =VLOOKUP(H79,[1]ОКТМО!B:J,6,0) -> Вилюйский муниципальный район | F79: =VLOOKUP(H79,[1]ОКТМО!B:J,9,0) -> Борогонский наслег | G79: =VLOOKUP(H79,[1]ОКТМО!B:M,12,0) -> Чай | H79: 98618416101 | I79: 2 ИЖС, 7 двор/терр.
A80: 45058 | B80: Маатта | C80: Горный район МО "Бердигестяхский наслег" | D80: с. Бердигестях | E80: =VLOOKUP(H80,[1]ОКТМО!B:J,6,0) -> Горный муниципальный район | F80: =VLOOKUP(H80,[1]ОКТМО!B:J,9,0) -> Бердигестяхский наслег | G80: =VLOOKUP(H80,[1]ОКТМО!B:M,12,0) -> Бердигестях | H80: 98620410101 | I80: 5 дворовых территорий
A81: 45063 | B81: р. Лена | C81: Хангаласский район МО "Мальжагарский 5-й наслег" | D81: с. Кытыл-Дюра | E81: =VLOOKUP(H81,[1]ОКТМО!B:J,6,0) -> Хангаласский муниципальный район | F81: =VLOOKUP(H81,[1]ОКТМО!B:J,9,0) -> Мальжагарский 5-й наслег | G81: =VLOOKUP(H81,[1]ОКТМО!B:M,12,0) -> Кытыл-Дюра | H81: 98644428101 | I81: 2 ИЖД | J81: ул. Молодежная д.1, ул. Исая Никифорова д.3, 5; ул. Луговая д.10
A82: 45066 | B82: р. Лена | C82: Намский район МО "Арбынский наслег" | D82: с. Арбын | E82: =VLOOKUP(H82,[1]ОКТМО!B:J,6,0) -> Намский муниципальный район | F82: =VLOOKUP(H82,[1]ОКТМО!B:J,9,0) -> Арбынский наслег | G82: =VLOOKUP(H82,[1]ОКТМО!B:M,12,0) -> Сыгыннах | H82: 98635405101 | I82: 2 ИЖД, 35 двор/терр. | J82: ул. Е.Ильиной, ул. Н. Иванова
A83: 45066 | B83: р. Лена | C83: Намский район, МО "Салбанский наслег" | D83: с. Хонгор-Биэ | E83: =VLOOKUP(H83,[1]ОКТМО!B:J,6,0) -> Намский муниципальный район | F83: =VLOOKUP(H83,[1]ОКТМО!B:J,9,0) -> Салбанский наслег | G83: =VLOOKUP(H83,[1]ОКТМО!B:M,12,0) -> Хонгор-Бие | H83: 98635440101 | I83: 7 ИЖД, 17 двор/терр.
A84: 45066 | B84: р. Амга | C84: Амгинский район, МО "Амгинский наслег" | D84: с. Амга | E84: =VLOOKUP(H84,[1]ОКТМО!B:J,6,0) -> Амгинский муниципальный район | F84: =VLOOKUP(H84,[1]ОКТМО!B:J,9,0) -> Амгинский наслег | G84: =VLOOKUP(H84,[1]ОКТМО!B:M,12,0) -> Амга | H84: 98608432101 | I84: 44 дворовых территорий
A85: 45066 | B85: р. Амга | C85: Амгинский район, МО "Чапчылганский наслег" | D85: с. Чапчылган | E85: =VLOOKUP(H85,[1]ОКТМО!B:J,6,0) -> Амгинский муниципальный район | F85: =VLOOKUP(H85,[1]ОКТМО!B:J,9,0) -> Чапчылганский наслег | G85: =VLOOKUP(H85,[1]ОКТМО!B:M,12,0) -> Чапчылган | H85: 98608472101 | I85: 33 дворовых территорий
A86: 45067 | B86: р. Наммара, р. Таатта | C86: Таттинский район, МО "Таттинский наслег" | D86: с. Ытык-Кюель | E86: =VLOOKUP(H86,[1]ОКТМО!B:J,6,0) -> Таттинский муниципальный район | F86: =VLOOKUP(H86,[1]ОКТМО!B:J,9,0) -> Таттинский наслег | G86: =VLOOKUP(H86,[1]ОКТМО!B:M,12,0) -> Ытык-Кюёль | H86: 98604445101 | I86: 11 дворовых территорий | J86: ул. Нутчина , ул. Ойунского
A87: 45068 | B87: р. Амга | C87: Таттинский район, МО "Жулейский наслег" | D87: с. Туора-Кюель | E87: =VLOOKUP(H87,[1]ОКТМО!B:J,6,0) -> Таттинский муниципальный район | F87: =VLOOKUP(H87,[1]ОКТМО!B:J,9,0) -> Жулейский наслег | G87: =VLOOKUP(H87,[1]ОКТМО!B:M,12,0) -> Туора-Кюёль | H87: 98604425101 | I87: 2 дворовые территории
A88: 45069 | B88: р. Амга, р. Суола | C88: Амгинский район МО "Мяндигинский наслег" | D88: с. Мяндиги | E88: =VLOOKUP(H88,[1]ОКТМО!B:J,6,0) -> Амгинский муниципальный район | F88: =VLOOKUP(H88,[1]ОКТМО!B:J,9,0) -> Мяндигинский наслег | G88: =VLOOKUP(H88,[1]ОКТМО!B:M,12,0) -> Мяндиги | H88: 98608455101 | I88: 5 дворовых территорий
A89: 45069 | B89: р. Чагдинка | C89: Кобяйский район, МО "Нижилинский наслег" | D89: с. Чагда | E89: =VLOOKUP(H89,[1]ОКТМО!B:J,6,0) -> Алданский муниципальный район | F89: =VLOOKUP(H89,[1]ОКТМО!B:J,9,0) -> Чагдинский наслег | G89: =VLOOKUP(H89,[1]ОКТМО!B:M,12,0) -> Чагда | H89: 98603460101 | I89: 22 ИЖД | J89: ул. Центральная д.5, 8, 10 | L89: 30
A90: 45069 | B90: р. Синнегес | C90: Кобяйский район, МО "Ситтинский наслег" | D90: с. Ситте | E90: =VLOOKUP(H90,[1]ОКТМО!B:J,6,0) -> Кобяйский муниципальный район | F90: =VLOOKUP(H90,[1]ОКТМО!B:J,9,0) -> Ситтинский наслег | G90: =VLOOKUP(H90,[1]ОКТМО!B:M,12,0) -> Ситте | H90: 98624450101 | I90: 1 ИЖД, 56 двор/терр. | L90: 205
A91: 45069 | B91: р. Лунгха | C91: Кобяйский район, МО "Куокуйский наслег" | D91: с. Аргас | E91: =VLOOKUP(H91,[1]ОКТМО!B:J,6,0) -> Кобяйский муниципальный район | F91: =VLOOKUP(H91,[1]ОКТМО!B:J,9,0) -> Куокуйский наслег | G91: =VLOOKUP(H91,[1]ОКТМО!B:M,12,0) -> Аргас | H91: 98624424101 | I91: 7 дворовых территорий | J91: ул. Им.Г.Иванова д. 7, 8, 9, 11, 12, 13, 15 | K91: Республика Саха (Якутия), м.р-н Кобяйский, с.п. Куокуйский наслег, с Аргас, ул им В.Иванова, д. 7 | L91: 724
E92: =VLOOKUP(H92,[1]ОКТМО!B:J,6,0) -> Кобяйский муниципальный район | F92: =VLOOKUP(H92,[1]ОКТМО!B:J,9,0) -> Куокуйский наслег | G92: =VLOOKUP(H92,[1]ОКТМО!B:M,12,0) -> Аргас | H92: 98624424101 | K92: Республика Саха (Якутия), м.р-н Кобяйский, с.п. Куокуйский наслег, с Аргас, ул им В.Иванова, д. 8 | L92: 724
E93: =VLOOKUP(H93,[1]ОКТМО!B:J,6,0) -> Кобяйский муниципальный район | F93: =VLOOKUP(H93,[1]ОКТМО!B:J,9,0) -> Куокуйский наслег | G93: =VLOOKUP(H93,[1]ОКТМО!B:M,12,0) -> Аргас | H93: 98624424101 | K93: Республика Саха (Якутия), м.р-н Кобяйский, с.п. Куокуйский наслег, с Аргас, ул им В.Иванова, д. 9 | L93: 724
E94: =VLOOKUP(H94,[1]ОКТМО!B:J,6,0) -> Кобяйский муниципальный район | F94: =VLOOKUP(H94,[1]ОКТМО!B:J,9,0) -> Куокуйский наслег | G94: =VLOOKUP(H94,[1]ОКТМО!B:M,12,0) -> Аргас | H94: 98624424101 | K94: Республика Саха (Якутия), м.р-н Кобяйский, с.п. Куокуйский наслег, с Аргас, ул им В.Иванова, д. 11 | L94: 724
E95: =VLOOKUP(H95,[1]ОКТМО!B:J,6,0) -> Кобяйский муниципальный район | F95: =VLOOKUP(H95,[1]ОКТМО!B:J,9,0) -> Куокуйский наслег | G95: =VLOOKUP(H95,[1]ОКТМО!B:M,12,0) -> Аргас | H95: 98624424101 | K95: Республика Саха (Якутия), м.р-н Кобяйский, с.п. Куокуйский наслег, с Аргас, ул им В.Иванова, д. 12 | L95: 724
E96: =VLOOKUP(H96,[1]ОКТМО!B:J,6,0) -> Кобяйский муниципальный район | F96: =VLOOKUP(H96,[1]ОКТМО!B:J,9,0) -> Куокуйский наслег | G96: =VLOOKUP(H96,[1]ОКТМО!B:M,12,0) -> Аргас | H96: 98624424101 | K96: Республика Саха (Якутия), м.р-н Кобяйский, с.п. Куокуйский наслег, с Аргас, ул им В.Иванова, д. 13 | L96: 724
E97: =VLOOKUP(H97,[1]ОКТМО!B:J,6,0) -> Кобяйский муниципальный район | F97: =VLOOKUP(H97,[1]ОКТМО!B:J,9,0) -> Куокуйский наслег | G97: =VLOOKUP(H97,[1]ОКТМО!B:M,12,0) -> Аргас | H97: 98624424101 | K97: Республика Саха (Якутия), м.р-н Кобяйский, с.п. Куокуйский наслег, с Аргас, ул им В.Иванова, д. 15 | L97: 724
A98: 45070 | B98: р. Амга | C98: Таттинский район, МО "Усть-Амгинский наслег" | D98: с. Чимнайи | E98: =VLOOKUP(H98,[1]ОКТМО!B:J,6,0) -> Таттинский муниципальный район | F98: =VLOOKUP(H98,[1]ОКТМО!B:J,9,0) -> Усть-Амгинский наслег | G98: =VLOOKUP(H98,[1]ОКТМО!B:M,12,0) -> Чымнайи | H98: 98604460101 | I98: 25 дворовых территорий | L98: 1223
A99: 45071 | B99: р. Амга | C99: Таттинский район, МО "Средне-Амгинский наслег" | D99: с. Харбалах | E99: =VLOOKUP(H99,[1]ОКТМО!B:J,6,0) -> Таттинский муниципальный район | F99: =VLOOKUP(H99,[1]ОКТМО!B:J,9,0) -> Средне-Амгинский наслег | G99: =VLOOKUP(H99,[1]ОКТМО!B:M,12,0) -> Харбалах | H99: 98604440101 | I99: 27 дворовых территорий
A100: 45073 | B100: р. Амга | C100: Чурапчинский район, МО "Болтогинский наслег" | D100: с. Харбала 2 | E100: =VLOOKUP(H100,[1]ОКТМО!B:J,6,0) -> Чурапчинский муниципальный район | F100: =VLOOKUP(H100,[1]ОКТМО!B:J,9,0) -> Болтогинский наслег | G100: =VLOOKUP(H100,[1]ОКТМО!B:M,12,0) -> Харбала 2-я | H100: 98658410101 | I100: 10 дворовых территорий
A101: 45075 | B101: р. Амга | C101: Таттинский район, МО "Октябрьский наслег" | D101: с. Черкех | E101: =VLOOKUP(H101,[1]ОКТМО!B:J,6,0) -> Таттинский муниципальный район | F101: =VLOOKUP(H101,[1]ОКТМО!B:J,9,0) -> Октябрьский наслег | G101: =VLOOKUP(H101,[1]ОКТМО!B:M,12,0) -> Черкёх | H101: 98604435101 | I101: 4 ИЖС, 77 двор/терр.
...

Sheet Реестр_затопленных_НП
A1: Район | B1: Наслег | C1: ОКТМО | D1: Период | E1: Река | F1: Населенный пункт | G1: Год затопления | I1: Кол-во ошибок "#н/д" | J1: =COUNTIF(C:C,"#н/д") -> 0
A2: =VLOOKUP(C2,[1]ОКТМО!B:J,6,0) -> Ленский муниципальный район | B2: =VLOOKUP(C2,[1]ОКТМО!B:J,9,0) -> поселок Витим | C2: 98627153051 | D2: Весеннее половодье | E2: Лена | F2: Витим | G2: 2006 | I2: Кол-во "не н.п." | J2: =COUNTIF(C:C,"не н.п.") -> 1
A3: =VLOOKUP(C3,[1]ОКТМО!B:J,6,0) -> Ленский муниципальный район | B3: =VLOOKUP(C3,[1]ОКТМО!B:J,9,0) -> город Ленск | C3: 98627101001 | D3: Весеннее половодье | E3: Лена | F3: Ленск | G3: 2001
A4: =VLOOKUP(C4,[1]ОКТМО!B:J,6,0) -> Олекминский муниципальный район | B4: =VLOOKUP(C4,[1]ОКТМО!B:J,9,0) -> Кыллахский наслег | C4: 98641430101 | D4: Весеннее половодье | E4: Лена | F4: Кыллах | G4: 2006
A5: =VLOOKUP(C5,[1]ОКТМО!B:J,6,0) -> Олекминский муниципальный район | B5: =VLOOKUP(C5,[1]ОКТМО!B:J,9,0) -> Кыллахский наслег | C5: 98641430101 | D5: Весеннее половодье | E5: Лена | F5: Кыллах | G5: 2011
A6: =VLOOKUP(C6,[1]ОКТМО!B:J,6,0) -> Олекминский муниципальный район | B6: =VLOOKUP(C6,[1]ОКТМО!B:J,9,0) -> Кыллахский наслег | C6: 98641430101 | D6: Весеннее половодье | E6: Лена | F6: Кыллах | G6: 2024
A7: =VLOOKUP(C7,[1]ОКТМО!B:J,6,0) -> Олекминский муниципальный район | B7: =VLOOKUP(C7,[1]ОКТМО!B:J,9,0) -> Троицкий наслег | C7: 98641470101 | D7: Весеннее половодье | E7: Лена | F7: Троицк | G7: 2011
A8: =VLOOKUP(C8,[1]ОКТМО!B:J,6,0) -> Олекминский муниципальный район | B8: =VLOOKUP(C8,[1]ОКТМО!B:J,9,0) -> Троицкий наслег | C8: 98641470101 | D8: Весеннее половодье | E8: Лена | F8: Троицк | G8: 2024
A9: =VLOOKUP(C9,[1]ОКТМО!B:J,6,0) -> Олекминский муниципальный район | B9: =VLOOKUP(C9,[1]ОКТМО!B:J,9,0) -> Солянский наслег | C9: 98641465101 | D9: Весеннее половодье | E9: Лена | F9: Солянка | G9: 2011
A10: =VLOOKUP(C10,[1]ОКТМО!B:J,6,0) -> Амгинский муниципальный район | B10: =VLOOKUP(C10,[1]ОКТМО!B:J,9,0) -> Абагинский наслег | C10: 98608405101 | D10: Весеннее половодье | E10: Лена | F10: Абага | G10: 2006
A11: =VLOOKUP(C11,[1]ОКТМО!B:J,6,0) -> Амгинский муниципальный район | B11: =VLOOKUP(C11,[1]ОКТМО!B:J,9,0) -> Абагинский наслег | C11: 98608405101 | D11: Весеннее половодье | E11: Лена | F11: Абага | G11: 2011
A12: =VLOOKUP(C12,[1]ОКТМО!B:J,6,0) -> Олекминский муниципальный район | B12: =VLOOKUP(C12,[1]ОКТМО!B:J,9,0) -> город Олекминск | C12: 98641101001 | D12: Весеннее половодье | E12: Лена | F12: Олёкминск | G12: 2001
A13: =VLOOKUP(C13,[1]ОКТМО!B:J,6,0) -> Олекминский муниципальный район | B13: =VLOOKUP(C13,[1]ОКТМО!B:J,9,0) -> город Олекминск | C13: 98641101001 | D13: Весеннее половодье | E13: Лена | F13: Олёкминск | G13: 2006
A14: =VLOOKUP(C14,[1]ОКТМО!B:J,6,0) -> Олекминский муниципальный район | B14: =VLOOKUP(C14,[1]ОКТМО!B:J,9,0) -> город Олекминск | C14: 98641101001 | D14: Весеннее половодье | E14: Лена | F14: Олёкминск | G14: 2011
... A313: =VLOOKUP(C313,[1]ОКТМО!B:J,6,0) -> Усть-Янский муниципальный район | B313: =VLOOKUP(C313,[1]ОКТМО!B:J,9,0) -> Казачинский национальный наслег | C313: 98656405101 | D313: Весеннее половодье | E313: Яна | F313: Казачье | G313: 2018
A314: =VLOOKUP(C314,[1]ОКТМО!B:J,6,0) -> #N/A | B314: =VLOOKUP(C314,[1]ОКТМО!B:J,9,0) -> #N/A | C314: не н.п. | D314: Весеннее половодье | E314: Яна | F314: Кресты | G314: 2018
A315: =VLOOKUP(C315,[1]ОКТМО!B:J,6,0) -> Анабарский национальный (долгано-эвенкийский) муниципальный район | B315: =VLOOKUP(C315,[1]ОКТМО!B:J,9,0) -> Саскылахский национальный (эвенкийский) наслег | C315: 98610411101 | D315: Весеннее половодье | E315: Анабар | F315: Саскылах | G315: 2017
A316: =VLOOKUP(C316,[1]ОКТМО!B:J,6,0) -> Анабарский национальный (долгано-эвенкийский) муниципальный район | B316: =VLOOKUP(C316,[1]ОКТМО!B:J,9,0) -> Саскылахский национальный (эвенкийский) наслег | C316: 98610411101 | D316: Весеннее половодье | E316: Анабар | F316: Саскылах | G316: 2023
A317: =VLOOKUP(C317,[1]ОКТМО!B:J,6,0) -> Анабарский национальный (долгано-эвенкийский) муниципальный район | B317: =VLOOKUP(C317,[1]ОКТМО!B:J,9,0) -> Саскылахский национальный (эвенкийский) наслег | C317: 98610411101 | D317: Весеннее половодье | E317: Анабар | F317: Саскылах | G317: 2024
A318: =VLOOKUP(C318,[1]ОКТМО!B:J,6,0) -> Анабарский национальный (долгано-эвенкийский) муниципальный район | B318: =VLOOKUP(C318,[1]ОКТМО!B:J,9,0) -> Юрюнг-Хаинский национальный (долганский) наслег | C318: 98610424101 | D318: Весеннее половодье | E318: Анабар | F318: Юрюнг-Хая | G318: 2017
A319: =VLOOKUP(C319,[1]ОКТМО!B:J,6,0) -> Момский муниципальный район | B319: =VLOOKUP(C319,[1]ОКТМО!B:J,9,0) -> Соболохский национальный наслег | C319: 98633428101 | D319: Весеннее половодье | E319: Индигирка | F319: Соболох | G319: 2020
A320: =VLOOKUP(C320,[1]ОКТМО!B:J,6,0) -> Мирнинский муниципальный район | B320: =VLOOKUP(C320,[1]ОКТМО!B:J,9,0) -> город Мирный | C320: 98631101106 | D320: Весеннее половодье | E320: Березовка | F320: Березовка | G320: 2007
A321: =VLOOKUP(C321,[1]ОКТМО!B:J,6,0) -> Мирнинский муниципальный район | B321: =VLOOKUP(C321,[1]ОКТМО!B:J,9,0) -> город Мирный | C321: 98631101106 | D321: Весеннее половодье | E321: Березовка | F321: Березовка | G321: 2011
A322: =VLOOKUP(C322,[1]ОКТМО!B:J,6,0) -> Мирнинский муниципальный район | B322: =VLOOKUP(C322,[1]ОКТМО!B:J,9,0) -> город Мирный | C322: 98631101106 | D322: Весеннее половодье | E322: Березовка | F322: Березовка | G322: 2017
A323: =VLOOKUP(C323,[1]ОКТМО!B:J,6,0) -> Мирнинский муниципальный район | B323: =VLOOKUP(C323,[1]ОКТМО!B:J,9,0) -> город Мирный | C323: 98631101106 | D323: Весеннее половодье | E323: Березовка | F323: Березовка | G323: 2018
A324: =VLOOKUP(C324,[1]ОКТМО!B:J,6,0) -> Мирнинский муниципальный район | B324: =VLOOKUP(C324,[1]ОКТМО!B:J,9,0) -> город Мирный | C324: 98631101106 | D324: Весеннее половодье | E324: Березовка | F324: Березовка | G324: 2020
A325: =VLOOKUP(C325,[1]ОКТМО!B:J,6,0) -> Ленский муниципальный район | B325: =VLOOKUP(C325,[1]ОКТМО!B:J,9,0) -> Орто-Нахаринский наслег | C325: 98627433101 | D325: Весеннее половодье | E325: Нюя | F325: Орто-Нахара | G325: 2001
A326: =VLOOKUP(C326,[1]ОКТМО!B:J,6,0) -> Олекминский муниципальный район | B326: =VLOOKUP(C326,[1]ОКТМО!B:J,9,0) -> Тянский национальный наслег | C326: 98641475101 | D326: Весеннее половодье | E326: Тяня | F326: Тяня | G326: 2023
... A361: =VLOOKUP(C361,[1]ОКТМО!B:J,6,0) -> Таттинский муниципальный район | B361: =VLOOKUP(C361,[1]ОКТМО!B:J,9,0) -> Жулейский наслег | C361: 98604425101 | D361: Весеннее половодье | E361: Оз. Мемен | F361: Туора-Кюель | G361: 2023
A362: =VLOOKUP(C362,[1]ОКТМО!B:J,6,0) -> Намский муниципальный район | B362: =VLOOKUP(C362,[1]ОКТМО!B:J,9,0) -> Салбанский наслег | C362: 98635440101 | D362: Весеннее половодье | F362: Салбанг (Хонгор-Биэ) | G362: 2023
A363: =VLOOKUP(C363,[1]ОКТМО!B:J,6,0) -> Таттинский муниципальный район | B363: =VLOOKUP(C363,[1]ОКТМО!B:J,9,0) -> Жулейский наслег | C363: 98604425101 | D363: Летне-осенние | E363: Оз. Мемен | F363: Туора-Кюель | G363: 2015
A364: =VLOOKUP(C364,[1]ОКТМО!B:J,6,0) -> Таттинский муниципальный район | B364: =VLOOKUP(C364,[1]ОКТМО!B:J,9,0) -> Таттинский наслег | C364: 98604445101 | D364: Летне-осенние | E364: Таатта | F364: Ытык-Кюёль | G364: 2012
A365: =VLOOKUP(C365,[1]ОКТМО!B:J,6,0) -> Таттинский муниципальный район | B365: =VLOOKUP(C365,[1]ОКТМО!B:J,9,0) -> Баягинский наслег | C365: 98604415101 | D365: Летне-осенние | E365: Баяга | F365: Баяга | G365: 2012
A366: =VLOOKUP(C366,[1]ОКТМО!B:J,6,0) -> Верхоянский муниципальный район | B366: =VLOOKUP(C366,[1]ОКТМО!B:J,9,0) -> Суордахский наслег | C366: 98616448101 | D366: Летне-осенние | E366: Дулгалах | F366: Суордах | G366: 2011
A367: =VLOOKUP(C367,[1]ОКТМО!B:J,6,0) -> Верхоянский муниципальный район | B367: =VLOOKUP(C367,[1]ОКТМО!B:J,9,0) -> Суордахский наслег | C367: 98616448101 | D367: Летне-осенние | E367: Дулгалах | F367: Суордах | G367: 2012
A368: =VLOOKUP(C368,[1]ОКТМО!B:J,6,0) -> Верхоянский муниципальный район | B368: =VLOOKUP(C368,[1]ОКТМО!B:J,9,0) -> Суордахский наслег | C368: 98616448101 | D368: Летне-осенние | E368: Дулгалах | F368: Суордах | G368: 2015
A369: =VLOOKUP(C369,[1]ОКТМО!B:J,6,0) -> Верхоянский муниципальный район | B369: =VLOOKUP(C369,[1]ОКТМО!B:J,9,0) -> Суордахский наслег | C369: 98616448101 | D369: Летне-осенние | E369: Дулгалах | F369: Суордах | G369: 2022
A370: =VLOOKUP(C370,[1]ОКТМО!B:J,6,0) -> Верхоянский муниципальный район | B370: =VLOOKUP(C370,[1]ОКТМО!B:J,9,0) -> Борулахский наслег | C370: 98616414101 | D370: Летне-осенние | E370: Дулгалах | F370: Томтор (Борулахский) | G370: 2012
A371: =VLOOKUP(C371,[1]ОКТМО!B:J,6,0) -> Верхоянский муниципальный район | B371: =VLOOKUP(C371,[1]ОКТМО!B:J,9,0) -> Борулахский наслег | C371: 98616414101 | D371: Летне-осенние | E371: Дулгалах | F371: Томтор (Борулахский) | G371: 2021
A372: =VLOOKUP(C372,[1]ОКТМО!B:J,6,0) -> Верхоянский муниципальный район | B372: =VLOOKUP(C372,[1]ОКТМО!B:J,9,0) -> Борулахский наслег | C372: 98616414101 | D372: Летне-осенние | E372: Дулгалах | F372: Томтор (Борулахский) | G372: 2022
A373: =VLOOKUP(C373,[1]ОКТМО!B:J,6,0) -> Верхоянский муниципальный район | B373: =VLOOKUP(C373,[1]ОКТМО!B:J,9,0) -> Борулахский наслег | C373: 98616414106 | D373: Летне-осенние | E373: Борулах | F373: Токума | G373: 2021
A374: =VLOOKUP(C374,[1]ОКТМО!B:J,6,0) -> Верхоянский муниципальный район | B374: =VLOOKUP(C374,[1]ОКТМО!B:J,9,0) -> Борулахский наслег | C374: 98616414106 | D374: Летне-осенние | E374: Борулах | F374: Токума | G374: 2022
... A440: =VLOOKUP(C440,[1]ОКТМО!B:J,6,0) -> Намский муниципальный район | B440: =VLOOKUP(C440,[1]ОКТМО!B:J,9,0) -> Арбынский наслег | C440: 98635405101 | D440: Летне-осенние | E440: Лена | F440: Сыгыннах | G440: 2022

Sheet Перечень_НП
A1: Перечень населённых пунктов на территории Республики Саха (Якутия), подверженных затоплению вследствие гидрологических и гидродинамических явлений и процессов
A2: № | B2: Дата | C2: Причина затопления | D2: Район, городской округ | E2: Водный объект | F2: Населенный пункт | G2: ОКТМО | H2: Геопозиция (широта) | I2: Геопозиция (долгота) | J2: Критический уровень, при котором происходит затопление (подтопление), см | K2: Количество населения в зоне возможного затопления, чел. | L2: Объекты затопления
L3: Жилые здания | M3: Социально значимые объекты | O3: Объекты экономики | Q3: Объекты жизнеобеспечения | S3: Примечание
A4: 1 | C4: 1. Риск весеннего половодья | D4: =VLOOKUP(G4,ОКТМО!B:G,6,0) -> Амгинский муниципальный район | E4: Амга | F4: =VLOOKUP(G4,ОКТМО!B:M,12,0) -> Амга | G4: 98608432101 | H4: =VLOOKUP(G4,ОКТМО!N:R,4,0) -> 60.8972222222222 | I4: =VLOOKUP(G4,ОКТМО!N:R,5,0) -> 131.980555555556 | J4: 925 | K4: 413 | L4: 64 | M4: 3 | N4: строится новый лагерь | O4: NULL | P4: упразднен | Q4: NULL | R4: NULL | S4: NULL | T4: =F4 -> Амга
A5: 2 | C5: 1. Риск весеннего половодья | D5: =VLOOKUP(G5,ОКТМО!B:G,6,0) -> Амгинский муниципальный район | E5: Амга | F5: =VLOOKUP(G5,ОКТМО!B:M,12,0) -> Чапчылган | G5: 98608472101 | H5: =VLOOKUP(G5,ОКТМО!N:R,4,0) -> 60.9133333333333 | I5: =VLOOKUP(G5,ОКТМО!N:R,5,0) -> 132.031111111111 | J5: 925 | K5: 338 | L5: 109 | M5: NULL | N5: NULL | O5: NULL | P5: NULL | Q5: NULL | R5: NULL | S5: NULL | T5: =F5 -> Чапчылган
A6: 3 | C6: 1. Риск весеннего половодья | D6: =VLOOKUP(G6,ОКТМО!B:G,6,0) -> Амгинский муниципальный район | E6: Амга | F6: =VLOOKUP(G6,ОКТМО!B:M,12,0) -> Абага | G6: 98608405101 | H6: =VLOOKUP(G6,ОКТМО!N:R,4,0) -> 61.0430555555556 | I6: =VLOOKUP(G6,ОКТМО!N:R,5,0) -> 132.283333333333 | J6: 960 | K6: 174 | L6: 45 | M6: NULL | N6: NULL | O6: NULL | P6: NULL | Q6: 1 | R6: ТП ВЛ-0,4кВт | S6: NULL | T6: =F6 -> Абага
A7: 4 | C7: 1. Риск весеннего половодья | D7: =VLOOKUP(G7,ОКТМО!B:G,6,0) -> Амгинский муниципальный район | E7: Амга | F7: =VLOOKUP(G7,ОКТМО!B:M,12,0) -> Мяндиги | G7: 98608455101 | H7: =VLOOKUP(G7,ОКТМО!N:R,4,0) -> 61.1808333333333 | I7: =VLOOKUP(G7,ОКТМО!N:R,5,0) -> 132.551388888889 | J7: 1000 | K7: 63 | L7: 22 | M7: NULL | N7: NULL | O7: NULL | P7: NULL | Q7: 2 | R7: ТП АВМ ВЛ-0,4кВт, котельная | S7: NULL | T7: =F7 -> Мяндиги
A8: 5 | C8: 1. Риск весеннего половодья | D8: =VLOOKUP(G8,ОКТМО!B:G,6,0) -> Амгинский муниципальный район | E8: Амга | F8: =VLOOKUP(G8,ОКТМО!B:M,12,0) -> Оннёс | G8: 98608429101 | H8: =VLOOKUP(G8,ОКТМО!N:R,4,0) -> 60.4613888888889 | I8: =VLOOKUP(G8,ОКТМО!N:R,5,0) -> 131.099444444444 | J8: NULL | K8: 3 | L8: 12 | M8: NULL | N8: NULL | O8: NULL | P8: NULL | Q8: NULL | R8: NULL | S8: NULL | T8: =F8 -> Оннёс
A9: 6 | C9: 1. Риск весеннего половодья | D9: =VLOOKUP(G9,ОКТМО!B:G,6,0) -> Амгинский муниципальный район | E9: Амга | F9: =VLOOKUP(G9,ОКТМО!B:M,12,0) -> Сатагай | G9: 98608458101 | H9: =VLOOKUP(G9,ОКТМО!N:R,4,0) -> 61.5658333333333 | I9: =VLOOKUP(G9,ОКТМО!N:R,5,0) -> 131.529722222222 | J9: 433 | K9: 93 | L9: 22 | M9: NULL | N9: NULL | O9: NULL | P9: NULL | Q9: NULL | R9: NULL | S9: NULL | T9: =F9 -> Сатагай
A10: 7 | C10: 1. Риск весеннего половодья | D10: =VLOOKUP(G10,ОКТМО!B:G,6,0) -> Амгинский муниципальный район | E10: Амга | F10: =VLOOKUP(G10,ОКТМО!B:M,12,0) -> Алтанцы | G10: 98608414101 | H10: =VLOOKUP(G10,ОКТМО!N:R,4,0) -> 61.4702777777778 | I10: =VLOOKUP(G10,ОКТМО!N:R,5,0) -> 131.501944444444 | J10: 632 | K10: 145 | L10: 49 | M10: NULL | N10: NULL | O10: NULL | P10: NULL | Q10: 1 | R10: ТП 143 ВЛ-0,4кВт | S10: NULL | T10: =F10 -> Алтанцы
A11: 8 | C11: 1. Риск весеннего половодья | D11: =VLOOKUP(G11,ОКТМО!B:G,6,0) -> Анабарский национальный (долгано-эвенкийский) муниципальный район | E11: Анабар | F11: =VLOOKUP(G11,ОКТМО!B:M,12,0) -> Саскылах | G11: 98610411101 | H11: =VLOOKUP(G11,ОКТМО!N:R,4,0) -> 71.9652777777778 | I11: =VLOOKUP(G11,ОКТМО!N:R,5,0) -> 114.092222222222 | J11: 1170 | K11: 98 | L11: 15 | M11: NULL | N11: NULL | O11: 3 | P11: ул.Авиаторов, ул.Авиапортовская, Взлетно-посадочная полоса | Q11: 1 | R11: Накопитель аэропорта | S11: NULL | T11: =F11 -> Саскылах
A12: 9 | C12: 1. Риск весеннего половодья | D12: =VLOOKUP(G12,ОКТМО!B:G,6,0) -> Анабарский национальный (долгано-эвенкийский) муниципальный район | E12: Анабар | F12: =VLOOKUP(G12,ОКТМО!B:M,12,0) -> Юрюнг-Хая | G12: 98610424101 | H12: =VLOOKUP(G12,ОКТМО!N:R,4,0) -> 72.8119444444444 | I12: =VLOOKUP(G12,ОКТМО!N:R,5,0) -> 113.232222222222 | J12: NULL | K12: NULL | L12: NULL | M12: NULL | N12: NULL | O12: NULL | P12: NULL | Q12: NULL | R12: NULL | S12: NULL | T12: =F12 -> Юрюнг-Хая
A13: 10 | C13: 1. Риск весеннего половодья | D13: =VLOOKUP(G13,ОКТМО!B:G,6,0) -> Аллаиховский муниципальный район | E13: Бёрёлёх | F13: =VLOOKUP(G13,ОКТМО!B:M,12,0) -> Чкалов | G13: 98606424101 | H13: =VLOOKUP(G13,ОКТМО!N:R,4,0) -> 70.5327777777778 | I13: =VLOOKUP(G13,ОКТМО!N:R,5,0) -> 144.7025 | J13: 187 | K13: 81 | L13: 16 | M13: 5 | N13: 5 | O13: 2 | P13: 2 | Q13: 2 | R13: 2 | S13: NULL | T13: =F13 -> Чкалов
A14: 11 | C14: 1. Риск весеннего половодья | D14: =VLOOKUP(G14,ОКТМО!B:G,6,0) -> Алданский муниципальный район | E14: Алдан | F14: =VLOOKUP(G14,ОКТМО!B:M,12,0) -> Хатыстыр | G14: 98603407101 | H14: =VLOOKUP(G14,ОКТМО!N:R,4,0) -> 58.9230555555556 | I14: =VLOOKUP(G14,ОКТМО!N:R,5,0) -> 125.16 | J14: NULL | K14: 32 | L14: 15 | M14: NULL | N14: NULL | O14: NULL | P14: NULL | Q14: NULL | R14: NULL | S14: запрет выделения з/у | T14: =F14 -> Хатыстыр
A15: 12 | C15: 1. Риск весеннего половодья | D15: =VLOOKUP(G15,ОКТМО!B:G,6,0) -> Алданский муниципальный район | E15: Алдан | F15: =VLOOKUP(G15,ОКТМО!B:M,12,0) -> Угоян | G15: 98603407106 | H15: =VLOOKUP(G15,ОКТМО!N:R,4,0) -> 59.2536111111111 | I15: =VLOOKUP(G15,ОКТМО!N:R,5,0) -> 125.290555555556 | J15: NULL | K15: 375 | L15: 62 | M15: NULL | N15: NULL | O15: NULL | P15: NULL | Q15: NULL | R15: NULL | S15: запрет выделения з/у | T15: =F15 -> Угоян
A16: 13 | C16: 1. Риск весеннего половодья | D16: =VLOOKUP(G16,ОКТМО!B:G,6,0) -> Алданский муниципальный район | E16: Алдан | F16: =VLOOKUP(G16,ОКТМО!B:M,12,0) -> Чагда | G16: 98603460101 | H16: =VLOOKUP(G16,ОКТМО!N:R,4,0) -> 58.7494444444444 | I16: =VLOOKUP(G16,ОКТМО!N:R,5,0) -> 130.608333333333 | J16: 1530 | K16: 39 | L16: 18 | M16: NULL | N16: NULL | O16: NULL | P16: NULL | Q16: NULL | R16: NULL | S16: NULL | T16: =F16 -> Чагда
A17: 14 | C17: 1. Риск весеннего половодья | D17: =VLOOKUP(G17,ОКТМО!B:G,6,0) -> Алданский муниципальный район | E17: Алдан | F17: =VLOOKUP(G17,ОКТМО!B:M,12,0) -> Кутана | G17: 98603404101 | H17: =VLOOKUP(G17,ОКТМО!N:R,4,0) -> 59.015 | I17: =VLOOKUP(G17,ОКТМО!N:R,5,0) -> 131.744444444444 | J17: NULL | K17: 332 | L17: 107 | M17: NULL | N17: NULL | O17: NULL | P17: NULL | Q17: NULL | R17: NULL | S17: NULL | T17: =F17 -> Кутана
A18: 15 | C18: 1. Риск весеннего половодья | D18: =VLOOKUP(G18,ОКТМО!B:G,6,0) -> Булунский муниципальный район | E18: Оленек | F18: =VLOOKUP(G18,ОКТМО!B:M,12,0) -> Таймылыр | G18: 98612445101 | H18: =VLOOKUP(G18,ОКТМО!N:R,4,0) -> 72.6119444444444 | I18: =VLOOKUP(G18,ОКТМО!N:R,5,0) -> 121.911944444444 | J18: 1400 | K18: 10 | L18: 2 | M18: 1 | N18: МБДОУ «Тугутчаан» | O18: NULL | P18: NULL | Q18: 1 | R18: ДЭС АО «Сахаэнерго» | S18: NULL | T18: =F18 -> Таймылыр
A19: 16 | C19: 1. Риск весеннего половодья | D19: =VLOOKUP(G19,ОКТМО!B:G,6,0) -> Булунский муниципальный район | E19: Лена | F19: =VLOOKUP(G19,ОКТМО!B:M,12,0) -> Кюсюр | G19: 98612412101 | H19: =VLOOKUP(G19,ОКТМО!N:R,4,0) -> 70.6861111111111 | I19: =VLOOKUP(G19,ОКТМО!N:R,5,0) -> 127.361666666667 | J19: 3100 | K19: 175 | L19: 32 | M19: 2 | N19: МБУ ЭКЦ «Чолбондор», КВА | O19: NULL | P19: NULL | Q19: 3 | R19: Нефтебаза ГУП «ЖКХ РС(Я)»,котельная «Центральная», котельная «Тундровая» | S19: NULL | T19: =F19 -> Кюсюр
A20: 17 | C20: 1. Риск весеннего половодья | D20: =VLOOKUP(G20,ОКТМО!B:G,6,0) -> Верхоянский муниципальный район | E20: Яна | F20: =VLOOKUP(G20,ОКТМО!B:M,12,0) -> Верхоянск | G20: 98616103001 | H20: =VLOOKUP(G20,ОКТМО!N:R,4,0) -> 67.55 | I20: =VLOOKUP(G20,ОКТМО!N:R,5,0) -> 133.383333333333 | J20: 1020 | K20: 450 | L20: 98 | M20: 6 | N20: больница, ферма СПХ, контора ГУП ЖКХ, объекты обслуж. компании ООО Энергопром, д/с № 1 гл. корпус, метеостанция | O20: NULL | P20: NULL | Q20: 3 | R20: котельная САП, котельная Квартальная, котельная Авиапорт | S20: строительство защитного сооружения, запрет на выделение з/у | T20: =F20 -> Верхоянск
A21: 18 | C21: 1. Риск весеннего половодья | D21: =VLOOKUP(G21,ОКТМО!B:G,6,0) -> Верхоянский муниципальный район | E21: Яна | F21: =VLOOKUP(G21,ОКТМО!B:M,12,0) -> Батагай | G21: 98616151051 | H21: =VLOOKUP(G21,ОКТМО!N:R,4,0) -> 67.6536111111111 | I21: =VLOOKUP(G21,ОКТМО!N:R,5,0) -> 134.631944444444 | J21: 970 | K21: 16 | L21: 10 | M21: NULL | N21: NULL | O21: 1 | P21: 1 | Q21: NULL | R21: NULL | S21: NULL | T21: =F21 -> Батагай
A22: 19 | C22: 1. Риск весеннего половодья | D22: =VLOOKUP(G22,ОКТМО!B:G,6,0) -> Верхнеколымский муниципальный район | E22: Колыма | F22: =VLOOKUP(G22,ОКТМО!B:M,12,0) -> Зырянка | G22: 98615151051 | H22: =VLOOKUP(G22,ОКТМО!N:R,4,0) -> 65.7344444444444 | I22: =VLOOKUP(G22,ОКТМО!N:R,5,0) -> 150.897777777778 | J22: 770 | K22: 806 | L22: 54 | M22: 1 | N22: МОБУ «ЗСОШ» | O22: 2 | P22: ВПП аэропорта Зырянка ФКП «Аэропорты Севера», нефтебаза АО "СНГС" | Q22: 2 | R22: кот. № 2, кот. № 3 | S22: NULL | T22: =F22 -> Зырянка
A23: 20 | C23: 1. Риск весеннего половодья | D23: =VLOOKUP(G23,ОКТМО!B:G,6,0) -> Верхнеколымский муниципальный район | E23: Ясачная | F23: =VLOOKUP(G23,ОКТМО!B:M,12,0) -> Верхнеколымск | G23: 98615409101 | H23: =VLOOKUP(G23,ОКТМО!N:R,4,0) -> 65.7183333333333 | I23: =VLOOKUP(G23,ОКТМО!N:R,5,0) -> 150.833055555556 | J23: NULL | K23: 188 | L23: 33 | M23: 3 | N23: д/с, ФАП, СЦК | O23: 1 | P23: мост | Q23: NULL | R23: NULL | S23: NULL | T23: =F23 -> Верхнеколымск
A24: 21 | C24: 1. Риск весеннего половодья | D24: =VLOOKUP(G24,ОКТМО!B:G,6,0) -> Вилюйский муниципальный район | E24: Вилюй | F24: =VLOOKUP(G24,ОКТМО!B:M,12,0) -> Староватово | G24: 98618462106 | H24: =VLOOKUP(G24,ОКТМО!N:R,4,0) -> 63.7836111111111 | I24: =VLOOKUP(G24,ОКТМО!N:R,5,0) -> 121.624444444444 | J24: 980 | K24: 38 | L24: 10 | M24: 1 | N24: д/с МБДОУ «Кэчээри» ул.Вилюйская д.3 | O24: 1 | P24: нефтесклад «Вилюйск» Нюрибнского филиала АО Саханефтегазсбыт | Q24: 1 | R24: котельная ВФ ГУП «ЖКХ РС(Я)» ул.Вилюйская д.1А | S24: 1 | T24: =F24 -> Староватово
A25: 22 | C25: 1. Риск весеннего половодья | D25: =VLOOKUP(G25,ОКТМО!B:G,6,0) -> Кобяйский муниципальный район | E25: Лена | F25: =VLOOKUP(G25,ОКТМО!B:M,12,0) -> Батамай | G25: 98624414106 | H25: =VLOOKUP(G25,ОКТМО!N:R,4,0) -> 63.5247222222222 | I25: =VLOOKUP(G25,ОКТМО!N:R,5,0) -> 129.418611111111 | J25: NULL | K25: NULL | L25: NULL | M25: 3 | N25: ФАП, СДК, школа-сад | O25: NULL | P25: NULL | Q25: NULL | R25: NULL | S25: NULL | T25: =F25 -> Батамай
A26: 23 | C26: 1. Риск весеннего половодья | D26: =VLOOKUP(G26,ОКТМО!B:G,6,0) -> Кобяйский муниципальный район | E26: Лена | F26: =VLOOKUP(G26,ОКТМО!B:M,12,0) -> Ситте | G26: 98624450101 | H26: =VLOOKUP(G26,ОКТМО!N:R,4,0) -> 63.4883333333333 | I26: =VLOOKUP(G26,ОКТМО!N:R,5,0) -> 128.035277777778 | J26: 1140 | K26: 215 | L26: 73 | M26: 3 | N26: д/с, ФАП, ДК | O26: NULL | P26: NULL | Q26: NULL | R26: NULL | S26: NULL | T26: =F26 -> Ситте
A27: 24 | C27: 1. Риск весеннего половодья | D27: =VLOOKUP(G27,ОКТМО!B:G,6,0) -> Кобяйский муниципальный район | E27: Лена | F27: =VLOOKUP(G27,ОКТМО!B:M,12,0) -> Сангар | G27: 98624151051 | H27: =VLOOKUP(G27,ОКТМО!N:R,4,0) -> 63.9194444444444 | I27: =VLOOKUP(G27,ОКТМО!N:R,5,0) -> 127.485833333333 | J27: NULL | K27: 57 | L27: 15 | M27: 3 | N27: д/с | O27: 1 | P27: дорога в аэропорт «Сангар» | Q27: NULL | R27: NULL | S27: NULL | T27: =F27 -> Сангар
A28: 25 | C28: 1. Риск весеннего половодья | D28: =VLOOKUP(G28,ОКТМО!B:G,6,0) -> Кобяйский муниципальный район | E28: Лена | F28: =VLOOKUP(G28,ОКТМО!B:M,12,0) -> Аргас | G28: 98624424101 | H28: =VLOOKUP(G28,ОКТМО!N:R,4,0) -> 63.9633333333333 | I28: =VLOOKUP(G28,ОКТМО!N:R,5,0) -> 126.621944444444 | J28: 1315 | K28: 70 | L28: 26 | M28: 2 | N28: библиотека, музей | O28: NULL | P28: NULL | Q28: NULL | R28: NULL | S28: NULL | T28: =F28 -> Аргас
A29: 26 | C29: 1. Риск весеннего половодья | D29: =VLOOKUP(G29,ОКТМО!B:G,6,0) -> Ленский муниципальный район | E29: Нюя | F29: =VLOOKUP(G29,ОКТМО!B:M,12,0) -> Орто-Нахара | G29: 98627433101 | H29: =VLOOKUP(G29,ОКТМО!N:R,4,0) -> 60.8236111111111 | I29: =VLOOKUP(G29,ОКТМО!N:R,5,0) -> 114.324166666667 | J29: 575 | K29: 29 | L29: 20 | M29: 1 | N29: дом культуры | O29: NULL | P29: NULL | Q29: NULL | R29: NULL | S29: NULL | T29: =F29 -> Орто-Нахара
A30: 27 | C30: 1. Риск весеннего половодья | D30: =VLOOKUP(G30,ОКТМО!B:G,6,0) -> Ленский муниципальный район | E30: Лена | F30: =VLOOKUP(G30,ОКТМО!B:M,12,0) -> Витим | G30: 98627153051 | H30: =VLOOKUP(G30,ОКТМО!N:R,4,0) -> 59.4380555555556 | I30: =VLOOKUP(G30,ОКТМО!N:R,5,0) -> 112.560277777778 | J30: 950 | K30: 809 | L30: 157 | M30: 1 | N30: котельная «Аэропорт» | O30: 1 | P30: территория ВРВПиС | Q30: 1 | R30: здание аэропорта АК «Аэропорты Севера» | S30: NULL | T30: =F30 -> Витим
A31: 28 | C31: 1. Риск весеннего половодья | D31: =VLOOKUP(G31,ОКТМО!B:G,6,0) -> Ленский муниципальный район | E31: Лена | F31: =VLOOKUP(G31,ОКТМО!B:M,12,0) -> Пеледуй | G31: 98627157051 | H31: =VLOOKUP(G31,ОКТМО!N:R,4,0) -> 59.6266666666667 | I31: =VLOOKUP(G31,ОКТМО!N:R,5,0) -> 112.750555555556 | J31: 1200 | K31: 52 | L31: 19 | M31: NULL | N31: NULL | O31: NULL | P31: NULL | Q31: NULL | R31: NULL | S31: NULL | T31: =F31 -> Пеледуй
A32: 29 | C32: 1. Риск весеннего половодья | D32: =VLOOKUP(G32,ОКТМО!B:G,6,0) -> Намский муниципальный район | E32: Лена | F32: =VLOOKUP(G32,ОКТМО!B:M,12,0) -> Ымыяхтах | G32: 98635415101 | H32: =VLOOKUP(G32,ОКТМО!N:R,4,0) -> 62.4561111111111 | I32: =VLOOKUP(G32,ОКТМО!N:R,5,0) -> 129.885277777778 | J32: 800 | K32: 1156 | L32: 219 | M32: 20 | N32: школа-интернат, отделение связи, администрация, д/сад и др | O32: NULL | P32: NULL | Q32: NULL | R32: NULL | S32: дамба | T32: =F32 -> Ымыяхтах
A33: 30 | C33: 1. Риск весеннего половодья | D33: =VLOOKUP(G33,ОКТМО!B:G,6,0) -> Намский муниципальный район | E33: Лена | F33: =VLOOKUP(G33,ОКТМО!B:M,12,0) -> Партизан | G33: 98635435101 | H33: =VLOOKUP(G33,ОКТМО!N:R,4,0) -> 62.5861111111111 | I33: =VLOOKUP(G33,ОКТМО!N:R,5,0) -> 129.771111111111 | J33: NULL | K33: NULL | L33: NULL | M33: 12 | N33: администрация, СОШ, д/с, врачебная амбулатория, маслоцех, ветеринарный участок, ДФ «Хомус», музей, баня, дом спорта, отделение связи, контора ЖКХ | O33: NULL | P33: NULL | Q33: NULL | R33: NULL | S33: NULL | T33: =F33 -> Партизан
A34: 31 | C34: 1. Риск весеннего половодья | D34: =VLOOKUP(G34,ОКТМО!B:G,6,0) -> Намский муниципальный район | E34: Лена | F34: =VLOOKUP(G34,ОКТМО!B:M,12,0) -> Никольский | G34: 98635432101 | H34: =VLOOKUP(G34,ОКТМО!N:R,4,0) -> 62.6288888888889 | I34: =VLOOKUP(G34,ОКТМО!N:R,5,0) -> 129.713055555556 | J34: 632 | K34: 982 | L34: 232 | M34: NULL | N34: NULL | O34: NULL | P34: NULL | Q34: NULL | R34: NULL | S34: NULL | T34: =F34 -> Никольский
A35: 32 | C35: 1. Риск весеннего половодья | D35: =VLOOKUP(G35,ОКТМО!B:G,6,0) -> Намский муниципальный район | E35: Лена | F35: =VLOOKUP(G35,ОКТМО!B:M,12,0) -> Хатас | G35: 98635466101 | H35: =VLOOKUP(G35,ОКТМО!N:R,4,0) -> 62.6805555555556 | I35: =VLOOKUP(G35,ОКТМО!N:R,5,0) -> 129.911944444444 | J35: 883 | K35: 108 | L35: 116 | M35: 4 | N35: школа-интернат, д/спорта, администрация, ХВА | O35: NULL | P35: NULL | Q35: 2 | R35: котельные | S35: фактически проживающих | T35: =F35 -> Хатас
A36: 33 | C36: 1. Риск весеннего половодья | D36: =VLOOKUP(G36,ОКТМО!B:G,6,0) -> Намский муниципальный район | E36: Лена | F36: =VLOOKUP(G36,ОКТМО!B:M,12,0) -> Крест-Кытыл | G36: 98635450101 | H36: =VLOOKUP(G36,ОКТМО!N:R,4,0) -> 62.6647222222222 | I36: =VLOOKUP(G36,ОКТМО!N:R,5,0) -> 129.703611111111 | J36: 620 | K36: 898 | L36: 269 | M36: 5 | N36: администрация, клуб, муз. школа, библиотека, мастерская | O36: NULL | P36: NULL | Q36: NULL | R36: NULL | S36: NULL | T36: =F36 -> Крест-Кытыл
A37: 34 | C37: 1. Риск весеннего половодья | D37: =VLOOKUP(G37,ОКТМО!B:G,6,0) -> Намский муниципальный район | E37: Лена | F37: =VLOOKUP(G37,ОКТМО!B:M,12,0) -> Намцы | G37: 98635425101 | H37: =VLOOKUP(G37,ОКТМО!N:R,4,0) -> 62.7186111111111 | I37: =VLOOKUP(G37,ОКТМО!N:R,5,0) -> 129.665 | J37: 925 | K37: 1135 | L37: 227 | M37: 14 | N37: 14 | O37: 1 | P37: участок автодороги | Q37: NULL | R37: NULL | S37: NULL | T37: =F37 -> Намцы
A38: 35 | C38: 1. Риск весеннего половодья | D38: =VLOOKUP(G38,ОКТМО!B:G,6,0) -> Намский муниципальный район | E38: Лена | F38: =VLOOKUP(G38,ОКТМО!B:M,12,0) -> Аппаны | G38: 98635455101 | H38: =VLOOKUP(G38,ОКТМО!N:R,4,0) -> 62.7594444444444 | I38: =VLOOKUP(G38,ОКТМО!N:R,5,0) -> 129.651111111111 | J38: 950 | K38: 1668 | L38: 446 | M38: 7 | N38: СОШ, интернат, 2 д/с, ДК, музыкальная школа, администрация | O38: 2 | P38: участок автодороги | Q38: 5 | R38: котельные | S38: дамба | T38: =F38 -> Аппаны
A39: 36 | C39: 1. Риск весеннего половодья | D39: =VLOOKUP(G39,ОКТМО!B:G,6,0) -> Намский муниципальный район | E39: Лена | F39: =VLOOKUP(G39,ОКТМО!B:M,12,0) -> Графский Берег | G39: 98635455106 | H39: =VLOOKUP(G39,ОКТМО!N:R,4,0) -> 62.7747222222222 | I39: =VLOOKUP(G39,ОКТМО!N:R,5,0) -> 129.689722222222 | J39: 950 | K39: 629 | L39: 163 | M39: 5 | N39: 2 д/с, ЗООШ, клуб, техникум | O39: 1 | P39: участок автодороги | Q39: 2 | R39: котельные | S39: дамба | T39: =F39 -> Графский Берег
A40: 37 | C40: 1. Риск весеннего половодья | D40: =VLOOKUP(G40,ОКТМО!B:G,6,0) -> Намский муниципальный район | E40: Лена | F40: =VLOOKUP(G40,ОКТМО!B:M,12,0) -> Кысыл-Деревня | G40: 98635455111 | H40: =VLOOKUP(G40,ОКТМО!N:R,4,0) -> 62.7830555555556 | I40: =VLOOKUP(G40,ОКТМО!N:R,5,0) -> 129.642222222222 | J40: 950 | K40: 101 | L40: 23 | M40: 2 | N40: МФЦ, ФАП | O40: NULL | P40: NULL | Q40: NULL | R40: NULL | S40: дамба | T40: =F40 -> Кысыл-Деревня
A41: 38 | C41: 1. Риск весеннего половодья | D41: =VLOOKUP(G41,ОКТМО!B:G,6,0) -> Намский муниципальный район | E41: Лена | F41: =VLOOKUP(G41,ОКТМО!B:M,12,0) -> Бютяй-Юрдя | G41: 98635410101 | H41: =VLOOKUP(G41,ОКТМО!N:R,4,0) -> 62.8272222222222 | I41: =VLOOKUP(G41,ОКТМО!N:R,5,0) -> 129.601111111111 | J41: NULL | K41: 91 | L41: 23 | M41: 4 | N41: ФАП, СОШ, д/с, АКЦ | O41: NULL | P41: NULL | Q41: 4 | R41: котельная, АГРС, ТП, ГРП | S41: NULL | T41: =F41 -> Бютяй-Юрдя
A42: 39 | C42: 1. Риск весеннего половодья | D42: =VLOOKUP(G42,ОКТМО!B:G,6,0) -> Намский муниципальный район | E42: Лена | F42: =VLOOKUP(G42,ОКТМО!B:M,12,0) -> Тумул | G42: 98635430101 | H42: =VLOOKUP(G42,ОКТМО!N:R,4,0) -> 62.9025 | I42: =VLOOKUP(G42,ОКТМО!N:R,5,0) -> 129.559722222222 | J42: NULL | K42: 25 | L42: 10 | M42: NULL | N42: NULL | O42: NULL | P42: NULL | Q42: NULL | R42: NULL | S42: NULL | T42: =F42 -> Тумул
A43: 40 | C43: 1. Риск весеннего половодья | D43: =VLOOKUP(G43,ОКТМО!B:G,6,0) -> Намский муниципальный район | E43: Лена | F43: =VLOOKUP(G43,ОКТМО!B:M,12,0) -> Сыгыннах | G43: 98635405101 | H43: =VLOOKUP(G43,ОКТМО!N:R,4,0) -> 63.3677777777778 | I43: =VLOOKUP(G43,ОКТМО!N:R,5,0) -> 129.657777777778 | J43: 771 | K43: 168 | L43: 70 | M43: 5 | N43: ФАП, СОШ, д/с, Центр культуры, администрация | O43: NULL | P43: NULL | Q43: 2 | R43: котельные | S43: дамба | T43: =F43 -> Сыгыннах
A44: 41 | C44: 1. Риск весеннего половодья | D44: =VLOOKUP(G44,ОКТМО!B:G,6,0) -> Нижнеколымский муниципальный район | E44: Колыма | F44: =VLOOKUP(G44,ОКТМО!B:M,12,0) -> Колымское | G44: 98637437101 | H44: =VLOOKUP(G44,ОКТМО!N:R,4,0) -> 68.7277777777778 | I44: =VLOOKUP(G44,ОКТМО!N:R,5,0) -> 158.703611111111 | J44: 1010 | K44: 166 | L44: 47 | M44: 6 | N44: д/с, СОШ, СДК, КУБ, Администрация, почта | O44: NULL | P44: NULL | Q44: NULL | R44: NULL | S44: NULL | T44: =F44 -> Колымское
A45: 42 | C45: 1. Риск весеннего половодья | D45: =VLOOKUP(G45,ОКТМО!B:G,6,0) -> Нижнеколымский муниципальный район | E45: Колыма | F45: =VLOOKUP(G45,ОКТМО!B:M,12,0) -> Походск | G45: 98637424101 | H45: =VLOOKUP(G45,ОКТМО!N:R,4,0) -> 69.0794444444444 | I45: =VLOOKUP(G45,ОКТМО!N:R,5,0) -> 160.969444444444 | J45: NULL | K45: 89 | L45: 14 | M45: NULL | N45: NULL | O45: NULL | P45: NULL | Q45: NULL | R45: NULL | S45: NULL | T45: =F45 -> Походск
A46: 43 | C46: 1. Риск весеннего половодья | D46: =VLOOKUP(G46,ОКТМО!B:G,6,0) -> Олекминский муниципальный район | E46: Тяня | F46: =VLOOKUP(G46,ОКТМО!B:M,12,0) -> Тяня | G46: 98641475101 | H46: =VLOOKUP(G46,ОКТМО!N:R,4,0) -> 59.0555555555556 | I46: =VLOOKUP(G46,ОКТМО!N:R,5,0) -> 119.795277777778 | J46: 550 | K46: 171 | L46: 41 | M46: 4 | N46: администрация, дет. сад, метеоплощадка, вышка Ростелеком | O46: NULL | P46: NULL | Q46: NULL | R46: NULL | S46: NULL | T46: =F46 -> Тяня
A47: 44 | C47: 1. Риск весеннего половодья | D47: =VLOOKUP(G47,ОКТМО!B:G,6,0) -> Олекминский муниципальный район | E47: Олекма | F47: =VLOOKUP(G47,ОКТМО!B:M,12,0) -> Троицк | G47: 98641470101 | H47: =VLOOKUP(G47,ОКТМО!N:R,4,0) -> 60.3513888888889 | I47: =VLOOKUP(G47,ОКТМО!N:R,5,0) -> 120.671666666667 | J47: 1000 | K47: 51 | L47: 27 | M47: NULL | N47: NULL | O47: NULL | P47: NULL | Q47: 1 | R47: котельная | S47: NULL | T47: =F47 -> Троицк
A48: 45 | C48: 1. Риск весеннего половодья | D48: =VLOOKUP(G48,ОКТМО!B:G,6,0) -> Олекминский муниципальный район | E48: Лена | F48: =VLOOKUP(G48,ОКТМО!B:M,12,0) -> Бирюк | G48: 98641445106 | H48: =VLOOKUP(G48,ОКТМО!N:R,4,0) -> 60.2602777777778 | I48: =VLOOKUP(G48,ОКТМО!N:R,5,0) -> 119.646666666667 | J48: NULL | K48: 183 | L48: 47 | M48: NULL | N48: NULL | O48: NULL | P48: NULL | Q48: NULL | R48: NULL | S48: NULL | T48: =F48 -> Бирюк
A49: 46 | C49: 1. Риск весеннего половодья | D49: =VLOOKUP(G49,ОКТМО!B:G,6,0) -> Олекминский муниципальный район | E49: Лена | F49: =VLOOKUP(G49,ОКТМО!B:M,12,0) -> Нерюктяйинск 1-й | G49: 98641445101 | H49: =VLOOKUP(G49,ОКТМО!N:R,4,0) -> 60.2591666666667 | I49: =VLOOKUP(G49,ОКТМО!N:R,5,0) -> 119.669444444444 | J49: 1000 | K49: 497 | L49: 132 | M49: NULL | N49: NULL | O49: NULL | P49: NULL | Q49: NULL | R49: NULL | S49: NULL | T49: =F49 -> Нерюктяйинск 1-й
A50: 47 | C50: 1. Риск весеннего половодья | D50: =VLOOKUP(G50,ОКТМО!B:G,6,0) -> Олекминский муниципальный район | E50: Лена | F50: =VLOOKUP(G50,ОКТМО!B:M,12,0) -> Нерюктяйинск 2-й | G50: 98641450101 | H50: =VLOOKUP(G50,ОКТМО!N:R,4,0) -> 60.2588888888889 | I50: =VLOOKUP(G50,ОКТМО!N:R,5,0) -> 119.889444444444 | J50: NULL | K50: 106 | L50: 38 | M50: NULL | N50: NULL | O50: NULL | P50: NULL | Q50: NULL | R50: NULL | S50: NULL | T50: =F50 -> Нерюктяйинск 2-й
A51: 48 | C51: 1. Риск весеннего половодья | D51: =VLOOKUP(G51,ОКТМО!B:G,6,0) -> Олекминский муниципальный район | E51: Лена | F51: =VLOOKUP(G51,ОКТМО!B:M,12,0) -> Абага центральная | G51: 98641405106 | H51: =VLOOKUP(G51,ОКТМО!N:R,4,0) -> 60.3094444444444 | I51: =VLOOKUP(G51,ОКТМО!N:R,5,0) -> 119.986388888889 | J51: NULL | K51: 233 | L51: 85 | M51: NULL | N51: NULL | O51: 1 | P51: участок республиканской автодороги «Умнас» | Q51: NULL | R51: NULL | S51: NULL | T51: =F51 -> Абага центральная
A52: 49 | C52: 1. Риск весеннего половодья | D52: =VLOOKUP(G52,ОКТМО!B:G,6,0) -> Олекминский муниципальный район | E52: Лена | F52: =VLOOKUP(G52,ОКТМО!B:M,12,0) -> Хоринцы | G52: 98641485101 | H52: =VLOOKUP(G52,ОКТМО!N:R,4,0) -> 60.6652777777778 | I52: =VLOOKUP(G52,ОКТМО!N:R,5,0) -> 121.442777777778 | J52: 1000 | K52: 217 | L52: 54 | M52: NULL | N52: NULL | O52: NULL | P52: NULL | Q52: 1 | R52: котельная | S52: NULL | T52: =F52 -> Хоринцы
A53: 50 | C53: 1. Риск весеннего половодья | D53: =VLOOKUP(G53,ОКТМО!B:G,6,0) -> Олекминский муниципальный район | E53: Лена | F53: =VLOOKUP(G53,ОКТМО!B:M,12,0) -> Кыллах | G53: 98641430101 | H53: =VLOOKUP(G53,ОКТМО!N:R,4,0) -> 60.20832002 | I53: =VLOOKUP(G53,ОКТМО!N:R,5,0) -> 119.93807636 | J53: 1000 | K53: 68 | L53: 32 | M53: 1 | N53: 1 клуб, 1 молокоприемный пункт | O53: NULL | P53: NULL | Q53: 1 | R53: котельная клуба | S53: данный нп ранее был выведен из зоны затопления | T53: =F53 -> Кыллах
A54: 51 | C54: 1. Риск весеннего половодья | D54: =VLOOKUP(G54,ОКТМО!B:G,6,0) -> Оленекский эвенкийский национальный муниципальный район | E54: Оленек | F54: =VLOOKUP(G54,ОКТМО!B:M,12,0) -> Оленек | G54: 98642437101 | H54: =VLOOKUP(G54,ОКТМО!N:R,4,0) -> 68.50318568 | I54: =VLOOKUP(G54,ОКТМО!N:R,5,0) -> 112.44887109 | J54: 1350 | K54: 93 | L54: 17 | M54: NULL | N54: NULL | O54: NULL | P54: NULL | Q54: NULL | R54: NULL | S54: NULL | T54: =F54 -> Оленек
A55: 52 | C55: 1. Риск весеннего половодья | D55: =VLOOKUP(G55,ОКТМО!B:G,6,0) -> Среднеколымский муниципальный район | E55: Колыма | F55: =VLOOKUP(G55,ОКТМО!B:M,12,0) -> Среднеколымск | G55: 98646101001 | H55: =VLOOKUP(G55,ОКТМО!N:R,4,0) -> 67.4591666666667 | I55: =VLOOKUP(G55,ОКТМО!N:R,5,0) -> 153.711388888889 | J55: 1200 | K55: 368 | L55: NULL | M55: NULL | N55: NULL | O55: NULL | P55: NULL | Q55: NULL | R55: NULL | S55: NULL | T55: =F55 -> Среднеколымск
A56: 53 | C56: 1. Риск весеннего половодья | D56: =VLOOKUP(G56,ОКТМО!B:G,6,0) -> Среднеколымский муниципальный район | E56: Березовка | F56: =VLOOKUP(G56,ОКТМО!B:M,12,0) -> Березовка | G56: 98646415101 | H56: =VLOOKUP(G56,ОКТМО!N:R,4,0) -> 67.1319444444444 | I56: =VLOOKUP(G56,ОКТМО!N:R,5,0) -> 156.583055555556 | J56: 1000 | K56: 11 | L56: 3 | M56: 3 | N56: д/с, КДЦ, администрация | O56: NULL | P56: NULL | Q56: 1 | R56: котельная | S56: решение о переносе населенного пункта | T56: =F56 -> Березовка
A57: 54 | C57: 1. Риск весеннего половодья | D57: =VLOOKUP(G57,ОКТМО!B:G,6,0) -> Среднеколымский муниципальный район | E57: Колыма | F57: =VLOOKUP(G57,ОКТМО!B:M,12,0) -> Налимск | G57: 98646410101 | H57: =VLOOKUP(G57,ОКТМО!N:R,4,0) -> 67.5841666666667 | I57: =VLOOKUP(G57,ОКТМО!N:R,5,0) -> 153.645 | J57: 1250 | K57: 71 | L57: 47 | M57: 4 | N57: 4 | O57: NULL | P57: NULL | Q57: 1 | R57: 1 | S57: NULL | T57: =F57 -> Налимск
A58: 55 | C58: 1. Риск весеннего половодья | D58: =VLOOKUP(G58,ОКТМО!B:G,6,0) -> Таттинский муниципальный район | E58: Амга | F58: =VLOOKUP(G58,ОКТМО!B:M,12,0) -> Дайа-Амгата | G58: 98604418101 | H58: =VLOOKUP(G58,ОКТМО!N:R,4,0) -> 61.9091666666667 | I58: =VLOOKUP(G58,ОКТМО!N:R,5,0) -> 133.611388888889 | J58: 1200 | K58: 257 | L58: 54 | M58: 1 | N58: СОШ | O58: NULL | P58: NULL | Q58: NULL | R58: NULL | S58: NULL | T58: =F58 -> Дайа-Амгата
A59: 56 | C59: 1. Риск весеннего половодья | D59: =VLOOKUP(G59,ОКТМО!B:G,6,0) -> Таттинский муниципальный район | E59: Амга | F59: =VLOOKUP(G59,ОКТМО!B:M,12,0) -> Харбалах | G59: 98604440101 | H59: =VLOOKUP(G59,ОКТМО!N:R,4,0) -> 62.1975 | I59: =VLOOKUP(G59,ОКТМО!N:R,5,0) -> 134.249722222222 | J59: 1107 | K59: 103 | L59: 40 | M59: 6 | N59: 6 | O59: 2 | P59: Харбалахский угольный разрез, участок автодороги | Q59: NULL | R59: NULL | S59: NULL | T59: =F59 -> Харбалах
A60: 57 | C60: 1. Риск весеннего половодья | D60: =VLOOKUP(G60,ОКТМО!B:G,6,0) -> Таттинский муниципальный район | E60: Амга | F60: =VLOOKUP(G60,ОКТМО!B:M,12,0) -> Чымнайи | G60: 98604460101 | H60: =VLOOKUP(G60,ОКТМО!N:R,4,0) -> 62.2466666666667 | I60: =VLOOKUP(G60,ОКТМО!N:R,5,0) -> 134.538055555556 | J60: 1213 | K60: 496 | L60: 121 | M60: 7 | N60: 7 | O60: 1 | P60: участок автодороги | Q60: NULL | R60: NULL | S60: дамба | T60: =F60 -> Чымнайи
A61: 58 | C61: 1. Риск весеннего половодья | D61: =VLOOKUP(G61,ОКТМО!B:G,6,0) -> Таттинский муниципальный район | E61: Алдан | F61: =VLOOKUP(G61,ОКТМО!B:M,12,0) -> Хара-Алдан | G61: 98604465101 | H61: =VLOOKUP(G61,ОКТМО!N:R,4,0) -> 63.2608333333333 | I61: =VLOOKUP(G61,ОКТМО!N:R,5,0) -> 133.225277777778 | J61: 1488 | K61: 116 | L61: 72 | M61: 3 | N61: 3 | O61: 1 | P61: участок автодороги | Q61: 3 | R61: 3 | S61: NULL | T61: =F61 -> Хара-Алдан
A62: 59 | C62: 1. Риск весеннего половодья | D62: =VLOOKUP(G62,ОКТМО!B:G,6,0) -> Томпонский муниципальный район | E62: Алдан | F62: =VLOOKUP(G62,ОКТМО!B:M,12,0) -> Джебарики-Хая | G62: 98650152051 | H62: =VLOOKUP(G62,ОКТМО!N:R,4,0) -> 62.2169444444444 | I62: =VLOOKUP(G62,ОКТМО!N:R,5,0) -> 135.859444444444 | J62: 1260 | K62: 24 | L62: 28 | M62: NULL | N62: NULL | O62: NULL | P62: NULL | Q62: NULL | R62: NULL | S62: NULL | T62: =F62 -> Джебарики-Хая
A63: 60 | C63: 1. Риск весеннего половодья | D63: =VLOOKUP(G63,ОКТМО!B:G,6,0) -> Томпонский муниципальный район | E63: Алдан | F63: =VLOOKUP(G63,ОКТМО!B:M,12,0) -> Хандыга | G63: 98650151051 | H63: =VLOOKUP(G63,ОКТМО!N:R,4,0) -> 62.6533333333333 | I63: =VLOOKUP(G63,ОКТМО!N:R,5,0) -> 135.559166666667 | J63: 1000 | K63: 271 | L63: 86 | M63: 9 | N63: 9 | O63: NULL | P63: NULL | Q63: 11 | R63: 2 ГУП «ЖКХ РС(Я)», 9 ТП | S63: NULL | T63: =F63 -> Хандыга
A64: 61 | C64: 1. Риск весеннего половодья | D64: =VLOOKUP(G64,ОКТМО!B:G,6,0) -> Томпонский муниципальный район | E64: Алдан | F64: =VLOOKUP(G64,ОКТМО!B:M,12,0) -> Кескил | G64: 98650430101 | H64: =VLOOKUP(G64,ОКТМО!N:R,4,0) -> 62.6516666666667 | I64: =VLOOKUP(G64,ОКТМО!N:R,5,0) -> 135.007777777778 | J64: 815 | K64: 360 | L64: 178 | M64: 6 | N64: д/с, СОШ, администрация, КЦ, почта, ФАП | O64: NULL | P64: NULL | Q64: 3 | R64: котельная уч. Кескил ТФ ГУП «ЖКХ РС (Я)», 2 ТП | S64: дамба | T64: =F64 -> Кескил
A65: 62 | C65: 1. Риск весеннего половодья | D65: =VLOOKUP(G65,ОКТМО!B:G,6,0) -> Томпонский муниципальный район | E65: Алдан | F65: =VLOOKUP(G65,ОКТМО!B:M,12,0) -> Мегино-Алдан | G65: 98650415101 | H65: =VLOOKUP(G65,ОКТМО!N:R,4,0) -> 62.6994444444444 | I65: =VLOOKUP(G65,ОКТМО!N:R,5,0) -> 134.613611111111 | J65: 700 | K65: 150 | L65: 167 | M65: NULL | N65: NULL | O65: NULL | P65: NULL | Q65: 2 | R65: водозабор, ТП | S65: NULL | T65: =F65 -> Мегино-Алдан
A66: 63 | C66: 1. Риск весеннего половодья | D66: =VLOOKUP(G66,ОКТМО!B:G,6,0) -> Верхоянский муниципальный район | E66: Алдан | F66: =VLOOKUP(G66,ОКТМО!B:M,12,0) -> Сайды | G66: 98616464101 | H66: =VLOOKUP(G66,ОКТМО!N:R,4,0) -> 68.6972222222222 | I66: =VLOOKUP(G66,ОКТМО!N:R,5,0) -> 134.464722222222 | J66: 950 | K66: 90 | L66: 60 | M66: 1 | N66: СКЦ | O66: NULL | P66: NULL | Q66: NULL | R66: NULL | S66: NULL | T66: =F66 -> Сайды
A67: 64 | C67: 1. Риск весеннего половодья | D67: =VLOOKUP(G67,ОКТМО!B:G,6,0) -> Томпонский муниципальный район | E67: Алдан | F67: =VLOOKUP(G67,ОКТМО!B:M,12,0) -> Новый | G67: 98650440101 | H67: =VLOOKUP(G67,ОКТМО!N:R,4,0) -> 62.5883333333333 | I67: =VLOOKUP(G67,ОКТМО!N:R,5,0) -> 135.527222222222 | J67: 950 | K67: 250 | L67: 50 | M67: 6 | N67: СОШ, д/с, интернат СОШ, ФАП, КСК, администрация | O67: NULL | P67: NULL | Q67: 3 | R67: котельная, водозабор, ТП | S67: NULL | T67: =F67 -> Новый
A68: 65 | C68: 1. Риск весеннего половодья | D68: =VLOOKUP(G68,ОКТМО!B:G,6,0) -> Томпонский муниципальный район | E68: Алдан | F68: =VLOOKUP(G68,ОКТМО!B:M,12,0) -> Охотский-Перевоз | G68: 98650425101 | H68: =VLOOKUP(G68,ОКТМО!N:R,4,0) -> 61.8775 | I68: =VLOOKUP(G68,ОКТМО!N:R,5,0) -> 135.527777777778 | J68: 1190 | K68: 42 | L68: 14 | M68: NULL | N68: NULL | O68: NULL | P68: NULL | Q68: NULL | R68: NULL | S68: NULL | T68: =F68 -> Охотский-Перевоз
A69: 66 | C69: 1. Риск весеннего половодья | D69: =VLOOKUP(G69,ОКТМО!B:G,6,0) -> Усть-Алданский муниципальный район | E69: Алдан | F69: =VLOOKUP(G69,ОКТМО!B:M,12,0) -> Кылайы | G69: 98652475101 | H69: =VLOOKUP(G69,ОКТМО!N:R,4,0) -> 63.2283333333333 | I69: =VLOOKUP(G69,ОКТМО!N:R,5,0) -> 132.12 | J69: 1115 | K69: 302 | L69: 71 | M69: 2 | N69: СОШ, д/с | O69: 1 | P69: участок автодороги | Q69: 1 | R69: котельная | S69: NULL | T69: =F69 -> Кылайы
A70: 67 | C70: 1. Риск весеннего половодья | D70: =VLOOKUP(G70,ОКТМО!B:G,6,0) -> Усть-Алданский муниципальный район | E70: Алдан | F70: =VLOOKUP(G70,ОКТМО!B:M,12,0) -> Чериктей | G70: 98652485101 | H70: =VLOOKUP(G70,ОКТМО!N:R,4,0) -> 63.2327777777778 | I70: =VLOOKUP(G70,ОКТМО!N:R,5,0) -> 130.989444444444 | J70: 1062 | K70: 318 | L70: 82 | M70: 4 | N70: СОШ, д/с, больница, администрация | O70: 1 | P70: участок автодороги | Q70: 1 | R70: котельная | S70: NULL | T70: =F70 -> Чериктей
A71: 68 | C71: 1. Риск весеннего половодья | D71: =VLOOKUP(G71,ОКТМО!B:G,6,0) -> Усть-Алданский муниципальный район | E71: Алдан | F71: =VLOOKUP(G71,ОКТМО!B:M,12,0) -> Дыгдал | G71: 98652465101 | H71: =VLOOKUP(G71,ОКТМО!N:R,4,0) -> 63.3044444444444 | I71: =VLOOKUP(G71,ОКТМО!N:R,5,0) -> 130.379166666667 | J71: 1149 | K71: 107 | L71: 137 | M71: NULL | N71: NULL | O71: 1 | P71: участок автодороги | Q71: 1 | R71: котельная | S71: NULL | T71: =F71 -> Дыгдал
